Workbook

Sheet Sources
A1: Sources brutes : postes de consommation sans vente, hors cuisine et hors alcool des menus (3 exercices)
A2: Litres par poste repris de R1-abattements-double-emploi.xlsx, onglet 2 (colonne E = total 3 exercices). Euros R1 = colonne I du meme onglet. La valorisation de la consommation du chef est reprise de R1-consommation-personnel.xlsx, onglet 1 : Macvin 8 109,83 EUR (CA equivalent determinable) ; le Picon (43,7 L) n'a aucun prix de revente propre en caisse (onglet 1, A13) : CA equivalent non determinable. La contenance d'articles mixtes de biere (295,99 L) et les offerts deja enregistres a 0 EUR (25,75 L) ont deja ete retires en amont (R1-cascade-doubles-comptages.csv).
A4: Poste | B4: Litres (3 ex.) | C4: Euros R1 (3 ex.) | D4: Deja compte ailleurs ? | E4: Euros retenus | G4: Source / base de calcul
A5: Consommation du chef (Picon + Macvin) | B5: 143 | C5: 14575 | D5: Non | E5: =8109.83 -> 8109.83 | G5: R1-consommation-personnel.xlsx o.1 : Macvin 8 109,83 EUR ; Picon non determinable
A6: Offerts non enregistres en caisse | B6: 14 | C6: 1281 | D6: Non | E6: =1281 -> 1281 | G6: R1-abattements o.2 L6/I6 (91,71 EUR/L apero) ; net des 25,75 L deja vendus
A7: Cafes offerts (sans alcool) | B7: 0 | C7: 4369 | D7: Non | E7: =4369 -> 4369 | G7: R1-abattements o.2 L7/I7 (3 cafes/j x 662 j, fichier 56)
A8: Sur-versement au verre | B8: 460.6 | C8: 42184 | D8: OUI - vin servi et facture | E8: =0 -> 0 | G8: R1-abattements o.2 L8/I8 : vin parti dans un verre facture, deja dans le CA au verre reconstitue
A9: Cremant non vendu | B9: 272 | C9: 8841 | D9: Non | E9: =8841 -> 8841 | G9: R1-abattements o.2 L9/I9 (32,50 EUR/L)
A10: Degustation offerte | B10: 125.8 | C10: 6045 | D10: Non | E10: =6045 -> 6045 | G10: R1-abattements o.2 L10/I10 (48,04 EUR/L)
A11: Freinte technique de la biere | B11: 120.5 | C11: 1880 | D11: Non | E11: =1880 -> 1880 | G11: R1-abattements o.2 L11/I11 (15,60 EUR/L fut Affligem)
A12: Sur-versement requalifie en consommation sans vente (ecart de verrouillage 483 -> 460,6 L) | B12: 22.1 | D12: Non | E12: =0 -> 0 | G12: Ecart entre l'ancien chiffrage (483 L) et le sur-versement verrouille a 460,6 L : volume non facture, demeure en consommation sans vente ; cale l'itemisation brute documentee a 1 158 L
A13: Base de comparaison : achats d'alcool et forfait du service
A14: Alcool achete sur les 3 exercices (L) | B14: 10622 | G14: R1-abattements o.3 B23 ; cascade des 10 622 L
A15: Taux du forfait du service | B15: 0.15 | G15: 5 % offerts + 5 % pertes + 5 % conso personnel (proposition p. 51-52)
A16: Forfait du service en CA boissons - ex.1 (EUR) | B16: 26751.21 | G16: R1-abattements o.3 B7 (5%x3 sur liquides 178 341,42)
A17: Forfait du service en CA boissons - ex.2 (EUR) | B17: 25352.16 | G17: R1-abattements o.3 C7
A18: Forfait du service en CA boissons - ex.3 (EUR) | B18: 24759.81 | G18: R1-abattements o.3 D7

Sheet Calcul
A1: Recalcul par formule : itemisation nette vs forfait du service
A2: Toutes les cellules de resultat ci-dessous sont des formules (=) operant sur l'onglet Sources. Aucun total n'est saisi en dur.
A4: Grandeur | B4: Litres | C4: Part du forfait | D4: EUR (indicatif) | E4: Note
A5: Forfait du service, exprime en volume (15 % des achats) | B5: =Sources!B14*Sources!B15 -> 1593.3 | C5: =Sources!B15 -> 0.15 | D5: =Sources!B16+Sources!B17+Sources!B18 -> 76863.18 | E5: Reference : le forfait, ramene aux achats d'alcool et au CA boissons
A6: Itemisation documentee, hors cuisine et menus (brute) | B6: =SUM(Sources!B5:B12) -> 1158 | C6: =B6/B5 -> 0.72679345 | D6: =SUM(Sources!C5:C12) -> 79175 | E6: Somme des 7 postes (colonne Litres de l'onglet Sources)
A7: dont sur-versement au verre, deja facture au client (a retirer) | B7: =-Sources!B8 -> -460.6 | C7: =B7/B5 -> -0.28908555 | D7: =-Sources!C8 -> -42184 | E7: Vin servi dans un verre paye : deja dans le CA au verre reconstitue (double emploi)
A8: Itemisation NETTE de consommation sans vente (hors cuisine, menus et sur-versement) | B8: =B6+B7 -> 697.4 | C8: =B8/B5 -> 0.4377079 | D8: =SUM(Sources!E5:E12) -> 30525.83 | E8: Total NET unique : seul chiffre a opposer au forfait
A9: Pour memoire (NON ajoute) : alcool de cuisine et des menus, deja vendu dans les menus | B9: 741 | C9: =B9/B5 -> 0.46507249 | D9: hors perimetre | E9: L'ajouter au total ferait un double emploi (menus deja reconstitues) : ecarte
A11: Conclusion chiffree
A12: Le forfait couvre, en volume, l'itemisation brute a hauteur de : | B12: =B6/B5 -> 0.72679345
A13: Le forfait couvre, en volume, l'itemisation nette a hauteur de : | B13: =B8/B5 -> 0.4377079
A14: Marge du forfait au-dela de l'itemisation nette (L) : | B14: =B5-B8 -> 895.9
A15: Marge du forfait au-dela de l'itemisation nette (EUR boissons) : | B15: =D5-D8 -> 46337.35

Sheet Methode
A1: Methode et sources, etape par etape
A3: Objet
A4: Comparer, dans une unite commune, le forfait de 15 % du service et la consommation sans vente que la defense peut reellement documenter, hors cuisine et hors alcool des menus.
A6: 1. Perimetre
A7: On exclut la cuisine et l'alcool des menus : ces volumes correspondent a des plats et menus qui ont ete VENDUS, donc deja compris dans le chiffre d'affaires reconstitue. Les y compter comme consommation sans vente serait un double emploi.
A9: 2. Litres par poste
A10: Repris de R1-abattements-double-emploi.xlsx, onglet 2, colonne E (total 3 exercices). Somme des postes documentes = 1 158 L (itemisation brute) ; le sur-versement est verrouille a 460,6 L (voir etape 3).
A12: 3. Retrait du sur-versement
A13: Le sur-versement au verre, verrouille a 460,6 L (soit 39,8 % de l'itemisation brute), est du vin parti dans un verre facture au client : ce n'est pas de la consommation sans vente et il figure deja dans le CA au verre reconstitue. Retire, l'itemisation nette tombe a 697,4 L. Les 22,1 L d'ecart avec l'ancien chiffrage (483 L) ne sont plus traites comme deja factures et demeurent en consommation sans vente.
A15: 4. Chiffre abandonne
A16: Le volume de 1 505 L (memoire du 10/07/2026) n'est pas repris : il double-comptait la contenance d'articles mixtes de biere (295,99 L) et des offerts deja enregistres a 0 EUR dans les ventes (25,75 L), d'apres R1-cascade-doubles-comptages.csv. Il n'est pas reproductible et est ecarte.
A18: 5. Forfait
... A31: Les annexes caisse primaires ne sont disponibles que pour 2022-2023. La ventilation des litres sur 2023-2024 et 2024-2025 repose sur un prorata des jours d'ouverture (222 / 221 / 219 j). La demonstration en volume est robuste sur l'agregat des trois exercices.
