Workbook

Sheet Sources
A1: Sources - cuisine a la carte (hors menus). Donnees copiees de R1-alcool-cuisine-controles.xlsx (onglet 3) et R1-alcool-cuisine-reperes.xlsx (onglet 2).
A3: Alcool | B3: Carte ex1 (L) | C3: Carte ex2 (L) | D3: Carte ex3 (L) | E3: Menus ex1 (L) | F3: Menus ex2 (L) | G3: Menus ex3 (L) | H3: Deja retranche service ex1 (L) | I3: ex2 | J3: ex3 | K3: Plafond achats ex1 (L) | L3: ex2 | M3: ex3
A4: Ravelin | B4: 51.7 | C4: 47 | D4: 53.2 | E4: 25 | F4: 39.8 | G4: 35.1 | H4: 162.32 | I4: 162.57 | J4: 155.54
A5: Macvin | B5: 36.14 | C5: 42.7 | D5: 44.32 | E5: 24.65 | F5: 14.38 | G5: 15.32 | H5: 77.74 | I5: 88.32 | J5: 74.06
A6: Vin jaune | B6: 39.39 | C6: 40.38 | D6: 33.65 | E6: 3.73 | F6: 3.5 | G6: 3.83 | H6: 37.17 | I6: 36.93 | J6: 37.48
A7: Calvados | B7: 36 | C7: 35.52 | D7: 35.02 | E7: 5.27 | F7: 3.84 | G7: 3.42 | H7: 33.1 | I7: 30.02 | J7: 30.05 | K7: 32 | L7: 22 | M7: 19
A8: Porto | B8: 16.32 | C8: 21.99 | D8: 21.84 | E8: 2.65 | F8: 3.69 | G8: 4.25 | H8: 3.98 | I8: 5.83 | J8: 5.56 | K8: 16.5 | L8: 51.8 | M8: 46.5
A9: Creme cassis | B9: 0.32 | C9: 1.48 | D9: 1 | E9: 5.3 | F9: 5.39 | G9: 5.18 | H9: 10.64 | I9: 11.32 | J9: 11.32
A10: Bailey's | B10: 0.28 | C10: 0.48 | D10: 0.16 | E10: 0 | F10: 6.86 | G10: 7.5 | H10: 0 | I10: 0 | J10: 0
A11: Grand Marnier | B11: 3.18 | C11: 2.48 | D11: 1.76 | E11: 0 | F11: 0 | G11: 0 | H11: 0 | I11: 0 | J11: 0 | K11: 2.8 | L11: 1.4 | M11: 6.3
A12: Marc bourgogne | B12: 0 | C12: 0 | D12: 0 | E12: 5.3 | F12: 0.28 | G12: 0 | H12: 0 | I12: 0 | J12: 0
A13: Liqueur poire | B13: 0 | C13: 0 | D13: 0 | E13: 0 | F13: 1.75 | G13: 2.32 | H13: 0 | I13: 0 | J13: 0
A15: Marc de Bourgogne : plafond specifique de 210 cl sortis du stock sur 3 exercices (280 cl factures, code 550252, moins 1 bouteille inventoriee au 31/03/2025). Voir onglet Calcul, ligne Marc.
A16: Ravelin : le service retranche la part cuisine du volume unique des BIB sur les TROIS exercices ; l'annexe 7-1 (p.51) porte le ravelin sur l'exercice 1 (25 bouteilles, 1 875 cl ; ligne 'Fondue Jurassienne 372 x 10 = 3 720'). La premisse 'ex1 = 0 retranche' est donc fausse : supplement ravelin = 0.

Sheet Calcul
A1: Calcul par FORMULE du supplement a la carte (hors menus), exercice par exercice, planche a zero.
A3: Alcool | B3: Demande totale ex1 (carte+menus) | C3: ex2 | D3: ex3 | E3: Demande effective (plafonnee) ex1 | F3: ex2 | G3: ex3 | H3: Supplement ex1 =MAX(0,eff-retranche) | I3: ex2 | J3: ex3 | K3: Supplement 3 ans | L3: Part MENUS (hors perimetre de cette page) | M3: Supplement A LA CARTE (cette page) | O3: menus-supp ex1 | P3: ex2 | Q3: ex3
A4: Ravelin | B4: =Sources!B4+Sources!E4 | C4: =Sources!C4+Sources!F4 | D4: =Sources!D4+Sources!G4 | E4: =B4 | F4: =C4 | G4: =D4 | H4: =MAX(0,E4-Sources!H4) | I4: =MAX(0,F4-Sources!I4) | J4: =MAX(0,G4-Sources!J4) | K4: =SUM(H4:J4) | L4: =SUM(O4:Q4) | M4: =K4-L4 | O4: =MIN(MAX(0,Sources!E4-Sources!H4),H4) | P4: =MIN(MAX(0,Sources!F4-Sources!I4),I4) | Q4: =MIN(MAX(0,Sources!G4-Sources!J4),J4)
A5: Macvin | B5: =Sources!B5+Sources!E5 | C5: =Sources!C5+Sources!F5 | D5: =Sources!D5+Sources!G5 | E5: =B5 | F5: =C5 | G5: =D5 | H5: =MAX(0,E5-Sources!H5) | I5: =MAX(0,F5-Sources!I5) | J5: =MAX(0,G5-Sources!J5) | K5: =SUM(H5:J5) | L5: =SUM(O5:Q5) | M5: =K5-L5 | O5: =MIN(MAX(0,Sources!E5-Sources!H5),H5) | P5: =MIN(MAX(0,Sources!F5-Sources!I5),I5) | Q5: =MIN(MAX(0,Sources!G5-Sources!J5),J5)
A6: Vin jaune | B6: =Sources!B6+Sources!E6 | C6: =Sources!C6+Sources!F6 | D6: =Sources!D6+Sources!G6 | E6: =B6 | F6: =C6 | G6: =D6 | H6: =MAX(0,E6-Sources!H6) | I6: =MAX(0,F6-Sources!I6) | J6: =MAX(0,G6-Sources!J6) | K6: =SUM(H6:J6) | L6: =SUM(O6:Q6) | M6: =K6-L6 | O6: =MIN(MAX(0,Sources!E6-Sources!H6),H6) | P6: =MIN(MAX(0,Sources!F6-Sources!I6),I6) | Q6: =MIN(MAX(0,Sources!G6-Sources!J6),J6)
A7: Calvados | B7: =Sources!B7+Sources!E7 | C7: =Sources!C7+Sources!F7 | D7: =Sources!D7+Sources!G7 | E7: =MIN(B7,Sources!K7) | F7: =MIN(C7,Sources!L7) | G7: =MIN(D7,Sources!M7) | H7: =MAX(0,E7-Sources!H7) | I7: =MAX(0,F7-Sources!I7) | J7: =MAX(0,G7-Sources!J7) | K7: =SUM(H7:J7) | L7: =SUM(O7:Q7) | M7: =K7-L7 | O7: =MIN(MAX(0,Sources!E7-Sources!H7),H7) | P7: =MIN(MAX(0,Sources!F7-Sources!I7),I7) | Q7: =MIN(MAX(0,Sources!G7-Sources!J7),J7)
A8: Porto | B8: =Sources!B8+Sources!E8 | C8: =Sources!C8+Sources!F8 | D8: =Sources!D8+Sources!G8 | E8: =MIN(B8,Sources!K8) | F8: =MIN(C8,Sources!L8) | G8: =MIN(D8,Sources!M8) | H8: =MAX(0,E8-Sources!H8) | I8: =MAX(0,F8-Sources!I8) | J8: =MAX(0,G8-Sources!J8) | K8: =SUM(H8:J8) | L8: =SUM(O8:Q8) | M8: =K8-L8 | O8: =MIN(MAX(0,Sources!E8-Sources!H8),H8) | P8: =MIN(MAX(0,Sources!F8-Sources!I8),I8) | Q8: =MIN(MAX(0,Sources!G8-Sources!J8),J8)
A9: Creme cassis | B9: =Sources!B9+Sources!E9 | C9: =Sources!C9+Sources!F9 | D9: =Sources!D9+Sources!G9 | E9: =B9 | F9: =C9 | G9: =D9 | H9: =MAX(0,E9-Sources!H9) | I9: =MAX(0,F9-Sources!I9) | J9: =MAX(0,G9-Sources!J9) | K9: =SUM(H9:J9) | L9: =SUM(O9:Q9) | M9: =K9-L9 | O9: =MIN(MAX(0,Sources!E9-Sources!H9),H9) | P9: =MIN(MAX(0,Sources!F9-Sources!I9),I9) | Q9: =MIN(MAX(0,Sources!G9-Sources!J9),J9)
A10: Bailey's | B10: =Sources!B10+Sources!E10 | C10: =Sources!C10+Sources!F10 | D10: =Sources!D10+Sources!G10 | E10: =B10 | F10: =C10 | G10: =D10 | H10: =MAX(0,E10-Sources!H10) | I10: =MAX(0,F10-Sources!I10) | J10: =MAX(0,G10-Sources!J10) | K10: =SUM(H10:J10) | L10: =SUM(O10:Q10) | M10: =K10-L10 | O10: =MIN(MAX(0,Sources!E10-Sources!H10),H10) | P10: =MIN(MAX(0,Sources!F10-Sources!I10),I10) | Q10: =MIN(MAX(0,Sources!G10-Sources!J10),J10)
A11: Grand Marnier | B11: =Sources!B11+Sources!E11 | C11: =Sources!C11+Sources!F11 | D11: =Sources!D11+Sources!G11 | E11: =MIN(B11,Sources!K11) | F11: =MIN(C11,Sources!L11) | G11: =MIN(D11,Sources!M11) | H11: =MAX(0,E11-Sources!H11) | I11: =MAX(0,F11-Sources!I11) | J11: =MAX(0,G11-Sources!J11) | K11: =SUM(H11:J11) | L11: =SUM(O11:Q11) | M11: =K11-L11 | O11: =MIN(MAX(0,Sources!E11-Sources!H11),H11) | P11: =MIN(MAX(0,Sources!F11-Sources!I11),I11) | Q11: =MIN(MAX(0,Sources!G11-Sources!J11),J11)
A12: Marc bourgogne | B12: =Sources!B12+Sources!E12 | C12: =Sources!C12+Sources!F12 | D12: =Sources!D12+Sources!G12 | E12: =B12 | F12: =C12 | G12: =D12 | H12: =MAX(0,E12-Sources!H12) | I12: =MAX(0,F12-Sources!I12) | J12: =MAX(0,G12-Sources!J12) | K12: =2.10 | L12: =2.10 | M12: =0 | O12: =MIN(MAX(0,Sources!E12-Sources!H12),H12) | P12: =MIN(MAX(0,Sources!F12-Sources!I12),I12) | Q12: =MIN(MAX(0,Sources!G12-Sources!J12),J12)
A13: Liqueur poire | B13: =Sources!B13+Sources!E13 | C13: =Sources!C13+Sources!F13 | D13: =Sources!D13+Sources!G13 | E13: =B13 | F13: =C13 | G13: =D13 | H13: =MAX(0,E13-Sources!H13) | I13: =MAX(0,F13-Sources!I13) | J13: =MAX(0,G13-Sources!J13) | K13: =SUM(H13:J13) | L13: =SUM(O13:Q13) | M13: =K13-L13 | O13: =MIN(MAX(0,Sources!E13-Sources!H13),H13) | P13: =MIN(MAX(0,Sources!F13-Sources!I13),I13) | Q13: =MIN(MAX(0,Sources!G13-Sources!J13),J13)
A14: TOTAL | K14: =SUM(K4:K13) | L14: =SUM(L4:L13) | M14: =SUM(M4:M13)
A16: La colonne M (supplement A LA CARTE) est le perimetre de cette page. La colonne L (part menus) est traitee dans R2-alcool-plats-menus.xlsx : elle est EXCLUE d'ici pour eviter tout double comptage.

Sheet Euros
A1: Conversion litres -> euros de CA liquides reconstitue (TTC). Prix de vente au verre : ANNEXE-B1_prix-vente-quantite_2022-2023.xls (exercice 2022-2023).
A3: Alcool (supplement a la carte) | B3: Litres | C3: cl/verre | D3: Prix verre TTC (B1) | E3: Prix au cl =prix/cl | F3: CA liquides TTC =litres*100*prix_cl
A4: Vin jaune | B4: 12.9 | C4: 12 | D4: 12 | E4: =D4/C4 | F4: =B4*100*E4
A5: Porto | B5: 52.9 | C5: 6 | D5: 4.2 | E5: =D5/C5 | F5: =B5*100*E5
A6: Bailey's (IVRESSE) | B6: 0.92 | C6: 4 | D6: 5.2 | E6: =D6/C6 | F6: =B6*100*E6
A7: Grand Marnier | B7: 5.96 | D7: prix de vente au verre absent de l'annexe B1 : effet euro non chiffre (limite)
A8: TOTAL CA liquides TTC (hors Grand Marnier) | F8: =SUM(F4:F6)
A10: Ce montant est l'effet sur le CA LIQUIDES reconstitue (TTC), avant application du coefficient liquides/solides et de la TVA par le service. Son exactitude par exercice suppose la communication des annexes 7-1 a 7-3 (prix unitaire reellement applique) et des annexes B des exercices 2023-2024 et 2024-2025, absentes du dossier.

Sheet Methode
A1: METHODE - R2-alcool-cuisine (cuisine A LA CARTE, hors menus)
A3: PERIMETRE. Cette page ne porte QUE l'alcool cuit dans les plats vendus A LA CARTE. L'alcool cuit dans les plats des MENUS au forfait est traite dans R2-alcool-plats-menus.xlsx. Les deux perimetres sont disjoints et s'additionnent, sans recouvrement.
A5: ETAPE 1 - Demande. Pour chaque alcool et chaque exercice, demande = volume carte + volume menus (onglet Sources), chaque terme = nombre de plats vendus en caisse (ANNEXE-D / C) x dose du courriel des dirigeants du 30/03/2026.
A6: ETAPE 2 - Plafonnement. La demande effective est plafonnee aux achats factures (code article, fournisseur FCBS) lorsque la demande les depasse : Calvados, Porto (ex1), Grand Marnier. Marc de Bourgogne : plafond global 210 cl sortis du stock.
A7: ETAPE 3 - Supplement = MAX(0 ; demande effective - deja retranche par le service), calcule EXERCICE PAR EXERCICE et planche a zero (un litre retranche sur un exercice ne neutralise pas un litre cuit sur un autre : les bases sont etablies exercice par exercice).
A8: ETAPE 4 - Separation carte / menus. La part MENUS du supplement (colonne L de l'onglet Calcul) est exclue de cette page et reportee dans R2-alcool-plats-menus.xlsx. Il reste la part A LA CARTE (colonne M).
A10: RESULTAT (onglet Calcul, colonne M) : Vin jaune 12,90 + Porto 52,90 + Bailey's (carte, IVRESSE) 0,92 + Grand Marnier 5,96 = 72,68 L.
A12: RAVELIN = 0. Le service declare avoir retranche 796,43 L de ravelin (480,43 L 'cuisine' + 316 L 'kirs'), dont la part cuisine sur les trois exercices. L'annexe 7-1 (p.51) etablit que le ravelin figure bien dans le volume unique des BIB de l'exercice 1 (25 bouteilles, 1 875 cl) et que le service y retranche la 'Fondue Jurassienne 372 x 10 = 3 720'. La premisse 'nulle sur l'exercice 1' qui soutenait l'ancien chiffre de 76,7 L est donc fausse : le supplement ravelin est nul sur les trois exercices.
A13: MACVIN = 0, CALVADOS = 0, CREME DE CASSIS = 0 : le service en retranche deja, exercice par exercice, davantage que le volume cuit (reperes Q, D et part desserts des cremes).
A15: DOSES - FOURCHETTES. Le courriel du 30/03/2026 donne une fourchette pour deux postes : fondue '9 ou 10 cl', plats flambes 'environ 4 a 5 cl'. On retient la valeur que LE SERVICE retient lui-meme : 10 cl pour la fondue (en-tete repere E, p.66), 4 cl pour le Calvados (repere D) ; pour le Macvin le service a retenu 5 cl (ex1 et ex2) puis 4 cl (ex3). Ces fourchettes sont sans effet sur le supplement de cette page : ravelin, macvin et calvados ont un supplement nul ; seul le vin jaune des fondues subsiste, a 10 cl = la valeur du service.
A16: MACVIN 5 cl : contrairement a l'ancienne redaction ('4 cl partout, sans exception'), le service applique 5 cl au macvin cuisine sur les exercices 1 et 2 (repere Q, annexe 7). Cela AUGMENTE ce qu'il retranche (240 L), donc le supplement macvin reste nul : le point joue en notre faveur.
A18: EUROS (onglet Euros). Effet sur le CA liquides reconstitue (TTC) = litres x 100 x (prix du verre / cl du verre), prix lus dans l'annexe B1 (2022-2023). Grand Marnier non chiffre faute de prix de vente au verre dans B1.
