Workbook

Sheet Sources
A1: Sources - alcool cuit dans les plats DES MENUS. Volumes menus copies de R1-alcool-cuisine-controles.xlsx (onglet 3) ; deja retranche = reperes du service (annexe 7).
A3: Alcool | B3: Menus ex1 (L) | C3: Menus ex2 (L) | D3: Menus ex3 (L) | E3: Deja retranche service ex1 (L) | F3: ex2 | G3: ex3 | H3: Plafond stock/achats (L)
A4: Ravelin | B4: 25 | C4: 39.8 | D4: 35.1 | E4: 162.32 | F4: 162.57 | G4: 155.54
A5: Macvin | B5: 24.65 | C5: 14.38 | D5: 15.32 | E5: 77.74 | F5: 88.32 | G5: 74.06
A6: Vin jaune | B6: 3.73 | C6: 3.5 | D6: 3.83 | E6: 37.17 | F6: 36.93 | G6: 37.48
A7: Calvados | B7: 5.27 | C7: 3.84 | D7: 3.42 | E7: 33.1 | F7: 30.02 | G7: 30.05
A8: Porto | B8: 2.65 | C8: 3.69 | D8: 4.25 | E8: 3.98 | F8: 5.83 | G8: 5.56
A9: Creme cassis | B9: 5.3 | C9: 5.39 | D9: 5.18 | E9: 10.64 | F9: 11.32 | G9: 11.32
A10: Bailey's | B10: 0 | C10: 6.86 | D10: 7.5 | E10: 0 | F10: 0 | G10: 0
A11: Marc bourgogne | B11: 5.3 | C11: 0.28 | D11: 0 | E11: 0 | F11: 0 | G11: 0 | H11: 2.1
A12: Liqueur poire | B12: 0 | C12: 1.75 | D12: 2.32 | E12: 0 | F12: 0 | G12: 0
A14: Ravelin : abandonne. L'annexe 7-1 (p.51) etablit que le service retranche deja 16 232 cl de ravelin sur le seul exercice 1 (dont 'Fondue Jurassienne 372 x 10'), contre 7 670 cl chiffres : supplement nul sur les 3 exercices.
A15: Marc de Bourgogne : plafond global 210 cl (280 cl factures code 550252 moins 1 bouteille en stock au 31/03/2025). Baba au marc = dessert du menu Bourguignon ; marc a la carte = 0.
A16: Probabilite de choix a l'interieur d'un menu : convention uniforme 1/n (non lue en caisse). Sans effet sur ravelin (plat unique) ; pour Bailey's / poire / marc elle encadre le volume (onglet Methode).

Sheet Calcul
A1: Calcul par FORMULE du supplement MENUS, exercice par exercice, planche a zero.
A3: Alcool | B3: Supplement menus ex1 =MAX(0,menus-retranche) | C3: ex2 | D3: ex3 | E3: Supplement menus 3 ans
A4: Ravelin | B4: =MAX(0,Sources!B4-Sources!E4) | C4: =MAX(0,Sources!C4-Sources!F4) | D4: =MAX(0,Sources!D4-Sources!G4) | E4: =SUM(B4:D4)
A5: Macvin | B5: =MAX(0,Sources!B5-Sources!E5) | C5: =MAX(0,Sources!C5-Sources!F5) | D5: =MAX(0,Sources!D5-Sources!G5) | E5: =SUM(B5:D5)
A6: Vin jaune | B6: =MAX(0,Sources!B6-Sources!E6) | C6: =MAX(0,Sources!C6-Sources!F6) | D6: =MAX(0,Sources!D6-Sources!G6) | E6: =SUM(B6:D6)
A7: Calvados | B7: =MAX(0,Sources!B7-Sources!E7) | C7: =MAX(0,Sources!C7-Sources!F7) | D7: =MAX(0,Sources!D7-Sources!G7) | E7: =SUM(B7:D7)
A8: Porto | B8: =MAX(0,Sources!B8-Sources!E8) | C8: =MAX(0,Sources!C8-Sources!F8) | D8: =MAX(0,Sources!D8-Sources!G8) | E8: =SUM(B8:D8)
A9: Creme cassis | B9: =MAX(0,Sources!B9-Sources!E9) | C9: =MAX(0,Sources!C9-Sources!F9) | D9: =MAX(0,Sources!D9-Sources!G9) | E9: =SUM(B9:D9)
A10: Bailey's | B10: =MAX(0,Sources!B10-Sources!E10) | C10: =MAX(0,Sources!C10-Sources!F10) | D10: =MAX(0,Sources!D10-Sources!G10) | E10: =SUM(B10:D10)
A11: Marc bourgogne | B11: =2.10 | C11: 0 | D11: 0 | E11: =2.10
A12: Liqueur poire | B12: =MAX(0,Sources!B12-Sources!E12) | C12: =MAX(0,Sources!C12-Sources!F12) | D12: =MAX(0,Sources!D12-Sources!G12) | E12: =SUM(B12:D12)
A13: TOTAL | E13: =SUM(E4:E12)
A15: Seuls subsistent Bailey's (14,36 L), liqueur de poire (4,07 L) et marc de Bourgogne (2,10 L) = 20,53 L. Les six autres alcools ont un supplement menus nul (le service retranche deja davantage, ou le ravelin est abandonne).

Sheet Euros
A1: Conversion litres -> euros de CA liquides reconstitue (TTC). Prix de vente au verre : ANNEXE-B1 (2022-2023).
A3: Alcool (supplement menus) | B3: Litres | C3: cl/verre | D3: Prix verre TTC (B1) | E3: Prix au cl =prix/cl | F3: CA liquides TTC =litres*100*prix_cl
A4: Bailey's | B4: 14.36 | C4: 4 | D4: 5.2 | E4: =D4/C4 | F4: =B4*100*E4
A5: Liqueur poire | B5: 4.07 | C5: 4 | D5: 5.2 | E5: =D5/C5 | F5: =B5*100*E5
A6: Marc bourgogne | B6: 2.1 | C6: 4 | D6: 6.5 | E6: =D6/C6 | F6: =B6*100*E6
A7: TOTAL CA liquides TTC | F7: =SUM(F4:F6)
A9: Effet sur le CA liquides reconstitue (TTC), avant coefficient liquides/solides et TVA. Prix du verre de l'exercice 2022-2023 (B1) ; les prix des exercices 2023-2024 et 2024-2025 ne figurent pas au dossier (annexes B correspondantes absentes).

Sheet Perimetre
A1: Controle d'absence de double comptage entre les deux pages couplees.
A3: Alcool | B3: A LA CARTE (R2-alcool-cuisine) L | C3: DANS LES MENUS (cette page) L | D3: Total L
A4: Vin jaune | B4: 12.9 | C4: 0 | D4: =B4+C4
A5: Porto | B5: 52.9 | C5: 0 | D5: =B5+C5
A6: Bailey's | B6: 0.92 | C6: 14.36 | D6: =B6+C6
A7: Grand Marnier | B7: 5.96 | C7: 0 | D7: =B7+C7
A8: Marc bourgogne | B8: 0 | C8: 2.1 | D8: =B8+C8
A9: Liqueur poire | B9: 0 | C9: 4.07 | D9: =B9+C9
A10: Ravelin | B10: 0 | C10: 0 | D10: =B10+C10
A11: Macvin | B11: 0 | C11: 0 | D11: =B11+C11
A12: Calvados | B12: 0 | C12: 0 | D12: =B12+C12
A13: Creme cassis | B13: 0 | C13: 0 | D13: =B13+C13
A14: TOTAL | B14: =SUM(B4:B13) | C14: =SUM(C4:C13) | D14: =SUM(D4:D13)
A16: Les deux colonnes sont disjointes : aucun litre n'apparait a la fois en 'carte' et en 'menus'. Le Bailey's figure dans les deux pages pour des portions DISTINCTES (0,92 L de dessert IVRESSE vendu a la carte ; 14,36 L de desserts servis dans les menus) : jamais le meme litre. Total general = 72,68 L (carte) + 20,53 L (menus) = 93,21 L.

Sheet Methode
A1: METHODE - R2-alcool-plats-menus (plats DES MENUS uniquement)
A3: PERIMETRE. Cette page ne porte QUE l'alcool cuit dans les plats servis a l'interieur d'un MENU au forfait. L'alcool cuit dans les plats vendus A LA CARTE est traite dans R2-alcool-cuisine.xlsx. Perimetres disjoints, additifs (voir onglet Perimetre).
A5: ETAPE 1 - Volume menus. Pour chaque alcool et chaque exercice : nombre de menus factures au prix catalogue x dose du courriel du 30/03/2026 x probabilite de choix de l'option dans le menu. La probabilite est une convention uniforme 1/n (n options au meme service), NON lue en caisse (un menu se vend au forfait, le plat choisi n'a pas de ligne de ticket) ; elle vaut 1 pour un plat unique (fondue du menu Dahu).
A6: ETAPE 2 - Supplement menus = MAX(0 ; volume menus - deja retranche par le service), exercice par exercice, planche a zero.
A7: ETAPE 3 - Plafonnement. Marc de Bourgogne ramene a 210 cl (volume sorti du stock sur 3 exercices).
A9: RESULTAT (onglet Calcul) : Bailey's 14,36 + liqueur de poire 4,07 + marc de Bourgogne 2,10 = 20,53 L.
A11: RAVELIN ABANDONNE. L'annexe 7-1 (p.51) etablit que le service retranche deja 16 232 cl de ravelin sur le seul exercice 1, contre 7 670 cl chiffres : supplement nul. (L'ancienne piece R1 imprimait encore 98,14 L parce qu'elle portait le ravelin a 76,7 L sur l'exercice 1 ; retire le ravelin, elle donne 21,44 L, dont 20,53 L de menus.)
A12: MACVIN, CREME DE CASSIS, CALVADOS, VIN JAUNE, PORTO : supplement menus nul. Le service retranche deja, exercice par exercice, plus que le volume cuit dans les menus (reperes D/E/G/Q et part desserts des cremes, pris tels que le service les imprime).
A14: DOUBLE COMPTAGE. Les 20,53 L de cette page ne recoupent AUCUN litre de R2-alcool-cuisine.xlsx : voir onglet Perimetre. Le Bailey's apparait dans les deux pages pour des portions distinctes (0,92 L a la carte, 14,36 L dans les menus).
A16: LIMITES. Le modele de probabilite des menus (bornes 1/n, cartes-periodes) repose sur la piece 54-boissons-4-menus-par-periode.xlsx, non jointe au dossier : les 20,53 L sont donc etayes pour les doses (courriel 30/03) et les achats (annexe 6, factures), mais la ventilation fine des menus par carte-periode appelle la production de cette piece. Prix de vente : annexe B1 (2022-2023) seule disponible.
