Workbook

Sheet Sources
A1: PIECE R2 — COEFFICIENT DE REVENTE : sources brutes (valeurs en dur, citees). Les onglets suivants ne contiennent que des FORMULES renvoyant a ces cellules.
A3: Donnee | B3: Valeur | C3: Unite | D3: Exercice / portee | E3: Source exacte
A4: CA alcool encaisse TVA 20 % | B4: 81911.2 | C4: EUR TTC | D4: 2022-2023 | E4: ANNEXE-D1, bloc LIQUIDE TVA 20 %, ligne de total
A5: CA alcool encaisse TVA 20 % | B5: 88909.01 | C5: EUR TTC | D5: 2023-2024 | E5: ANNEXE-D2, bloc LIQUIDE TVA 20 %, ligne de total
A6: CA alcool encaisse TVA 20 % | B6: 86389.75 | C6: EUR TTC | D6: 2024-2025 | E6: ANNEXE-D3, bloc LIQUIDE TVA 20 %, ligne de total
A7: Cout d'achat de l'alcool (3 ans) | B7: 107924 | C7: EUR HT | D7: globalise 3 ans | E7: Factures fournisseur FCBS (sous-ensemble alcool des achats boissons), releve R1 onglet 3
A8: Alcool achete, volume (3 ans) | B8: 10622 | C8: litres | D8: globalise 3 ans | E8: R1-cascade-bilan-matiere.xlsx, onglet 1, total factures
A9: Cascade - vendu au verre | B9: 5457 | C9: litres | D9: globalise 3 ans | E9: R1-cascade-bilan-matiere, onglet 1 (mesure, annexes C1-C3 hors articles mixtes)
A10: Cascade - vendu en cocktails | B10: 998 | C10: litres | D10: globalise 3 ans | E10: R1-cascade-bilan-matiere, onglet 1 (cocktails caisse x recette carte)
A11: Cout matieres (boisson+nourriture) | B11: 175437 | C11: EUR | D11: 2022-2023 | E11: Proposition p. 34-35 (reproduite p. 56)
A12: Cout matieres (boisson+nourriture) | B12: 183693 | C12: EUR | D12: 2023-2024 | E12: Proposition p. 34-35 (reproduite p. 56)
A13: Cout matieres (boisson+nourriture) | B13: 188539 | C13: EUR | D13: 2024-2025 | E13: Proposition p. 34-35 (reproduite p. 56)
A14: CA reconstitue par le service | B14: 597265 | C14: EUR | D14: 2022-2023 | E14: Proposition p. 52 (reproduite p. 90)
A15: CA reconstitue par le service | B15: 577522 | C15: EUR | D15: 2023-2024 | E15: Proposition p. 52 (reproduite p. 90)
... A18: Taux de perte substitue par le service | B18: 0.15 | C18: part | D18: methode service | E18: Reponse 04/09/2026 p. 59 et 93

Sheet Cascade
A1: Bilan matiere des 10 622 L (R1-cascade-bilan-matiere.xlsx). La part revendue est le SEUL chiffre decisif ; elle est ici DERIVEE par formule.
A3: Poste | B3: Litres | C3: Nature | D3: Part des achats (=formule)
A4: Vendu au verre | B4: 5457 | C4: mesure | D4: =B4/$B$15
A5: Vendu en cocktails | B5: 998 | C5: calcule | D5: =B5/$B$15
A6: Cuisine et alcool des menus | B6: 741 | C6: calcule | D6: =B6/$B$15
A7: Cremant non vendu | B7: 272 | C7: calcule | D7: =B7/$B$15
A8: Sur-versement au verre | B8: 483 | C8: estime | D8: =B8/$B$15
A9: Degustation offerte | B9: 126 | C9: mesure | D9: =B9/$B$15
A10: Freinte technique de la biere | B10: 120 | C10: estime | D10: =B10/$B$15
A11: Consommation du chef | B11: 143 | C11: estime | D11: =B11/$B$15
A12: Offerts non enregistres en caisse | B12: 14 | C12: estime | D12: =B12/$B$15
A13: Stock final | B13: 213 | C13: mesure | D13: =B13/$B$15
A14: Perte pure (casse, evaporation, fonds de verre, rincage) = RESIDU | B14: 2055 | C14: residu | D14: =B14/$B$15
A15: TOTAL achete (controle = doit faire 10 622) | B15: =SUM(B4:B14) | D15: =SUM(D4:D14)
A17: Alcool REVENDU = vendu au verre + vendu en cocktails | B17: =B4+B5
A18: PART REVENDUE = revendu / total achete | B18: =B17/B15

Sheet Coefficient
A1: Du coefficient sur achat revendu au coefficient sur la totalite des achats. Tout est DERIVE par formule des onglets Sources et Cascade.
A3: Grandeur | B3: Formule (en clair) | C3: Resultat | D3: Unite | E3: Commentaire
A4: CA alcool encaisse, 3 ans | C4: =SUM(Sources!B4:B6) | D4: EUR | E4: 81911,20 + 88909,01 + 86389,75 (annexes D)
A5: Cout d'achat de l'alcool, 3 ans | C5: =Sources!B7 | D5: EUR | E5: factures FCBS
A6: Part revendue (onglet Cascade) | C6: =Cascade!B18 | D6: part | E6: soit 6 455 / 10 622
A7: COEF sur la TOTALITE des achats = CA alcool / cout achats | C7: =C4/C5 | D7: ratio | E7: ANCRE FIXE : 257209,96 / 107924 = 2,383251
A8: Cout de l'alcool REVENDU = cout achats x part revendue | C8: =C5*C6 | D8: EUR
A9: COEF sur achat REVENDU = CA alcool / cout revendu | C9: =C4/C8 | D9: ratio | E9: 3,92 globalise 3 ans ; la cascade n'existe qu'en cumul triennal
A10: CONTROLE d'identite = coef revendu x part | C10: =C9*C6 | D10: ratio | E10: doit egaler le coef sur la totalite des achats (2,383251)
A12: Le calcul du service et le meme calcul avec la part mesuree
A13: Lecture | B13: Part retenue | C13: Coef sur achat revendu | D13: Coef sur totalite achats (=produit) | E13: CA alcool implique / 107924
A14: Service p.59/93 : 3,85 x (1-0,15) | B14: =1-Sources!B18 | C14: =Sources!B17 | D14: =C14*B14 | E14: =C5*D14
A15: Meme calcul, coef non arrondi 3,921810 | B15: =1-Sources!B18 | C15: =C9 | D15: =C15*B15 | E15: =C5*D15
A16: Part revendue MESUREE (cascade) : 6 455 L / 10 622 L | B16: =C6 | C16: =C9 | D16: =C16*B16 | E16: =C5*D16
A18: L'ecart 3,2725 -> 2,383251 tient ENTIEREMENT a la part supposee (85 %) vs mesuree (60,77 %) : 0,85 / 0,6076916 = 1,399, soit +39,9 %.

Sheet Confrontation
A1: Test de la page 93 : coef applique au cout des matieres de chaque exercice. Repere service 3,2725 ; repere mesure = coef sur totalite (2,383251).
A3: Exercice | B3: Cout matieres | C3: CA declare | D3: CA reconstitue | E3: CA au repere 3,2725 (=formule) | F3: Ecart recon / 3,2725 | G3: CA au repere mesure (=formule) | H3: Ecart recon / mesure | I3: Ecart declare / mesure
A4: 2022-2023 | B4: =Sources!B11 | C4: 404031 | D4: 597265 | E4: =B4*3.2725 | F4: =D4-E4 | G4: =B4*Coefficient!C7 | H4: =D4-G4 | I4: =C4-G4
A5: 2023-2024 | B5: =Sources!B12 | C5: 438658 | D5: 577522 | E5: =B5*3.2725 | F5: =D5-E5 | G5: =B5*Coefficient!C7 | H5: =D5-G5 | I5: =C5-G5
A6: 2024-2025 | B6: =Sources!B13 | C6: 435525 | D6: 575253 | E6: =B6*3.2725 | F6: =D6-E6 | G6: =B6*Coefficient!C7 | H6: =D6-G6 | I6: =C6-G6
A7: TOTAL 3 ans | B7: =SUM(B4:B6) | C7: =SUM(C4:C6) | D7: =SUM(D4:D6) | E7: =SUM(E4:E6) | F7: =SUM(F4:F6) | G7: =SUM(G4:G6) | H7: =SUM(H4:H6) | I7: =SUM(I4:I6)

Sheet Annuel
A1: Repartition INDICATIVE par exercice du coefficient sur achat revendu. La part revendue (60,77 %) n'est mesuree qu'en cumul 3 ans : la ventilation ci-dessous est un PRORATA des factures d'alcool, pas une mesure annuelle.
A3: Achats d'alcool factures FCBS par exercice (bière + vin/cidre + spiritueux/liqueur, HT brut, src/data/calculsBoissons/achatsBoissonsParPeriode.json)
A4: Exercice | B4: Factures alcool HT brut (EUR) | C4: Part de l exercice (=formule) | D4: Cout alcool retenu 107 924 x part (=formule) | E4: Cout alcool REVENDU = cout x 60,77 % (=formule) | F4: CA alcool encaisse (annexe D, TVA 20 %) | G4: Coef sur achat REVENDU (=formule) | H4: Coef sur la TOTALITE des achats (=formule)
A5: 2022-2023 | B5: 36963.72 | C5: =B5/$B$8 | D5: =Sources!$B$7*C5 | E5: =D5*Cascade!$B$18 | F5: =Sources!B4 | G5: =F5/E5 | H5: =F5/D5
A6: 2023-2024 | B6: 37969.83 | C6: =B6/$B$8 | D6: =Sources!$B$7*C6 | E6: =D6*Cascade!$B$18 | F6: =Sources!B5 | G6: =F6/E6 | H6: =F6/D6
A7: 2024-2025 | B7: 38063 | C7: =B7/$B$8 | D7: =Sources!$B$7*C7 | E7: =D7*Cascade!$B$18 | F7: =Sources!B6 | G7: =F7/E7 | H7: =F7/D7
A8: GLOBALISE 3 ans (seule MESURE) | B8: =SUM(B5:B7) | C8: =SUM(C5:C7) | D8: =SUM(D5:D7) | E8: =SUM(E5:E7) | F8: =SUM(F5:F7) | G8: =F8/E8 | H8: =F8/D8
A10: Lecture : par exercice, le coefficient sur la TOTALITE des achats d'alcool (colonne H) suit les coefficients globaux declares releves par le service p. 56 (2,30 / 2,39 / 2,31) et ceux du memoire du 10/07/2026 pour la boisson (2,35 / 2,49 / 2,44).
A11: Limite : la ligne 8 est la seule mesure (257 209,96 / 65 585 = 3,92 ; 257 209,96 / 107 924 = 2,383251). Les lignes 5 a 7 supposent une part revendue identique chaque annee ; elles ne sont pas opposees comme coefficients annuels mesures.
A12: Ecart 112 996,55 (factures brutes 3 categories) vs 107 924 (cout d'alcool retenu, boissonsPageData.json) : le prorata porte sur les PARTS (col. C), le montant total reste 107 924.

Sheet Tableau p34
A1: Controle arithmetique du tableau du service, proposition du 18/05/2026 p. 34 (repris p. 35 avec le CA reconstitue). Valeurs lues sur la page scannee ; totaux recalcules par formule.
A3: Ligne du tableau p. 34 | B3: Exercice clos 31/03/2023 | C3: Exercice clos 31/03/2024 | D3: Exercice clos 31/03/2025
A4: TOTAL CHIFFRE D AFFAIRES TTC (inclus 706 800 pourboires) | B4: 404030.87 | C4: 438658.43 | D4: 435524.92
A5: Compte 601 100 - Achats denrees | B5: 127473.87 | C5: 137971.41 | D5: 142129.11
A6: Compte 601 200 - Achats boissons | B6: 48237.09 | C6: 46384.45 | D6: 47098.84
A7: Variation stocks denrees (signe du tableau) | B7: 526.38 | C7: -1646.54 | D7: -430.25
A8: Variation stocks boissons (signe du tableau) | B8: -800.83 | C8: -1029.67 | D8: -273.41
A9: Cout d achats des matieres ECRIT par le service | B9: 175436.51 | C9: 183679.65 | D9: 188544.29
A10: Cout d achats RECALCULE = 601100 + 601200 + variations (=formule) | B10: =SUM(B5:B8) | C10: =SUM(C5:C8) | D10: =SUM(D5:D8)
A11: ECART ecrit - recalcule (=formule) : 0 attendu | B11: =B9-B10 | C11: =C9-C10 | D11: =D9-D10
A13: Coefficient declare, tel que le service l ecrit (CA / cout ecrit) | B13: =B4/B9 | C13: =C4/C9 | D13: =D4/D9
A14: Coefficient declare, sur le cout recalcule (=formule) | B14: =B4/B10 | C14: =C4/C10 | D14: =D4/D10
A16: CA reconstitue par le service (p. 35) | B16: 597265.42 | C16: 577522 | D16: 575252.68
A17: Coefficient reconstitue, tel que le service l ecrit (p. 35 : 3,404 / 3,144 / 3,051) | B17: =B16/B9 | C17: =C16/C9 | D17: =D16/D9
A18: Coefficient reconstitue, sur le cout recalcule (=formule) | B18: =B16/B10 | C18: =C16/C10 | D18: =D16/D10
A20: Lecture : sur 2023-2024 le total ecrit (183 679,65) depasse de 2 000,00 EUR la somme de ses propres lignes (181 679,65) ; sur 2024-2025 l ecart est de 20,00 EUR. Le coefficient declare 2023-2024 ressort a 2,414 et non 2,388 ; le reconstitue a 3,179 et non 3,144. Sans incidence sur la demonstration de la page (tests conduits sur les chiffres du service tels quels), mais le tableau fondant le grief ne s additionne pas.

Sheet Methode
A1: METHODE — PIECE R2 COEFFICIENT DE REVENTE
A3: 1. Ancre fixe, non discutable : le coefficient de revente sur la TOTALITE des achats d'alcool = CA alcool encaisse / cout d'achat de l'alcool
A4: = 257 209,96 EUR (somme des trois annexes D, bloc alcool TVA 20 %) / 107 924 EUR (factures FCBS) = 2,383251. Onglet Coefficient, ligne 'COEF sur la TOTALITE'.
A6: 2. Decomposition : coef sur la totalite = coef sur achat REVENDU x part des achats REVENDUE. C'est une identite (l'alcool non revendu n'encaisse rien).
A7: La part revendue est le seul terme a etablir ; elle vient du bilan matiere des 10 622 L (onglet Cascade, R1-cascade-bilan-matiere.xlsx).
A8: Part revendue = (vendu au verre 5 457 L + vendu en cocktails 998 L) / 10 622 L = 6 455 / 10 622 = 60,77 %.
A9: La cascade boucle exactement a 10 622 L (controle onglet Cascade) : aucun litre introuvable.
A11: 3. Il s'ensuit, par formule : cout de l'alcool revendu = 107 924 x 60,77 % = 65 585 EUR ; coef sur achat revendu = 257 209,96 / 65 585 = 3,9218 (arrondi 3,92).
A12: Controle d'identite : 3,9218 x 60,77 % = 2,383251 (egal au coef sur la totalite). L'operation du service 3,85 x (1-0,15) applique la MEME identite avec une part supposee de 85 %.
A14: 4. Une seule valeur circule desormais : part revendue 60,77 % (6 455 L) et coef sur achat revendu 3,92 (3,9218). Les variantes 59,03 % / 6 271 L et 4,04 sont SUPPRIMEES :
A15: elles supposaient 6 271 L revendus, incompatibles avec le bilan matiere (5 457 + 998 = 6 455) et avec l'identite (3,92 x 0,5903 = 2,315, non 2,383251).
A17: 5. Perte pure (casse, evaporation, fonds de verre, rincage) = RESIDU du bilan = 2 055 L = 19,3 % (onglet Cascade). C'est le solde de l'egalite, pas un taux pose.
... A24: (c) les deux reperes sont tires de l'alcool seul, alors que 3,40/3,14/3,05 portent sur la totalite des matieres ; (d) aucun referentiel professionnel externe n'est produit pour un coef global de ~2,30.
