Workbook

Sheet Méthode
A1: Pièce R2 : cas de suppressions « DEL », 89 exemples datés sur les 3 exercices (3 familles)
A2: Source : annexes de caisse remises au titre de l’article L. 47 A, II du LPF : E (tpvevenement, lignes DEL), C (détail des tickets), F (règlements).
A3: Contenu : le fichier des cas (renduFinalCasSuppressions.json) embarqué sur la page du site, un exemple par mois et par famille.
A4: Famille « forfait » (conversion au forfait / facture sans détail) : la somme des suppressions de la rafale = le total exact d’une note encaissée ne contenant que des menus.
A5: Famille « partage » (paiement séparé / partage de table) : l’article supprimé réapparaît divisé (quantités fractionnaires) sur au moins 2 notes encaissées ; la somme des fractions est entière.
A6: Famille « deplacement » (articles déplacés vers la bonne table) : rafale d’au moins 4 suppressions dont la somme = le total exact d’une note détaillée encaissée juste après (au moins une ligne hors menu).
A7: Onglet Exemples : une ligne par exemple ; colonnes « somme DEL » et « total notes » = SUMIF sur les onglets Suppressions et Notes ; « ecart » = différence ; « verdict » = formule.
A8: Onglet Partage_qte : pour chaque exemple de partage et chaque article, somme des quantités sur les notes (SUMIFS) et test d’intégrité (MOD).
A9: Onglet Synthèse : COUNTIF / SUMIF par famille. Aucun chiffre n’est saisi en dur dans la Synthèse.
A10: Arrondis : sur les quantités fractionnaires (0,25 / 0,75), la caisse arrondit chaque ligne au centime ; 6 lignes d’articles sur 1 047 diffèrent de 0,01 € du produit prix x quantité et 4 notes de partage présentent un écart d’arrondi de 0,02 à 0,05 € entre la somme des lignes et le total de caisse (contrôles en bas de la Synthèse). Les identités « somme DEL = total note » et « fractions entières » ne sont pas affectées.
A11: Les 9 exemples ouvrant les familles (2022-04-21, 2022-04-16, 2022-04-24) sont ceux que le service a reproduits p. 4-5 de sa réponse du 04/09/2026 ; le 09/09/2022 (p. 7-15) et le 21/03/2024 (p. 16-17) y figurent aussi.

Sheet Synthèse
A1: Famille | B1: Exemples | C1: dont 2022-2023 | D1: dont 2023-2024 | E1: dont 2024-2025 | F1: Lignes DEL | G1: Somme DEL (€) | H1: Total des notes (€) | I1: Exemples vérifiés (identité exacte) | J1: Exemples en écart
A2: Conversion au forfait (facture sans détail) | B2: =COUNTIF(Exemples!$B$2:$B$90,"forfait") -> 31 | C2: =COUNTIFS(Exemples!$B$2:$B$90,"forfait",Exemples!$C$2:$C$90,"2022-2023") -> 11 | D2: =COUNTIFS(Exemples!$B$2:$B$90,"forfait",Exemples!$C$2:$C$90,"2023-2024") -> 10 | E2: =COUNTIFS(Exemples!$B$2:$B$90,"forfait",Exemples!$C$2:$C$90,"2024-2025") -> 10 | F2: =COUNTIF(Suppressions!$B:$B,"forfait") -> 172 | G2: =ROUND(SUMIF(Suppressions!$B:$B,"forfait",Suppressions!$E:$E),2) -> 2315.5 | H2: =ROUND(SUMIF(Notes!$B:$B,"forfait",Notes!$F:$F),2) -> 2315.5 | I2: =COUNTIFS(Exemples!$B$2:$B$90,"forfait",Exemples!$J$2:$J$90,"somme DEL = total note") -> 31 | J2: =B2-I2 -> 0
A3: Paiement séparé / partage de table | B3: =COUNTIF(Exemples!$B$2:$B$90,"partage") -> 34 | C3: =COUNTIFS(Exemples!$B$2:$B$90,"partage",Exemples!$C$2:$C$90,"2022-2023") -> 12 | D3: =COUNTIFS(Exemples!$B$2:$B$90,"partage",Exemples!$C$2:$C$90,"2023-2024") -> 11 | E3: =COUNTIFS(Exemples!$B$2:$B$90,"partage",Exemples!$C$2:$C$90,"2024-2025") -> 11 | F3: =COUNTIF(Suppressions!$B:$B,"partage") -> 85 | G3: =ROUND(SUMIF(Suppressions!$B:$B,"partage",Suppressions!$E:$E),2) -> 745.8 | H3: =ROUND(SUMIF(Notes!$B:$B,"partage",Notes!$F:$F),2) -> 5440.3 | I3: =COUNTIFS(Exemples!$B$2:$B$90,"partage",Exemples!$J$2:$J$90,"partage entier") -> 34 | J3: =B3-I3 -> 0
A4: Articles déplacés vers la bonne table | B4: =COUNTIF(Exemples!$B$2:$B$90,"deplacement") -> 24 | C4: =COUNTIFS(Exemples!$B$2:$B$90,"deplacement",Exemples!$C$2:$C$90,"2022-2023") -> 10 | D4: =COUNTIFS(Exemples!$B$2:$B$90,"deplacement",Exemples!$C$2:$C$90,"2023-2024") -> 8 | E4: =COUNTIFS(Exemples!$B$2:$B$90,"deplacement",Exemples!$C$2:$C$90,"2024-2025") -> 6 | F4: =COUNTIF(Suppressions!$B:$B,"deplacement") -> 135 | G4: =ROUND(SUMIF(Suppressions!$B:$B,"deplacement",Suppressions!$E:$E),2) -> 1285.9 | H4: =ROUND(SUMIF(Notes!$B:$B,"deplacement",Notes!$F:$F),2) -> 1285.9 | I4: =COUNTIFS(Exemples!$B$2:$B$90,"deplacement",Exemples!$J$2:$J$90,"somme DEL = total note") -> 24 | J4: =B4-I4 -> 0
A5: Total | B5: =SUM(B2:B4) -> 89 | C5: =SUM(C2:C4) -> 33 | D5: =SUM(D2:D4) -> 29 | E5: =SUM(E2:E4) -> 27 | F5: =SUM(F2:F4) -> 392 | G5: =SUM(G2:G4) -> 4347.2 | H5: =SUM(H2:H4) -> 9041.7 | I5: =SUM(I2:I4) -> 89 | J5: =SUM(J2:J4) -> 0
A7: Articles : lignes dont montant = prix unitaire x quantité (contrôle) | B7: =SUM(Articles!$I:$I) -> 1041 | C7: =COUNTA(Articles!$A:$A)-1 -> 1047
A8: Notes : notes dont la somme des articles = total (écart <= 0,01 €) | B8: =COUNTIF(Notes!$I:$I,0) -> 138 | C8: =COUNTA(Notes!$A:$A)-1 -> 142

Sheet Exemples
A1: ex_id | B1: famille | C1: exercice | D1: date | E1: nb suppressions | F1: somme DEL (€) | G1: nb notes | H1: total notes (€) | I1: ecart (€) | J1: verdict | K1: notes (libellés)
A2: forfait-01 | B2: forfait | C2: 2022-2023 | D2: 2022-04-21 | E2: =COUNTIF(Suppressions!$A:$A,A2) -> 3 | F2: =ROUND(SUMIF(Suppressions!$A:$A,A2,Suppressions!$E:$E),2) -> 30.4 | G2: =COUNTIF(Notes!$A:$A,A2) -> 1 | H2: =ROUND(SUMIF(Notes!$A:$A,A2,Notes!$F:$F),2) -> 30.4 | I2: =ROUND(H2-F2,2) -> 0 | J2: =IF(ABS(I2)<=0.01,"somme DEL = total note","écart") -> somme DEL = total note | K2: Note n°17 (12:59) 30.40 €
A3: forfait-02 | B3: forfait | C3: 2022-2023 | D3: 2022-05-04 | E3: =COUNTIF(Suppressions!$A:$A,A3) -> 3 | F3: =ROUND(SUMIF(Suppressions!$A:$A,A3,Suppressions!$E:$E),2) -> 63.6 | G3: =COUNTIF(Notes!$A:$A,A3) -> 1 | H3: =ROUND(SUMIF(Notes!$A:$A,A3,Notes!$F:$F),2) -> 63.6 | I3: =ROUND(H3-F3,2) -> 0 | J3: =IF(ABS(I3)<=0.01,"somme DEL = total note","écart") -> somme DEL = total note | K3: Note n°13 (19:05) 63.60 €
A4: forfait-03 | B4: forfait | C4: 2022-2023 | D4: 2022-06-10 | E4: =COUNTIF(Suppressions!$A:$A,A4) -> 7 | F4: =ROUND(SUMIF(Suppressions!$A:$A,A4,Suppressions!$E:$E),2) -> 76.9 | G4: =COUNTIF(Notes!$A:$A,A4) -> 1 | H4: =ROUND(SUMIF(Notes!$A:$A,A4,Notes!$F:$F),2) -> 76.9 | I4: =ROUND(H4-F4,2) -> 0 | J4: =IF(ABS(I4)<=0.01,"somme DEL = total note","écart") -> somme DEL = total note | K4: Note n°2 (11:59) 76.90 €
A5: forfait-04 | B5: forfait | C5: 2022-2023 | D5: 2022-07-01 | E5: =COUNTIF(Suppressions!$A:$A,A5) -> 5 | F5: =ROUND(SUMIF(Suppressions!$A:$A,A5,Suppressions!$E:$E),2) -> 57.1 | G5: =COUNTIF(Notes!$A:$A,A5) -> 1 | H5: =ROUND(SUMIF(Notes!$A:$A,A5,Notes!$F:$F),2) -> 57.1 | I5: =ROUND(H5-F5,2) -> 0 | J5: =IF(ABS(I5)<=0.01,"somme DEL = total note","écart") -> somme DEL = total note | K5: Note n°17 (19:33) 57.10 €
A6: forfait-05 | B6: forfait | C6: 2022-2023 | D6: 2022-08-09 | E6: =COUNTIF(Suppressions!$A:$A,A6) -> 4 | F6: =ROUND(SUMIF(Suppressions!$A:$A,A6,Suppressions!$E:$E),2) -> 45.6 | G6: =COUNTIF(Notes!$A:$A,A6) -> 1 | H6: =ROUND(SUMIF(Notes!$A:$A,A6,Notes!$F:$F),2) -> 45.6 | I6: =ROUND(H6-F6,2) -> 0 | J6: =IF(ABS(I6)<=0.01,"somme DEL = total note","écart") -> somme DEL = total note | K6: Note n°11 (12:14) 45.60 €
A7: forfait-06 | B7: forfait | C7: 2022-2023 | D7: 2022-09-09 | E7: =COUNTIF(Suppressions!$A:$A,A7) -> 7 | F7: =ROUND(SUMIF(Suppressions!$A:$A,A7,Suppressions!$E:$E),2) -> 76.9 | G7: =COUNTIF(Notes!$A:$A,A7) -> 1 | H7: =ROUND(SUMIF(Notes!$A:$A,A7,Notes!$F:$F),2) -> 76.9 | I7: =ROUND(H7-F7,2) -> 0 | J7: =IF(ABS(I7)<=0.01,"somme DEL = total note","écart") -> somme DEL = total note | K7: Note n°3 (12:08) 76.90 €
A8: forfait-07 | B8: forfait | C8: 2022-2023 | D8: 2022-10-01 | E8: =COUNTIF(Suppressions!$A:$A,A8) -> 2 | F8: =ROUND(SUMIF(Suppressions!$A:$A,A8,Suppressions!$E:$E),2) -> 21.1 | G8: =COUNTIF(Notes!$A:$A,A8) -> 1 | H8: =ROUND(SUMIF(Notes!$A:$A,A8,Notes!$F:$F),2) -> 21.1 | I8: =ROUND(H8-F8,2) -> 0 | J8: =IF(ABS(I8)<=0.01,"somme DEL = total note","écart") -> somme DEL = total note | K8: Note n°26 (19:34) 21.10 €
A9: forfait-08 | B9: forfait | C9: 2022-2023 | D9: 2022-11-03 | E9: =COUNTIF(Suppressions!$A:$A,A9) -> 4 | F9: =ROUND(SUMIF(Suppressions!$A:$A,A9,Suppressions!$E:$E),2) -> 47.7 | G9: =COUNTIF(Notes!$A:$A,A9) -> 1 | H9: =ROUND(SUMIF(Notes!$A:$A,A9,Notes!$F:$F),2) -> 47.7 | I9: =ROUND(H9-F9,2) -> 0 | J9: =IF(ABS(I9)<=0.01,"somme DEL = total note","écart") -> somme DEL = total note | K9: Note n°17 (13:19) 47.70 €
A10: forfait-09 | B10: forfait | C10: 2022-2023 | D10: 2022-12-15 | E10: =COUNTIF(Suppressions!$A:$A,A10) -> 5 | F10: =ROUND(SUMIF(Suppressions!$A:$A,A10,Suppressions!$E:$E),2) -> 53.5 | G10: =COUNTIF(Notes!$A:$A,A10) -> 1 | H10: =ROUND(SUMIF(Notes!$A:$A,A10,Notes!$F:$F),2) -> 53.5 | I10: =ROUND(H10-F10,2) -> 0 | J10: =IF(ABS(I10)<=0.01,"somme DEL = total note","écart") -> somme DEL = total note | K10: Note n°6 (12:31) 53.50 €
A11: forfait-10 | B11: forfait | C11: 2022-2023 | D11: 2023-01-04 | E11: =COUNTIF(Suppressions!$A:$A,A11) -> 4 | F11: =ROUND(SUMIF(Suppressions!$A:$A,A11,Suppressions!$E:$E),2) -> 64.7 | G11: =COUNTIF(Notes!$A:$A,A11) -> 1 | H11: =ROUND(SUMIF(Notes!$A:$A,A11,Notes!$F:$F),2) -> 64.7 | I11: =ROUND(H11-F11,2) -> 0 | J11: =IF(ABS(I11)<=0.01,"somme DEL = total note","écart") -> somme DEL = total note | K11: Note n°4 (12:20) 64.70 €
A12: forfait-11 | B12: forfait | C12: 2022-2023 | D12: 2023-03-22 | E12: =COUNTIF(Suppressions!$A:$A,A12) -> 12 | F12: =ROUND(SUMIF(Suppressions!$A:$A,A12,Suppressions!$E:$E),2) -> 194.3 | G12: =COUNTIF(Notes!$A:$A,A12) -> 1 | H12: =ROUND(SUMIF(Notes!$A:$A,A12,Notes!$F:$F),2) -> 194.3 | I12: =ROUND(H12-F12,2) -> 0 | J12: =IF(ABS(I12)<=0.01,"somme DEL = total note","écart") -> somme DEL = total note | K12: Note n°12 (20:37) 194.30 €
A13: forfait-12 | B13: forfait | C13: 2023-2024 | D13: 2023-05-10 | E13: =COUNTIF(Suppressions!$A:$A,A13) -> 3 | F13: =ROUND(SUMIF(Suppressions!$A:$A,A13,Suppressions!$E:$E),2) -> 38 | G13: =COUNTIF(Notes!$A:$A,A13) -> 1 | H13: =ROUND(SUMIF(Notes!$A:$A,A13,Notes!$F:$F),2) -> 38 | I13: =ROUND(H13-F13,2) -> 0 | J13: =IF(ABS(I13)<=0.01,"somme DEL = total note","écart") -> somme DEL = total note | K13: Note n°12 (18:56) 38.00 €
... A32: forfait-31 | B32: forfait | C32: 2024-2025 | D32: 2025-03-05 | E32: =COUNTIF(Suppressions!$A:$A,A32) -> 6 | F32: =ROUND(SUMIF(Suppressions!$A:$A,A32,Suppressions!$E:$E),2) -> 71.9 | G32: =COUNTIF(Notes!$A:$A,A32) -> 1 | H32: =ROUND(SUMIF(Notes!$A:$A,A32,Notes!$F:$F),2) -> 71.9 | I32: =ROUND(H32-F32,2) -> 0 | J32: =IF(ABS(I32)<=0.01,"somme DEL = total note","écart") -> somme DEL = total note | K32: Note n°20 (19:32) 71.90 €
A33: partage-01 | B33: partage | C33: 2022-2023 | D33: 2022-04-16 | E33: =COUNTIF(Suppressions!$A:$A,A33) -> 4 | F33: =ROUND(SUMIF(Suppressions!$A:$A,A33,Suppressions!$E:$E),2) -> 25.1 | G33: =COUNTIF(Notes!$A:$A,A33) -> 2 | H33: =ROUND(SUMIF(Notes!$A:$A,A33,Notes!$F:$F),2) -> 68.8 | I33: =ROUND(H33-F33,2) -> 43.7 | J33: =IF(COUNTIFS(Partage_qte!$A:$A,A33,Partage_qte!$E:$E,0)=0,"partage entier","fraction non entière") -> partage entier | K33: Note n°23 (20:22) 34.40 € ; Note n°24 (20:22) 34.40 €
A34: partage-02 | B34: partage | C34: 2022-2023 | D34: 2022-05-14 | E34: =COUNTIF(Suppressions!$A:$A,A34) -> 4 | F34: =ROUND(SUMIF(Suppressions!$A:$A,A34,Suppressions!$E:$E),2) -> 48.1 | G34: =COUNTIF(Notes!$A:$A,A34) -> 2 | H34: =ROUND(SUMIF(Notes!$A:$A,A34,Notes!$F:$F),2) -> 113.5 | I34: =ROUND(H34-F34,2) -> 65.4 | J34: =IF(COUNTIFS(Partage_qte!$A:$A,A34,Partage_qte!$E:$E,0)=0,"partage entier","fraction non entière") -> partage entier | K34: Note n°22 (19:35) 56.75 € ; Note n°23 (19:36) 56.75 €
A35: partage-03 | B35: partage | C35: 2022-2023 | D35: 2022-06-25 | E35: =COUNTIF(Suppressions!$A:$A,A35) -> 2 | F35: =ROUND(SUMIF(Suppressions!$A:$A,A35,Suppressions!$E:$E),2) -> 7.7 | G35: =COUNTIF(Notes!$A:$A,A35) -> 4 | H35: =ROUND(SUMIF(Notes!$A:$A,A35,Notes!$F:$F),2) -> 103.7 | I35: =ROUND(H35-F35,2) -> 96 | J35: =IF(COUNTIFS(Partage_qte!$A:$A,A35,Partage_qte!$E:$E,0)=0,"partage entier","fraction non entière") -> partage entier | K35: Note n°25 (20:07) 26.55 € ; Note n°26 (20:07) 26.55 € ; Note n°27 (20:17) 25.30 € ; Note n°28 (20:18) 25.30 €
A36: partage-04 | B36: partage | C36: 2022-2023 | D36: 2022-07-03 | E36: =COUNTIF(Suppressions!$A:$A,A36) -> 4 | F36: =ROUND(SUMIF(Suppressions!$A:$A,A36,Suppressions!$E:$E),2) -> 18 | G36: =COUNTIF(Notes!$A:$A,A36) -> 4 | H36: =ROUND(SUMIF(Notes!$A:$A,A36,Notes!$F:$F),2) -> 154.2 | I36: =ROUND(H36-F36,2) -> 136.2 | J36: =IF(COUNTIFS(Partage_qte!$A:$A,A36,Partage_qte!$E:$E,0)=0,"partage entier","fraction non entière") -> partage entier | K36: Note n°9 (13:08) 42.65 € ; Note n°10 (13:08) 42.65 € ; Note n°12 (13:17) 34.45 € ; Note n°13 (13:17) 34.45 €
A37: partage-05 | B37: partage | C37: 2022-2023 | D37: 2022-08-02 | E37: =COUNTIF(Suppressions!$A:$A,A37) -> 2 | F37: =ROUND(SUMIF(Suppressions!$A:$A,A37,Suppressions!$E:$E),2) -> 7.4 | G37: =COUNTIF(Notes!$A:$A,A37) -> 4 | H37: =ROUND(SUMIF(Notes!$A:$A,A37,Notes!$F:$F),2) -> 212.8 | I37: =ROUND(H37-F37,2) -> 205.4 | J37: =IF(COUNTIFS(Partage_qte!$A:$A,A37,Partage_qte!$E:$E,0)=0,"partage entier","fraction non entière") -> partage entier | K37: Note n°26 (19:31) 71.05 € ; Note n°27 (19:32) 71.05 € ; Note n°29 (19:43) 35.35 € ; Note n°30 (19:43) 35.35 €
A38: partage-06 | B38: partage | C38: 2022-2023 | D38: 2022-09-25 | E38: =COUNTIF(Suppressions!$A:$A,A38) -> 2 | F38: =ROUND(SUMIF(Suppressions!$A:$A,A38,Suppressions!$E:$E),2) -> 9.1 | G38: =COUNTIF(Notes!$A:$A,A38) -> 2 | H38: =ROUND(SUMIF(Notes!$A:$A,A38,Notes!$F:$F),2) -> 66.5 | I38: =ROUND(H38-F38,2) -> 57.4 | J38: =IF(COUNTIFS(Partage_qte!$A:$A,A38,Partage_qte!$E:$E,0)=0,"partage entier","fraction non entière") -> partage entier | K38: Note n°20 (19:49) 38.30 € ; Note n°21 (19:50) 28.20 €
A39: partage-07 | B39: partage | C39: 2022-2023 | D39: 2022-10-22 | E39: =COUNTIF(Suppressions!$A:$A,A39) -> 3 | F39: =ROUND(SUMIF(Suppressions!$A:$A,A39,Suppressions!$E:$E),2) -> 11.1 | G39: =COUNTIF(Notes!$A:$A,A39) -> 2 | H39: =ROUND(SUMIF(Notes!$A:$A,A39,Notes!$F:$F),2) -> 266.2 | I39: =ROUND(H39-F39,2) -> 255.1 | J39: =IF(COUNTIFS(Partage_qte!$A:$A,A39,Partage_qte!$E:$E,0)=0,"partage entier","fraction non entière") -> partage entier | K39: Note n°21 (20:23) 133.10 € ; Note n°22 (20:23) 133.10 €
A40: partage-08 | B40: partage | C40: 2022-2023 | D40: 2022-11-02 | E40: =COUNTIF(Suppressions!$A:$A,A40) -> 3 | F40: =ROUND(SUMIF(Suppressions!$A:$A,A40,Suppressions!$E:$E),2) -> 12 | G40: =COUNTIF(Notes!$A:$A,A40) -> 4 | H40: =ROUND(SUMIF(Notes!$A:$A,A40,Notes!$F:$F),2) -> 253 | I40: =ROUND(H40-F40,2) -> 241 | J40: =IF(COUNTIFS(Partage_qte!$A:$A,A40,Partage_qte!$E:$E,0)=0,"partage entier","fraction non entière") -> partage entier | K40: Note n°25 (20:05) 92.60 € ; Note n°26 (20:06) 92.60 € ; Note n°28 (20:08) 33.90 € ; Note n°29 (20:08) 33.90 €
A41: partage-09 | B41: partage | C41: 2022-2023 | D41: 2022-12-10 | E41: =COUNTIF(Suppressions!$A:$A,A41) -> 2 | F41: =ROUND(SUMIF(Suppressions!$A:$A,A41,Suppressions!$E:$E),2) -> 6.1 | G41: =COUNTIF(Notes!$A:$A,A41) -> 2 | H41: =ROUND(SUMIF(Notes!$A:$A,A41,Notes!$F:$F),2) -> 67.4 | I41: =ROUND(H41-F41,2) -> 61.3 | J41: =IF(COUNTIFS(Partage_qte!$A:$A,A41,Partage_qte!$E:$E,0)=0,"partage entier","fraction non entière") -> partage entier | K41: Note n°6 (13:02) 33.70 € ; Note n°7 (13:03) 33.70 €
A42: partage-10 | B42: partage | C42: 2022-2023 | D42: 2023-01-07 | E42: =COUNTIF(Suppressions!$A:$A,A42) -> 1 | F42: =ROUND(SUMIF(Suppressions!$A:$A,A42,Suppressions!$E:$E),2) -> 7.2 | G42: =COUNTIF(Notes!$A:$A,A42) -> 4 | H42: =ROUND(SUMIF(Notes!$A:$A,A42,Notes!$F:$F),2) -> 161.6 | I42: =ROUND(H42-F42,2) -> 154.4 | J42: =IF(COUNTIFS(Partage_qte!$A:$A,A42,Partage_qte!$E:$E,0)=0,"partage entier","fraction non entière") -> partage entier | K42: Note n°8 (19:12) 31.25 € ; Note n°9 (19:13) 31.25 € ; Note n°11 (19:22) 49.55 € ; Note n°12 (19:22) 49.55 €
A43: partage-11 | B43: partage | C43: 2022-2023 | D43: 2023-02-25 | E43: =COUNTIF(Suppressions!$A:$A,A43) -> 1 | F43: =ROUND(SUMIF(Suppressions!$A:$A,A43,Suppressions!$E:$E),2) -> 8.9 | G43: =COUNTIF(Notes!$A:$A,A43) -> 2 | H43: =ROUND(SUMIF(Notes!$A:$A,A43,Notes!$F:$F),2) -> 156.5 | I43: =ROUND(H43-F43,2) -> 147.6 | J43: =IF(COUNTIFS(Partage_qte!$A:$A,A43,Partage_qte!$E:$E,0)=0,"partage entier","fraction non entière") -> partage entier | K43: Note n°4 (12:18) 78.25 € ; Note n°6 (12:20) 78.25 €
A44: partage-12 | B44: partage | C44: 2022-2023 | D44: 2023-03-11 | E44: =COUNTIF(Suppressions!$A:$A,A44) -> 3 | F44: =ROUND(SUMIF(Suppressions!$A:$A,A44,Suppressions!$E:$E),2) -> 31 | G44: =COUNTIF(Notes!$A:$A,A44) -> 2 | H44: =ROUND(SUMIF(Notes!$A:$A,A44,Notes!$F:$F),2) -> 178.2 | I44: =ROUND(H44-F44,2) -> 147.2 | J44: =IF(COUNTIFS(Partage_qte!$A:$A,A44,Partage_qte!$E:$E,0)=0,"partage entier","fraction non entière") -> partage entier | K44: Note n°5 (13:07) 89.10 € ; Note n°6 (13:07) 89.10 €
... A66: partage-34 | B66: partage | C66: 2024-2025 | D66: 2025-03-05 | E66: =COUNTIF(Suppressions!$A:$A,A66) -> 4 | F66: =ROUND(SUMIF(Suppressions!$A:$A,A66,Suppressions!$E:$E),2) -> 24.3 | G66: =COUNTIF(Notes!$A:$A,A66) -> 2 | H66: =ROUND(SUMIF(Notes!$A:$A,A66,Notes!$F:$F),2) -> 106.1 | I66: =ROUND(H66-F66,2) -> 81.8 | J66: =IF(COUNTIFS(Partage_qte!$A:$A,A66,Partage_qte!$E:$E,0)=0,"partage entier","fraction non entière") -> partage entier | K66: Note n°24 (20:16) 53.05 € ; Note n°25 (20:16) 53.05 €
A67: deplacement-01 | B67: deplacement | C67: 2022-2023 | D67: 2022-04-24 | E67: =COUNTIF(Suppressions!$A:$A,A67) -> 4 | F67: =ROUND(SUMIF(Suppressions!$A:$A,A67,Suppressions!$E:$E),2) -> 73.1 | G67: =COUNTIF(Notes!$A:$A,A67) -> 1 | H67: =ROUND(SUMIF(Notes!$A:$A,A67,Notes!$F:$F),2) -> 73.1 | I67: =ROUND(H67-F67,2) -> 0 | J67: =IF(ABS(I67)<=0.01,"somme DEL = total note","écart") -> somme DEL = total note | K67: Note n°1 (11:54) 73.10 €
A68: deplacement-02 | B68: deplacement | C68: 2022-2023 | D68: 2022-05-25 | E68: =COUNTIF(Suppressions!$A:$A,A68) -> 5 | F68: =ROUND(SUMIF(Suppressions!$A:$A,A68,Suppressions!$E:$E),2) -> 86.45 | G68: =COUNTIF(Notes!$A:$A,A68) -> 1 | H68: =ROUND(SUMIF(Notes!$A:$A,A68,Notes!$F:$F),2) -> 86.45 | I68: =ROUND(H68-F68,2) -> 0 | J68: =IF(ABS(I68)<=0.01,"somme DEL = total note","écart") -> somme DEL = total note | K68: Note n°29 (20:19) 86.45 €
A69: deplacement-03 | B69: deplacement | C69: 2022-2023 | D69: 2022-06-01 | E69: =COUNTIF(Suppressions!$A:$A,A69) -> 8 | F69: =ROUND(SUMIF(Suppressions!$A:$A,A69,Suppressions!$E:$E),2) -> 47.1 | G69: =COUNTIF(Notes!$A:$A,A69) -> 1 | H69: =ROUND(SUMIF(Notes!$A:$A,A69,Notes!$F:$F),2) -> 47.1 | I69: =ROUND(H69-F69,2) -> 0 | J69: =IF(ABS(I69)<=0.01,"somme DEL = total note","écart") -> somme DEL = total note | K69: Note n°5 (12:25) 47.10 €
A70: deplacement-04 | B70: deplacement | C70: 2022-2023 | D70: 2022-07-06 | E70: =COUNTIF(Suppressions!$A:$A,A70) -> 6 | F70: =ROUND(SUMIF(Suppressions!$A:$A,A70,Suppressions!$E:$E),2) -> 31.6 | G70: =COUNTIF(Notes!$A:$A,A70) -> 1 | H70: =ROUND(SUMIF(Notes!$A:$A,A70,Notes!$F:$F),2) -> 31.6 | I70: =ROUND(H70-F70,2) -> 0 | J70: =IF(ABS(I70)<=0.01,"somme DEL = total note","écart") -> somme DEL = total note | K70: Note n°13 (18:10) 31.60 €
A71: deplacement-05 | B71: deplacement | C71: 2022-2023 | D71: 2022-08-11 | E71: =COUNTIF(Suppressions!$A:$A,A71) -> 5 | F71: =ROUND(SUMIF(Suppressions!$A:$A,A71,Suppressions!$E:$E),2) -> 22.95 | G71: =COUNTIF(Notes!$A:$A,A71) -> 1 | H71: =ROUND(SUMIF(Notes!$A:$A,A71,Notes!$F:$F),2) -> 22.95 | I71: =ROUND(H71-F71,2) -> 0 | J71: =IF(ABS(I71)<=0.01,"somme DEL = total note","écart") -> somme DEL = total note | K71: Note n°23 (19:39) 22.95 €
A72: deplacement-06 | B72: deplacement | C72: 2022-2023 | D72: 2022-09-04 | E72: =COUNTIF(Suppressions!$A:$A,A72) -> 7 | F72: =ROUND(SUMIF(Suppressions!$A:$A,A72,Suppressions!$E:$E),2) -> 71.85 | G72: =COUNTIF(Notes!$A:$A,A72) -> 1 | H72: =ROUND(SUMIF(Notes!$A:$A,A72,Notes!$F:$F),2) -> 71.85 | I72: =ROUND(H72-F72,2) -> 0 | J72: =IF(ABS(I72)<=0.01,"somme DEL = total note","écart") -> somme DEL = total note | K72: Note n°24 (20:04) 71.85 €
A73: deplacement-07 | B73: deplacement | C73: 2022-2023 | D73: 2022-10-05 | E73: =COUNTIF(Suppressions!$A:$A,A73) -> 4 | F73: =ROUND(SUMIF(Suppressions!$A:$A,A73,Suppressions!$E:$E),2) -> 38.05 | G73: =COUNTIF(Notes!$A:$A,A73) -> 1 | H73: =ROUND(SUMIF(Notes!$A:$A,A73,Notes!$F:$F),2) -> 38.05 | I73: =ROUND(H73-F73,2) -> 0 | J73: =IF(ABS(I73)<=0.01,"somme DEL = total note","écart") -> somme DEL = total note | K73: Note n°20 (20:26) 38.05 €
A74: deplacement-08 | B74: deplacement | C74: 2022-2023 | D74: 2022-12-07 | E74: =COUNTIF(Suppressions!$A:$A,A74) -> 5 | F74: =ROUND(SUMIF(Suppressions!$A:$A,A74,Suppressions!$E:$E),2) -> 28.35 | G74: =COUNTIF(Notes!$A:$A,A74) -> 1 | H74: =ROUND(SUMIF(Notes!$A:$A,A74,Notes!$F:$F),2) -> 28.35 | I74: =ROUND(H74-F74,2) -> 0 | J74: =IF(ABS(I74)<=0.01,"somme DEL = total note","écart") -> somme DEL = total note | K74: Note n°14 (19:37) 28.35 €
A75: deplacement-09 | B75: deplacement | C75: 2022-2023 | D75: 2023-01-07 | E75: =COUNTIF(Suppressions!$A:$A,A75) -> 5 | F75: =ROUND(SUMIF(Suppressions!$A:$A,A75,Suppressions!$E:$E),2) -> 59.1 | G75: =COUNTIF(Notes!$A:$A,A75) -> 1 | H75: =ROUND(SUMIF(Notes!$A:$A,A75,Notes!$F:$F),2) -> 59.1 | I75: =ROUND(H75-F75,2) -> 0 | J75: =IF(ABS(I75)<=0.01,"somme DEL = total note","écart") -> somme DEL = total note | K75: Note n°13 (19:33) 59.10 €
A76: deplacement-10 | B76: deplacement | C76: 2022-2023 | D76: 2023-03-26 | E76: =COUNTIF(Suppressions!$A:$A,A76) -> 5 | F76: =ROUND(SUMIF(Suppressions!$A:$A,A76,Suppressions!$E:$E),2) -> 25.6 | G76: =COUNTIF(Notes!$A:$A,A76) -> 1 | H76: =ROUND(SUMIF(Notes!$A:$A,A76,Notes!$F:$F),2) -> 25.6 | I76: =ROUND(H76-F76,2) -> 0 | J76: =IF(ABS(I76)<=0.01,"somme DEL = total note","écart") -> somme DEL = total note | K76: Note n°4 (12:26) 25.60 €
A77: deplacement-11 | B77: deplacement | C77: 2023-2024 | D77: 2023-04-30 | E77: =COUNTIF(Suppressions!$A:$A,A77) -> 5 | F77: =ROUND(SUMIF(Suppressions!$A:$A,A77,Suppressions!$E:$E),2) -> 36.35 | G77: =COUNTIF(Notes!$A:$A,A77) -> 1 | H77: =ROUND(SUMIF(Notes!$A:$A,A77,Notes!$F:$F),2) -> 36.35 | I77: =ROUND(H77-F77,2) -> 0 | J77: =IF(ABS(I77)<=0.01,"somme DEL = total note","écart") -> somme DEL = total note | K77: Note n°19 (19:49) 36.35 €
A78: deplacement-12 | B78: deplacement | C78: 2023-2024 | D78: 2023-05-07 | E78: =COUNTIF(Suppressions!$A:$A,A78) -> 5 | F78: =ROUND(SUMIF(Suppressions!$A:$A,A78,Suppressions!$E:$E),2) -> 35.75 | G78: =COUNTIF(Notes!$A:$A,A78) -> 1 | H78: =ROUND(SUMIF(Notes!$A:$A,A78,Notes!$F:$F),2) -> 35.75 | I78: =ROUND(H78-F78,2) -> 0 | J78: =IF(ABS(I78)<=0.01,"somme DEL = total note","écart") -> somme DEL = total note | K78: Note n°18 (19:31) 35.75 €
... A90: deplacement-24 | B90: deplacement | C90: 2024-2025 | D90: 2024-12-06 | E90: =COUNTIF(Suppressions!$A:$A,A90) -> 7 | F90: =ROUND(SUMIF(Suppressions!$A:$A,A90,Suppressions!$E:$E),2) -> 86.9 | G90: =COUNTIF(Notes!$A:$A,A90) -> 1 | H90: =ROUND(SUMIF(Notes!$A:$A,A90,Notes!$F:$F),2) -> 86.9 | I90: =ROUND(H90-F90,2) -> 0 | J90: =IF(ABS(I90)<=0.01,"somme DEL = total note","écart") -> somme DEL = total note | K90: Note n°19 (19:55) 86.90 €

Sheet Suppressions
A1: ex_id | B1: famille | C1: date | D1: heure | E1: montant (€) | F1: devient (article) | G1: tables
A2: forfait-01 | B2: forfait | C2: 2022-04-21 | D2: 12:58 | E2: 4.4
A3: forfait-01 | B3: forfait | C3: 2022-04-21 | D3: 12:58 | E3: 8.4
A4: forfait-01 | B4: forfait | C4: 2022-04-21 | D4: 12:58 | E4: 17.6
A5: forfait-02 | B5: forfait | C5: 2022-05-04 | D5: 19:05 | E5: 4.4
A6: forfait-02 | B6: forfait | C6: 2022-05-04 | D6: 19:05 | E6: 24
A7: forfait-02 | B7: forfait | C7: 2022-05-04 | D7: 19:05 | E7: 35.2
A8: forfait-03 | B8: forfait | C8: 2022-06-10 | D8: 11:59 | E8: 4.4
A9: forfait-03 | B9: forfait | C9: 2022-06-10 | D9: 11:59 | E9: 4.7
A10: forfait-03 | B10: forfait | C10: 2022-06-10 | D10: 11:59 | E10: 5.9
A11: forfait-03 | B11: forfait | C11: 2022-06-10 | D11: 11:59 | E11: 9.4
A12: forfait-03 | B12: forfait | C12: 2022-06-10 | D12: 11:59 | E12: 15.9
A13: forfait-03 | B13: forfait | C13: 2022-06-10 | D13: 11:59 | E13: 17.6
... A173: forfait-31 | B173: forfait | C173: 2025-03-05 | D173: 19:32 | E173: 18.6
A174: partage-01 | B174: partage | C174: 2022-04-16 | D174: 20:07 | E174: 3.9 | F174: Jus de Fruit / POMMES FRITES | G174: n°23, n°24
A175: partage-01 | B175: partage | C175: 2022-04-16 | D175: 20:07 | E175: 4.7 | F175: Crêpe Marrons | G175: n°23, n°24
A176: partage-01 | B176: partage | C176: 2022-04-16 | D176: 20:07 | E176: 7.8 | F176: Pinte | G176: n°23, n°24
A177: partage-01 | B177: partage | C177: 2022-04-16 | D177: 20:07 | E177: 8.7 | F177: Pavlova | G177: n°23, n°24
A178: partage-02 | B178: partage | C178: 2022-05-14 | D178: 19:47 | E178: 3.8 | F178: Whisky L.J (2cl) Bab | G178: n°22, n°23
A179: partage-02 | B179: partage | C179: 2022-05-14 | D179: 19:47 | E179: 9.8 | F179: Pichet 50cl vin | G179: n°22, n°23
A180: partage-02 | B180: partage | C180: 2022-05-14 | D180: 19:47 | E180: 16.9 | F180: Croûtes Morilles | G180: n°22, n°23
A181: partage-02 | B181: partage | C181: 2022-05-14 | D181: 19:47 | E181: 17.6 | F181: TRUITE JURASSIENNE | G181: n°22, n°23
A182: partage-03 | B182: partage | C182: 2022-06-25 | D182: 20:16 | E182: 3.8 | F182: Jambon Blanc | G182: n°27, n°28
A183: partage-03 | B183: partage | C183: 2022-06-25 | D183: 20:16 | E183: 3.9 | F183: POMMES FRITES | G183: n°25, n°26
A184: partage-04 | B184: partage | C184: 2022-07-03 | D184: 13:18 | E184: 1.8 | F184: Chantilly | G184: n°9, n°10
A185: partage-04 | B185: partage | C185: 2022-07-03 | D185: 13:18 | E185: 3.9 | F185: Fuze Tea / GLACE 2 BOULES / Panaché | G185: n°9, n°10, n°12, n°13
... A258: partage-34 | B258: partage | C258: 2025-03-05 | D258: 20:30 | E258: 9 | F258: MAEVA | G258: n°24, n°25
A259: deplacement-01 | B259: deplacement | C259: 2022-04-24 | D259: 11:58 | E259: 6.6
A260: deplacement-01 | B260: deplacement | C260: 2022-04-24 | D260: 11:58 | E260: 17.6
A261: deplacement-01 | B261: deplacement | C261: 2022-04-24 | D261: 11:58 | E261: 19
A262: deplacement-01 | B262: deplacement | C262: 2022-04-24 | D262: 11:58 | E262: 29.9
A263: deplacement-02 | B263: deplacement | C263: 2022-05-25 | D263: 20:20 | E263: 3.8
A264: deplacement-02 | B264: deplacement | C264: 2022-05-25 | D264: 20:20 | E264: 4
A265: deplacement-02 | B265: deplacement | C265: 2022-05-25 | D265: 20:20 | E265: 5.45
A266: deplacement-02 | B266: deplacement | C266: 2022-05-25 | D266: 20:20 | E266: 13.4
A267: deplacement-02 | B267: deplacement | C267: 2022-05-25 | D267: 20:20 | E267: 59.8
A268: deplacement-03 | B268: deplacement | C268: 2022-06-01 | D268: 12:25 | E268: 1.8
A269: deplacement-03 | B269: deplacement | C269: 2022-06-01 | D269: 12:25 | E269: 2.6
A270: deplacement-03 | B270: deplacement | C270: 2022-06-01 | D270: 12:25 | E270: 3.3
... A393: deplacement-24 | B393: deplacement | C393: 2024-12-06 | D393: 19:55 | E393: 24.5

Sheet Notes
A1: ex_id | B1: famille | C1: date | D1: note | E1: heure | F1: total (€) | G1: nb articles | H1: somme articles (€) | I1: ecart (€)
A2: forfait-01 | B2: forfait | C2: 2022-04-21 | D2: Note n°17 | E2: 12:59 | F2: 30.4 | G2: =COUNTIFS(Articles!$A:$A,A2,Articles!$D:$D,D2) -> 1 | H2: =ROUND(SUMIFS(Articles!$H:$H,Articles!$A:$A,A2,Articles!$D:$D,D2),2) -> 30.4 | I2: =ROUND(H2-F2,2) -> 0
A3: forfait-02 | B3: forfait | C3: 2022-05-04 | D3: Note n°13 | E3: 19:05 | F3: 63.6 | G3: =COUNTIFS(Articles!$A:$A,A3,Articles!$D:$D,D3) -> 1 | H3: =ROUND(SUMIFS(Articles!$H:$H,Articles!$A:$A,A3,Articles!$D:$D,D3),2) -> 63.6 | I3: =ROUND(H3-F3,2) -> 0
A4: forfait-03 | B4: forfait | C4: 2022-06-10 | D4: Note n°2 | E4: 11:59 | F4: 76.9 | G4: =COUNTIFS(Articles!$A:$A,A4,Articles!$D:$D,D4) -> 1 | H4: =ROUND(SUMIFS(Articles!$H:$H,Articles!$A:$A,A4,Articles!$D:$D,D4),2) -> 76.9 | I4: =ROUND(H4-F4,2) -> 0
A5: forfait-04 | B5: forfait | C5: 2022-07-01 | D5: Note n°17 | E5: 19:33 | F5: 57.1 | G5: =COUNTIFS(Articles!$A:$A,A5,Articles!$D:$D,D5) -> 1 | H5: =ROUND(SUMIFS(Articles!$H:$H,Articles!$A:$A,A5,Articles!$D:$D,D5),2) -> 57.1 | I5: =ROUND(H5-F5,2) -> 0
A6: forfait-05 | B6: forfait | C6: 2022-08-09 | D6: Note n°11 | E6: 12:14 | F6: 45.6 | G6: =COUNTIFS(Articles!$A:$A,A6,Articles!$D:$D,D6) -> 1 | H6: =ROUND(SUMIFS(Articles!$H:$H,Articles!$A:$A,A6,Articles!$D:$D,D6),2) -> 45.6 | I6: =ROUND(H6-F6,2) -> 0
A7: forfait-06 | B7: forfait | C7: 2022-09-09 | D7: Note n°3 | E7: 12:08 | F7: 76.9 | G7: =COUNTIFS(Articles!$A:$A,A7,Articles!$D:$D,D7) -> 1 | H7: =ROUND(SUMIFS(Articles!$H:$H,Articles!$A:$A,A7,Articles!$D:$D,D7),2) -> 76.9 | I7: =ROUND(H7-F7,2) -> 0
A8: forfait-07 | B8: forfait | C8: 2022-10-01 | D8: Note n°26 | E8: 19:34 | F8: 21.1 | G8: =COUNTIFS(Articles!$A:$A,A8,Articles!$D:$D,D8) -> 1 | H8: =ROUND(SUMIFS(Articles!$H:$H,Articles!$A:$A,A8,Articles!$D:$D,D8),2) -> 21.1 | I8: =ROUND(H8-F8,2) -> 0
A9: forfait-08 | B9: forfait | C9: 2022-11-03 | D9: Note n°17 | E9: 13:19 | F9: 47.7 | G9: =COUNTIFS(Articles!$A:$A,A9,Articles!$D:$D,D9) -> 1 | H9: =ROUND(SUMIFS(Articles!$H:$H,Articles!$A:$A,A9,Articles!$D:$D,D9),2) -> 47.7 | I9: =ROUND(H9-F9,2) -> 0
A10: forfait-09 | B10: forfait | C10: 2022-12-15 | D10: Note n°6 | E10: 12:31 | F10: 53.5 | G10: =COUNTIFS(Articles!$A:$A,A10,Articles!$D:$D,D10) -> 1 | H10: =ROUND(SUMIFS(Articles!$H:$H,Articles!$A:$A,A10,Articles!$D:$D,D10),2) -> 53.5 | I10: =ROUND(H10-F10,2) -> 0
A11: forfait-10 | B11: forfait | C11: 2023-01-04 | D11: Note n°4 | E11: 12:20 | F11: 64.7 | G11: =COUNTIFS(Articles!$A:$A,A11,Articles!$D:$D,D11) -> 1 | H11: =ROUND(SUMIFS(Articles!$H:$H,Articles!$A:$A,A11,Articles!$D:$D,D11),2) -> 64.7 | I11: =ROUND(H11-F11,2) -> 0
A12: forfait-11 | B12: forfait | C12: 2023-03-22 | D12: Note n°12 | E12: 20:37 | F12: 194.3 | G12: =COUNTIFS(Articles!$A:$A,A12,Articles!$D:$D,D12) -> 2 | H12: =ROUND(SUMIFS(Articles!$H:$H,Articles!$A:$A,A12,Articles!$D:$D,D12),2) -> 194.3 | I12: =ROUND(H12-F12,2) -> 0
A13: forfait-12 | B13: forfait | C13: 2023-05-10 | D13: Note n°12 | E13: 18:56 | F13: 38 | G13: =COUNTIFS(Articles!$A:$A,A13,Articles!$D:$D,D13) -> 1 | H13: =ROUND(SUMIFS(Articles!$H:$H,Articles!$A:$A,A13,Articles!$D:$D,D13),2) -> 38 | I13: =ROUND(H13-F13,2) -> 0
... A143: deplacement-24 | B143: deplacement | C143: 2024-12-06 | D143: Note n°19 | E143: 19:55 | F143: 86.9 | G143: =COUNTIFS(Articles!$A:$A,A143,Articles!$D:$D,D143) -> 7 | H143: =ROUND(SUMIFS(Articles!$H:$H,Articles!$A:$A,A143,Articles!$D:$D,D143),2) -> 86.9 | I143: =ROUND(H143-F143,2) -> 0

Sheet Articles
A1: ex_id | B1: famille | C1: date | D1: note | E1: article | F1: qte | G1: prix unitaire (€) | H1: montant (€) | I1: check pu x qte | J1: article partagé
A2: forfait-01 | B2: forfait | C2: 2022-04-21 | D2: Note n°17 | E2: Menu 'Demi Lune' | F2: 2 | G2: 15.2 | H2: 30.4 | I2: =IF(ABS(ROUND(F2*G2,2)-H2)<=0.01,1,0) -> 1 | J2: 0
A3: forfait-02 | B3: forfait | C3: 2022-05-04 | D3: Note n°13 | E3: Menu du jour | F3: 2 | G3: 31.8 | H3: 63.6 | I3: =IF(ABS(ROUND(F3*G3,2)-H3)<=0.01,1,0) -> 1 | J3: 0
A4: forfait-03 | B4: forfait | C4: 2022-06-10 | D4: Note n°2 | E4: Menu du jour | F4: 2 | G4: 38.45 | H4: 76.9 | I4: =IF(ABS(ROUND(F4*G4,2)-H4)<=0.01,1,0) -> 1 | J4: 0
A5: forfait-04 | B5: forfait | C5: 2022-07-01 | D5: Note n°17 | E5: Menu du jour | F5: 2 | G5: 28.55 | H5: 57.1 | I5: =IF(ABS(ROUND(F5*G5,2)-H5)<=0.01,1,0) -> 1 | J5: 0
A6: forfait-05 | B6: forfait | C6: 2022-08-09 | D6: Note n°11 | E6: Menu 'Demi Lune' | F6: 2 | G6: 22.8 | H6: 45.6 | I6: =IF(ABS(ROUND(F6*G6,2)-H6)<=0.01,1,0) -> 1 | J6: 0
A7: forfait-06 | B7: forfait | C7: 2022-09-09 | D7: Note n°3 | E7: Menu 'Demi Lune' | F7: 2 | G7: 38.45 | H7: 76.9 | I7: =IF(ABS(ROUND(F7*G7,2)-H7)<=0.01,1,0) -> 1 | J7: 0
A8: forfait-07 | B8: forfait | C8: 2022-10-01 | D8: Note n°26 | E8: Menu du jour | F8: 1 | G8: 21.1 | H8: 21.1 | I8: =IF(ABS(ROUND(F8*G8,2)-H8)<=0.01,1,0) -> 1 | J8: 0
A9: forfait-08 | B9: forfait | C9: 2022-11-03 | D9: Note n°17 | E9: Menu du jour | F9: 2 | G9: 23.85 | H9: 47.7 | I9: =IF(ABS(ROUND(F9*G9,2)-H9)<=0.01,1,0) -> 1 | J9: 0
A10: forfait-09 | B10: forfait | C10: 2022-12-15 | D10: Note n°6 | E10: Menu du jour | F10: 2 | G10: 26.75 | H10: 53.5 | I10: =IF(ABS(ROUND(F10*G10,2)-H10)<=0.01,1,0) -> 1 | J10: 0
A11: forfait-10 | B11: forfait | C11: 2023-01-04 | D11: Note n°4 | E11: Menu du jour | F11: 2 | G11: 32.35 | H11: 64.7 | I11: =IF(ABS(ROUND(F11*G11,2)-H11)<=0.01,1,0) -> 1 | J11: 0
A12: forfait-11 | B12: forfait | C12: 2023-03-22 | D12: Note n°12 | E12: Menu 'Demi Lune' | F12: 2 | G12: 64 | H12: 128 | I12: =IF(ABS(ROUND(F12*G12,2)-H12)<=0.01,1,0) -> 1 | J12: 0
A13: forfait-11 | B13: forfait | C13: 2023-03-22 | D13: Note n°12 | E13: Menu 'Demi Lune' | F13: 1 | G13: 66.3 | H13: 66.3 | I13: =IF(ABS(ROUND(F13*G13,2)-H13)<=0.01,1,0) -> 1 | J13: 0
... A1048: deplacement-24 | B1048: deplacement | C1048: 2024-12-06 | D1048: Note n°19 | E1048: Crepe Chocolat | F1048: 0.5 | G1048: 5.9 | H1048: 2.95 | I1048: =IF(ABS(ROUND(F1048*G1048,2)-H1048)<=0.01,1,0) -> 1 | J1048: 0

Sheet Partage_qte
A1: ex_id | B1: date | C1: article | D1: somme des quantités sur les notes | E1: entier ? (1 = oui)
A2: partage-01 | B2: 2022-04-16 | C2: Pinte | D2: =SUMIFS(Articles!$F:$F,Articles!$A:$A,A2,Articles!$E:$E,C2) -> 1 | E2: =IF(ABS(D2-ROUND(D2,0))<0.0001,1,0) -> 1
A3: partage-01 | B3: 2022-04-16 | C3: Jus de Fruit | D3: =SUMIFS(Articles!$F:$F,Articles!$A:$A,A3,Articles!$E:$E,C3) -> 1 | E3: =IF(ABS(D3-ROUND(D3,0))<0.0001,1,0) -> 1
A4: partage-01 | B4: 2022-04-16 | C4: PAYSANNE | D4: =SUMIFS(Articles!$F:$F,Articles!$A:$A,A4,Articles!$E:$E,C4) -> 2 | E4: =IF(ABS(D4-ROUND(D4,0))<0.0001,1,0) -> 1
A5: partage-01 | B5: 2022-04-16 | C5: POMMES FRITES | D5: =SUMIFS(Articles!$F:$F,Articles!$A:$A,A5,Articles!$E:$E,C5) -> 1 | E5: =IF(ABS(D5-ROUND(D5,0))<0.0001,1,0) -> 1
A6: partage-01 | B6: 2022-04-16 | C6: Crêpe Marrons | D6: =SUMIFS(Articles!$F:$F,Articles!$A:$A,A6,Articles!$E:$E,C6) -> 1 | E6: =IF(ABS(D6-ROUND(D6,0))<0.0001,1,0) -> 1
A7: partage-01 | B7: 2022-04-16 | C7: Pavlova | D7: =SUMIFS(Articles!$F:$F,Articles!$A:$A,A7,Articles!$E:$E,C7) -> 1 | E7: =IF(ABS(D7-ROUND(D7,0))<0.0001,1,0) -> 1
A8: partage-02 | B8: 2022-05-14 | C8: Père Gregoire | D8: =SUMIFS(Articles!$F:$F,Articles!$A:$A,A8,Articles!$E:$E,C8) -> 1 | E8: =IF(ABS(D8-ROUND(D8,0))<0.0001,1,0) -> 1
A9: partage-02 | B9: 2022-05-14 | C9: Crémant | D9: =SUMIFS(Articles!$F:$F,Articles!$A:$A,A9,Articles!$E:$E,C9) -> 1 | E9: =IF(ABS(D9-ROUND(D9,0))<0.0001,1,0) -> 1
A10: partage-02 | B10: 2022-05-14 | C10: Whisky L.J (2cl) Bab | D10: =SUMIFS(Articles!$F:$F,Articles!$A:$A,A10,Articles!$E:$E,C10) -> 1 | E10: =IF(ABS(D10-ROUND(D10,0))<0.0001,1,0) -> 1
A11: partage-02 | B11: 2022-05-14 | C11: Macvin du Jura | D11: =SUMIFS(Articles!$F:$F,Articles!$A:$A,A11,Articles!$E:$E,C11) -> 1 | E11: =IF(ABS(D11-ROUND(D11,0))<0.0001,1,0) -> 1
A12: partage-02 | B12: 2022-05-14 | C12: Salade Franc-Comptoi | D12: =SUMIFS(Articles!$F:$F,Articles!$A:$A,A12,Articles!$E:$E,C12) -> 1 | E12: =IF(ABS(D12-ROUND(D12,0))<0.0001,1,0) -> 1
A13: partage-02 | B13: 2022-05-14 | C13: Croûtes Morilles | D13: =SUMIFS(Articles!$F:$F,Articles!$A:$A,A13,Articles!$E:$E,C13) -> 1 | E13: =IF(ABS(D13-ROUND(D13,0))<0.0001,1,0) -> 1
... A419: partage-34 | B419: 2025-03-05 | C419: Crêpe Nutella | D419: =SUMIFS(Articles!$F:$F,Articles!$A:$A,A419,Articles!$E:$E,C419) -> 1 | E419: =IF(ABS(D419-ROUND(D419,0))<0.0001,1,0) -> 1
