Workbook

Sheet Sources
A1: Sources brutes — données réellement tracées et bases énoncées par le service
A2: Seules les lignes enregistrées en caisse à prix nul constituent une trace directe d'une mise à disposition gratuite. Les annexes de détail des trois exercices (C1, C2, C3) sont au dossier : le balayage des sept lignes de vin nommé au verre/pichet à 0 € a été refait directement sur chacune. La dose de 2 cl, le nombre de 6 292 couples note x vin nommé et la partition verre/pichet proviennent du décompte note par note, reproductible sur les mêmes annexes.
A4: A. Lignes de vin nommé (verre/pichet) enregistrées à prix nul sur les 3 exercices
A5: Exercice | B5: Date | C5: N° note | D5: Libellé caisse | E5: Vin nommé | F5: Quantité | G5: Volume (L) | I5: Par exercice (lignes tracées à 0 €) | J5: Lignes | K5: Volume (L)
A6: Exercice 2 (2023-2024) | B6: 2023-04-20 | C6: 27 | D6: Saint Véran Verre | E6: Saint Véran | F6: 1 | G6: 0.15 | I6: Exercice 1 (2022-2023) | J6: =COUNTIF($A$6:$A$12,I6) -> 0 | K6: =SUMIF($A$6:$A$12,I6,$G$6:$G$12) -> 0
A7: Exercice 2 (2023-2024) | B7: 2023-05-19 | C7: 28 | D7: Savagnin verre | E7: Savagnin | F7: 1 | G7: 0.15 | I7: Exercice 2 (2023-2024) | J7: =COUNTIF($A$6:$A$12,I7) -> 5 | K7: =SUMIF($A$6:$A$12,I7,$G$6:$G$12) -> 1.1
A8: Exercice 2 (2023-2024) | B8: 2023-08-05 | C8: 32 | D8: PICHET ALIGOTE 50cL | E8: Aligoté | F8: 1 | G8: 0.5 | I8: Exercice 3 (2024-2025) | J8: =COUNTIF($A$6:$A$12,I8) -> 2 | K8: =SUMIF($A$6:$A$12,I8,$G$6:$G$12) -> 0.75
A9: Exercice 2 (2023-2024) | B9: 2023-08-10 | C9: 32 | D9: Arbois Trousseau Le | E9: Arbois Trousseau | F9: 1 | G9: 0.15 | I9: Cumul 3 exercices | J9: =SUM(J6:J8) -> 7 | K9: =SUM(K6:K8) -> 1.85
A10: Exercice 2 (2023-2024) | B10: 2024-03-07 | C10: 7 | D10: Savagnin verre | E10: Savagnin | F10: 1 | G10: 0.15
A11: Exercice 3 (2024-2025) | B11: 2024-05-10 | C11: 27 | D11: Saint Véran Verre | E11: Saint Véran | F11: 2 | G11: 0.3
A12: Exercice 3 (2024-2025) | B12: 2024-10-30 | C12: 15 | D12: Savagnin verre | E12: Savagnin | F12: 3 | G12: 0.45
A13: TOTAL tracé | E13: 7 lignes | F13: =SUM(F6:F12) -> 10 | G13: =SUM(G6:G12) -> 1.85
A14: Nature : verres et pichets entiers portés à 0 €, et non des larmes de 2 cl. Balayage direct des trois annexes C : exercice 1 (C1), aucune ligne de vin nommé au verre/pichet à 0 € (la seule ligne de vin nommé à 0 € y est une bouteille, ref 2025 « H.C.B BEAUNE BTL », exclue) ; exercice 2 (C2), 5 lignes pour 1,10 L ; exercice 3 (C3), 2 lignes pour 0,75 L.
A16: B. Bases énoncées par le service pour ses abattements de 15 % (p. 86)
A17: Catégorie | B17: Exercice | C17: Base énoncée | D17: Unité | E17: Résultat annoncé (L)
A18: Vins au BIB | B18: Exercice 1 | C18: 45433 | D18: cl | E18: 67.99
A19: Vins au BIB | B19: Exercice 2 | C19: 44079 | D19: cl | E19: 66.12
A20: Vins au BIB | B20: Exercice 3 | C20: 42696 | D20: cl | E20: 64.04
A21: Bouteilles bouchées | B21: Exercice 1 | C21: 1169 | D21: L | E21: 175.35
A22: Bouteilles bouchées | B22: Exercice 2 | C22: 1153.87 | D22: L | E22: 173.08
A23: Bouteilles bouchées | B23: Exercice 3 | C23: 1020.75 | D23: L | E23: 153.11
A25: C. Paramètres du décompte R1 (hypothèse de dose + comptage note par note)
A26: Paramètre | B26: Valeur | C26: Statut / source
A27: Dose de dégustation | B27: 0.02 | C27: Convention déclarée par la société, jamais mesurée (L/geste)
A28: Couples note x vin nommé comptés (3 ex.) | B28: 6292 | C28: Décompte note par note sur annexes C1/C2/C3 (97 775 lignes lues, re-vérifié) — lignes de VENTE, non des offerts
A29: dont vins au BIB (Aligoté, Chusclan) | B29: 1092 | C29: Décompte R1 — périmètre couvert par l'abattement BIB
A30: dont vin vendu seulement en bouteille entière | B30: 329 | C30: Décompte — refs 2019 et 1831, prix bouteille (vérifié sur C1/C2/C3)
A31: dont vendu au verre | B31: 3798 | C31: Décompte R1 — part exposée à l'objection p. 64
A32: dont vendu au pichet | B32: 1073 | C32: Décompte R1 — volume vendu = contenance du récipient

Sheet Calcul
A1: Calculs — tous les résultats ci-dessous sont obtenus par formule
A2: Chaque cellule « Résultat » renvoie à une base de l'onglet Sources ; aucun résultat n'est saisi en dur. Les volumes hypothétiques dépendent de la dose conventionnelle de 2 cl (Sources, bloc C).
A4: 1. Volume de vin nommé réellement tracé à prix nul (verres/pichets entiers)
A5: Grandeur | B5: Formule renvoyant aux sources | C5: Résultat (L)
A6: Volume tracé sur 3 exercices (7 lignes) | B6: Somme des 7 volumes (Sources) | C6: =Sources!G13 -> 1.85
A8: 2. Recontrôle de l'abattement « vins au BIB » (base cl x 15 %)
A9: Exercice | B9: Base (cl) -> Sources | C9: Recalcul 15 % (L) | D9: Annoncé (L) | E9: Écart (L)
A10: Exercice 1 | B10: =Sources!C18 -> 45433 | C10: =Sources!C18*0.15/100 -> 68.1495 | D10: =Sources!E18 -> 67.99 | E10: =C10-D10 -> 0.1595
A11: Exercice 2 | B11: =Sources!C19 -> 44079 | C11: =Sources!C19*0.15/100 -> 66.1185 | D11: =Sources!E19 -> 66.12 | E11: =C11-D11 -> -0.0015
A12: Exercice 3 | B12: =Sources!C20 -> 42696 | C12: =Sources!C20*0.15/100 -> 64.044 | D12: =Sources!E20 -> 64.04 | E12: =C12-D12 -> 0.004
A13: Cumul 3 exercices (valeur retenue) | C13: =SUM(C10:C12) -> 198.312 | D13: =SUM(D10:D12) -> 198.15 | E13: =C13-D13 -> 0.162
A14: Note : la valeur exacte du cumul BIB est de 198,31 L (et non 198,15 L, qui est la somme des seuls chiffres arrondis annoncés par le service). Le service l'arrondit lui-même à « 198 L ».
A16: 3. Recontrôle de l'abattement « bouteilles bouchées » (base L x 15 %)
A17: Exercice | B17: Base (L) -> Sources | C17: Recalcul 15 % (L) | D17: Annoncé (L) | E17: Écart (L)
A18: Exercice 1 | B18: =Sources!C21 -> 1169 | C18: =Sources!C21*0.15 -> 175.35 | D18: =Sources!E21 -> 175.35 | E18: =C18-D18 -> 0
A19: Exercice 2 | B19: =Sources!C22 -> 1153.87 | C19: =Sources!C22*0.15 -> 173.0805 | D19: =Sources!E22 -> 173.08 | E19: =C19-D19 -> 0.0005
A20: Exercice 3 | B20: =Sources!C23 -> 1020.75 | C20: =Sources!C23*0.15 -> 153.1125 | D20: =Sources!E23 -> 153.11 | E20: =C20-D20 -> 0.0025
A21: Cumul 3 exercices (valeur retenue) | C21: =SUM(C18:C20) -> 501.543 | D21: =SUM(D18:D20) -> 501.54 | E21: =C21-D21 -> 0.003
A23: 4. Volume hypothétique de la demande (dose 2 cl x comptage R1) — chaîne unique
A24: Étape | B24: Couples -> Sources | C24: Volume (L) = couples x dose
A25: Couples note x vin nommé comptés | B25: =Sources!B28 -> 6292 | C25: =Sources!B28*Sources!B27 -> 125.84
A26: moins vins au BIB (couverts par l'abattement BIB) | B26: =-Sources!B29 -> -1092 | C26: =-Sources!B29*Sources!B27 -> -21.84
A27: Sous-total bouteilles (intermédiaire) | B27: =B25+B26 -> 5200 | C27: =C25+C26 -> 104
A28: moins vin vendu seulement en bouteille entière (refs 2019, 1831) | B28: =-Sources!B30 -> -329 | C28: =-Sources!B30*Sources!B27 -> -6.58
A29: Volume hypothétique de la demande | B29: =B27+B28 -> 4871 | C29: =C27+C28 -> 97.42
A31: 5. Partition du volume hypothétique : verre (objection p. 64) vs pichet (hors objection)
A32: Contenant vendu | B32: Couples -> Sources | C32: Volume (L) | D32: Statut de preuve
A33: Vendu au verre | B33: =Sources!B31 -> 3798 | C33: =Sources!B31*Sources!B27 -> 75.96 | D33: À ÉTAYER : suspendu à une attestation de salle non produite
A34: Vendu au pichet | B34: =Sources!B32 -> 1073 | C34: =Sources!B32*Sources!B27 -> 21.46 | D34: Volume vendu = contenance du récipient (50 cl) ; objection p. 64 sans objet
A35: Total (contrôle = demande) | C35: =C33+C34 -> 97.42
A37: 6. Synthèse — ce qui est prouvé aujourd'hui vs ce qui est hypothétique
A38: Niveau de preuve | B38: Volume (L) | C38: Ce dont il dépend
A39: Tracé en caisse (lignes à 0 €) | B39: =Calcul!C6 -> 1.85 | C39: 7 lignes enregistrées à 0 € ; verres/pichets entiers, non des larmes
A40: Hypothétique, au verre (à étayer) | B40: =Calcul!C33 -> 75.96 | C40: Attestation de salle décrivant le geste (verre distinct vs verre complété)
A41: Hypothétique, au pichet | B41: =Calcul!C34 -> 21.46 | C41: Dose 2 cl conventionnelle ; contenant pichet non atteint par l'objection
A42: Total hypothétique de la demande | B42: =Calcul!C29 -> 97.42

Sheet Méthode
A1: Méthode — d'où vient chaque chiffre
A3: 1. Le poste « dégustation offerte » n'est pas lu dans la caisse.
A4: La caisse enregistre des VENTES. Qu'un vin nommé figure sur une note prouve qu'il a été facturé, pas qu'une larme de 2 cl a été offerte. La seule trace directe d'une mise à disposition gratuite est une ligne portée à prix nul : sur 3 exercices, l'onglet « Vin nommé à prix zéro » de la pièce R1 (verre-et-pichet) n'en recense que 7 (10 unités, 1,85 L), et précise qu'il s'agit de verres/pichets ENTIERS à 0 €, non de larmes.
A6: 2. Vérification directe sur les trois annexes de détail (C1, C2, C3).
A7: Les annexes de détail des trois exercices sont au dossier. Balayage direct des lignes de vin nommé au verre/pichet enregistrées à 0 € : exercice 1 (C1, 33 222 lignes), aucune (la seule ligne de vin nommé à 0 € est une bouteille, ref 2025 « H.C.B BEAUNE BTL », exclue) ; exercice 2 (C2), 5 lignes pour 1,10 L ; exercice 3 (C3), 2 lignes pour 0,75 L. Soit 7 lignes et 1,85 L sur les trois exercices, chacune re-vérifiable à sa date et son numéro de note.
A9: 3. La dose de 2 cl est une hypothèse, pas une mesure.
A10: Elle est déclarée par la société et n'a fait l'objet d'aucun relevé ni d'aucune constatation. À 1 cl le volume tombe de moitié, à 3 cl il croît de 50 %. Tout volume calculé « couples x 2 cl » est donc indexé sur un paramètre non établi : il est présenté comme hypothèse, non comme fait.
A12: 4. Le comptage de 6 292 couples et la partition verre/pichet viennent de R1.
A13: Décompte note par note sur C1/C2/C3 (97 775 lignes lues ; 6 326 lignes de vin nommé au verre/pichet ; 16 613 notes dont 5 457 retenues), reproductible sur les annexes au dossier. Ils comptent des lignes de vente, pas des gestes gratuits, et servent uniquement à borner le volume HYPOTHÉTIQUE que la demande atteindrait SI le geste était attesté.
A15: 5. Chaîne de la demande, valeur unique.
A16: 125,84 L (6 292 x 2 cl) moins 21,84 L de vins au BIB (1 092 x 2 cl, couverts par l'abattement BIB) = 104,00 L ; moins 6,58 L de vin vendu seulement en bouteille entière (329 x 2 cl, refs 2019 et 1831 au prix bouteille, vérifié sur C1) = 97,42 L. Le 104,00 L n'est qu'un intermédiaire : la seule valeur de demande est 97,42 L. La pièce R1 « par note » qui affichait 104,00 L comme « volume demandé » est corrigée ici.
A18: 6. Correction de l'erreur arithmétique BIB.
... A28: Le grief porte sur un chiffre d'affaires. Ici la dégustation retranche un VOLUME du vin réputé vendable en amont de l'abattement de 15 % et du coefficient d'extrapolation (environ x3) appliqués par le service. L'incidence exacte en euros n'est pas isolable des pièces produites (ni le prix moyen au litre retenu dans la reconstitution, ni le coefficient par poste ne sont sourçables ligne à ligne) : elle n'est donc pas chiffrée en euros, par honnêteté.
