Workbook

Sheet Sources
A1: SOURCES : lignes LUES sur la proposition personnelle de M. Thierry PASTEUR du 19/10/2026 (PDF scanné, OCR + lecture visuelle). Aucune formule ici.
A3: Ligne (libellé du service) | B3: 2023 | C3: 2024 | D3: 2025 | E3: Page(s)
A4: Discordance TTC société (proposition du 18/05/2026 p. 52 ; rappel p. 59 arrondi) | B4: 193234.55 | C4: 138863.57 | D4: 139727.76 | E4: p. 59 ; prop. 18/05 p. 52
A5: TVA incluse (minoration de TVA, prop. 18/05/2026) | B5: 20421.1 | C5: 14854.01 | D5: 14651.59 | E5: prop. 18/05 p. 52-53
A6: Distributions occultes arrondies (part HT ÷ 2) | B6: 86407 | C6: 62005 | D6: 62538 | E6: p. 62
A7: Part TVA ÷ 2 (« désinvestissements », art. 109-1-2°) | B7: 10210 | C7: 7427 | D7: 7326 | E7: p. 60, p. 62
A8: Base RCM du foyer | B8: 96617 | C8: 69432 | D8: 69864 | E8: p. 62
A9: Assiette IR après × 1,25 (art. 158-7-2°) | B9: 120771 | C9: 86790 | D9: 87330 | E9: p. 63
A10: Revenu net imposable AVANT contrôle | B10: 21237 | C10: 25125 | D10: 23540 | E10: p. 67, 71, 75
A11: Revenu net imposable APRÈS contrôle | B11: 142008 | C11: 111915 | D11: 110870 | E11: p. 67, 71, 75
A12: Nombre de parts | B12: 1.5 | C12: 1.5 | D12: 1.5 | E12: p. 67, 71, 75 ; détail p. 69, 73, 77
A13: Revenus des associés et gérants (déclarés) | B13: 18123 | C13: 22151 | D13: 21360 | E13: p. 69, 73, 77
A14: RCM déjà déclarés (dividendes) avant contrôle | B14: 7534 | C14: 7543 | D14: 7549 | E14: p. 70, 74, 78 (« RCM déjà soumis aux PS »)
A15: Impôt sur le revenu AVANT contrôle | B15: -964 | C15: 36 | D15: 77 | E15: p. 67, 71, 75
... A29: Montant total des rappels (TOTAL IR + TOTAL PS) = supplément notifié | B29: 83391 | C29: 56724 | D29: 56830 | E29: p. 68, 72, 76 ; p. 70, 74, 78
A30: CSG déductible supplémentaire annoncée (à déclarer sur les revenus 2026) | B30: 6570 | C30: 4721 | E30: p. 70, 74 (2025 : non imprimé)
A31: Revenu fiscal de référence après contrôle | B31: 145010 | C31: 114917 | D31: 113872 | E31: p. 70, 74, 78
A33: Lecture : les nombres ci-dessus sont ceux du service. Les feuilles suivantes les recalculent par formule et affichent l'écart.

Sheet Barèmes
A1: PARAMÈTRES DE DROIT (vérifiés) : barème art. 197 CGI par année de revenus, plafonnement du quotient familial (art. 197 I-2), prélèvements sociaux, intérêt de retard.
A3: Seuil (€) / année | B3: 2023 (LF 2024) | C3: 2024 (LF 2025) | D3: 2025 (LF 2026) | E3: Taux marginal | F3: Incrément de taux (pour SUMPRODUCT)
A4: Tranche 1 | B4: 0 | C4: 0 | D4: 0 | E4: 0 | F4: 0
A5: Tranche 2 | B5: 11294 | C5: 11497 | D5: 11600 | E5: 0.11 | F5: 0.11
A6: Tranche 3 | B6: 28797 | C6: 29315 | D6: 29579 | E6: 0.3 | F6: 0.19
A7: Tranche 4 | B7: 82341 | C7: 83823 | D7: 84577 | E7: 0.41 | F7: 0.11
A8: Tranche 5 | B8: 177106 | C8: 180294 | D8: 181917 | E8: 0.45 | F8: 0.04
A10: Paramètre | B10: 2023 | C10: 2024 | D10: 2025 | E10: Source
A11: Plafond de l'avantage par demi-part (art. 197 I-2) | B11: 1759 | C11: 1791 | D11: 1807 | E11: BOI-IR-LIQ-20-20-20 § 40 (1 807 € revenus 2025) ; 1 791 € (rev. 2024) ; 1 759 € (rev. 2023)
A12: Taux PS appliqué par le service | B12: 0.172 | C12: 0.172 | D12: 0.186 | E12: p. 70, 74 ; p. 75-77 (11,1 % + 7,5 %)
A13: Taux PS de droit commun 17,2 % (CSG 9,2 + CRDS 0,5 + PSOL 7,5) | B13: 0.172 | C13: 0.172 | D13: 0.172 | E13: L. 136-6 CSS ; art. 235 ter CGI ; LFSS 2026 art. 12 : CSG 10,6 % sur revenus du patrimoine 2025 (à vérifier pour les RCM par rôle)
A14: Intérêt de retard mensuel (art. 1727 III) | B14: 0.002 | C14: 0.002 | D14: 0.002 | E14: 0,20 % par mois depuis le 01/01/2018
A15: Point de départ (1er juillet N+1) et arrêt (31/10/2026, mois de la proposition) | B15: 01/07/2024 | C15: 01/07/2025 | D15: 01/07/2026 | E15: BOI-CF-INF-10-10-20 § 70 et § 130
A16: Mois courus jusqu'au 31/10/2026 | B16: 28 | C16: 16 | D16: 4 | E16: recalcul : juil. 2024 → oct. 2026 = 28 ; juil. 2025 → oct. 2026 = 16 ; juil. 2026 → oct. 2026 = 4
A17: Majoration manquement délibéré (art. 1729 a) | B17: 0.4 | C17: 0.4 | D17: 0.4 | E17: BOI-CF-INF-10-20-20 § 20
A18: Coefficient d'assiette (art. 158-7-2°) | B18: 1.25 | C18: 1.25 | D18: 1.25 | E18: BOI-RPPM-RCM-20-10-20-10 § 120-150 ; exclu des PS : CC 2017-643/650 QPC § 17
A19: PFU (art. 200 A 1 A 1°) si pas d'option barème | B19: 0.128 | C19: 0.128 | D19: 0.128 | E19: RM Klinkert n° 3778, JO AN 24/10/2023 ; LF 2021 art. 39 : × 1,25 même au PFU

Sheet Controle ligne a ligne
A1: CONTRÔLE LIGNE À LIGNE : chaque ligne du service est recalculée par formule (colonnes B-D), comparée (E-G = recalcul − service).
A3: Ligne | B3: Recalcul 2023 | C3: Recalcul 2024 | D3: Recalcul 2025 | E3: Écart 2023 | F3: Écart 2024 | G3: Écart 2025 | H3: Formule / règle
A4: Part HT ÷ 2 = ROUND((TTC − TVA)/2) | B4: =ROUND((Sources!B4-Sources!B5)/2,0) -> 86407 | C4: =ROUND((Sources!C4-Sources!C5)/2,0) -> 62005 | D4: =ROUND((Sources!D4-Sources!D5)/2,0) -> 62538 | E4: =B4-Sources!B6 -> 0 | F4: =C4-Sources!C6 -> 0 | G4: =D4-Sources!D6 -> 0 | H4: arrondi du service
A5: Part TVA ÷ 2 = ROUND(TVA/2) | B5: =ROUND(Sources!B5/2,0) -> 10211 | C5: =ROUND(Sources!C5/2,0) -> 7427 | D5: =ROUND(Sources!D5/2,0) -> 7326 | E5: =B5-Sources!B7 -> 1 | F5: =C5-Sources!C7 -> 0 | G5: =D5-Sources!D7 -> 0 | H5: 2023 : 10 210,55 arrondi à 10 210 par le service (1 € de moins)
A6: Base RCM = ROUND(TTC/2) | B6: =ROUND(Sources!B4/2,0) -> 96617 | C6: =ROUND(Sources!C4/2,0) -> 69432 | D6: =ROUND(Sources!D4/2,0) -> 69864 | E6: =B6-Sources!B8 -> 0 | F6: =C6-Sources!C8 -> 0 | G6: =D6-Sources!D8 -> 0 | H6: CANON : 96 617 / 69 432 / 69 864
A7: Assiette IR = ROUND(base × 1,25) | B7: =ROUND(Sources!B8*1.25,0) -> 120771 | C7: =ROUND(Sources!C8*1.25,0) -> 86790 | D7: =ROUND(Sources!D8*1.25,0) -> 87330 | E7: =B7-Sources!B9 -> 0 | F7: =C7-Sources!C9 -> 0 | G7: =D7-Sources!D9 -> 0 | H7: art. 158-7-2°
A8: Variation du revenu imposable = après − avant | B8: =Sources!B11-Sources!B10 -> 120771 | C8: =Sources!C11-Sources!C10 -> 86790 | D8: =Sources!D11-Sources!D10 -> 87330 | E8: =B8-Sources!B9 -> 0 | F8: =C8-Sources!C9 -> 0 | G8: =D8-Sources!D9 -> 0 | H8: doit égaler l'assiette × 1,25
A9: IR barème APRÈS contrôle (1,5 part, plafonnement QF) | B9: =ROUND(MAX(SUMPRODUCT((Sources!B11/Sources!B12>Barèmes!$B$4:$B$8)*(Sources!B11/Sources!B12-Barèmes!$B$4:$B$8)*Barèmes!$F$4:$F$8)*Sources!B12,SUMPRODUCT((Sources!B11>Barèmes!$B$4:$B$8)*(Sources!B11-Barèmes!$B$4:$B$8)*Barèmes!$F$4:$F$8)-Barèmes!B11*(Sources!B12-1)*2),0) -> 40693 | C9: =ROUND(MAX(SUMPRODUCT((Sources!C11/Sources!C12>Barèmes!$C$4:$C$8)*(Sources!C11/Sources!C12-Barèmes!$C$4:$C$8)*Barèmes!$F$4:$F$8)*Sources!C12,SUMPRODUCT((Sources!C11>Barèmes!$C$4:$C$8)*(Sources!C11-Barèmes!$C$4:$C$8)*Barèmes!$F$4:$F$8)-Barèmes!C11*(Sources!C12-1)*2),0) -> 28039 | D9: =ROUND(MAX(SUMPRODUCT((Sources!D11/Sources!D12>Barèmes!$D$4:$D$8)*(Sources!D11/Sources!D12-Barèmes!$D$4:$D$8)*Barèmes!$F$4:$F$8)*Sources!D12,SUMPRODUCT((Sources!D11>Barèmes!$D$4:$D$8)*(Sources!D11-Barèmes!$D$4:$D$8)*Barèmes!$F$4:$F$8)-Barèmes!D11*(Sources!D12-1)*2),0) -> 27450 | E9: =B9-Sources!B17 -> 0 | F9: =C9-Sources!C17 -> 0 | G9: =D9-Sources!D17 -> 0 | H9: art. 197 I-1 et I-2 ; = ligne « IR sur les revenus soumis au barème »
A10: IR barème AVANT contrôle (même formule) | B10: =ROUND(MAX(SUMPRODUCT((Sources!B10/Sources!B12>Barèmes!$B$4:$B$8)*(Sources!B10/Sources!B12-Barèmes!$B$4:$B$8)*Barèmes!$F$4:$F$8)*Sources!B12,SUMPRODUCT((Sources!B10>Barèmes!$B$4:$B$8)*(Sources!B10-Barèmes!$B$4:$B$8)*Barèmes!$F$4:$F$8)-Barèmes!B11*(Sources!B12-1)*2),0) -> 473 | C10: =ROUND(MAX(SUMPRODUCT((Sources!C10/Sources!C12>Barèmes!$C$4:$C$8)*(Sources!C10/Sources!C12-Barèmes!$C$4:$C$8)*Barèmes!$F$4:$F$8)*Sources!C12,SUMPRODUCT((Sources!C10>Barèmes!$C$4:$C$8)*(Sources!C10-Barèmes!$C$4:$C$8)*Barèmes!$F$4:$F$8)-Barèmes!C11*(Sources!C12-1)*2),0) -> 867 | D10: =ROUND(MAX(SUMPRODUCT((Sources!D10/Sources!D12>Barèmes!$D$4:$D$8)*(Sources!D10/Sources!D12-Barèmes!$D$4:$D$8)*Barèmes!$F$4:$F$8)*Sources!D12,SUMPRODUCT((Sources!D10>Barèmes!$D$4:$D$8)*(Sources!D10-Barèmes!$D$4:$D$8)*Barèmes!$F$4:$F$8)-Barèmes!D11*(Sources!D12-1)*2),0) -> 675 | H10: avant décote/réductions : non comparable au « −964 / 36 / 77 » du service (crédits, PFU restitué)
A11: Majoration 40 % IR = ROUND(0,4 × droits IR) | B11: =ROUND(0.4*Sources!B18,0) -> 16277 | C11: =ROUND(0.4*Sources!C18,0) -> 11068 | D11: =ROUND(0.4*Sources!D18,0) -> 10947 | E11: =B11-Sources!B21 -> 0 | F11: =C11-Sources!C21 -> 0 | G11: =D11-Sources!D21 -> 0 | H11: art. 1729 a ; base = variation d'IR
A12: Intérêts IR sur la VARIATION = ROUND(droits × 0,2 % × mois) | B12: =ROUND(Sources!B18*0.002*Sources!B20,0) -> 2279 | C12: =ROUND(Sources!C18*0.002*Sources!C20,0) -> 885 | D12: =ROUND(Sources!D18*0.002*Sources!D20,0) -> 219 | E12: =B12-Sources!B19 -> 54 | F12: =C12-Sources!C19 -> 0 | G12: =D12-Sources!D19 -> 0 | H12: 2023 : le service a retenu 39 729 (IR après contrôle) : 2 225 au lieu de 2 279, 54 € en faveur du contribuable
A13: Intérêts IR sur l'IR APRÈS contrôle | B13: =ROUND(Sources!B16*0.002*Sources!B20,0) -> 2225 | C13: =ROUND(Sources!C16*0.002*Sources!C20,0) -> 887 | D13: =ROUND(Sources!D16*0.002*Sources!D20,0) -> 220 | E13: =B13-Sources!B19 -> 0 | F13: =C13-Sources!C19 -> 2 | G13: =D13-Sources!D19 -> 1 | H13: base effectivement utilisée en 2023
A14: TOTAL IR = droits + intérêts + majoration | B14: =Sources!B18+Sources!B19+Sources!B21 -> 59195 | C14: =Sources!C18+Sources!C19+Sources!C21 -> 39622 | D14: =Sources!D18+Sources!D19+Sources!D21 -> 38533 | E14: =B14-Sources!B22 -> 0 | F14: =C14-Sources!C22 -> 0 | G14: =D14-Sources!D22 -> 0
A15: PS = ROUND(base PS × taux appliqué) | B15: =ROUND(Sources!B23*Sources!B24,0) -> 16618 | C15: =ROUND(Sources!C23*Sources!C24,0) -> 11942 | D15: =ROUND(Sources!D23*Sources!D24,0) -> 12995 | E15: =B15-Sources!B25 -> 0 | F15: =C15-Sources!C25 -> 0 | G15: =D15-Sources!D25 -> 0 | H15: base SANS le 1,25 : réserve CC 2017-643/650 respectée
A16: PS au taux de droit commun 17,2 % | B16: =ROUND(Sources!B23*Barèmes!B13,0) -> 16618 | C16: =ROUND(Sources!C23*Barèmes!C13,0) -> 11942 | D16: =ROUND(Sources!D23*Barèmes!D13,0) -> 12017 | E16: =B16-Sources!B25 -> 0 | F16: =C16-Sources!C25 -> 0 | G16: =D16-Sources!D25 -> -978 | H16: 2025 : écart = effet du passage à 18,6 % (LFSS 2026 art. 12)
A17: Intérêts PS = ROUND(PS × 0,2 % × mois) | B17: =ROUND(Sources!B25*0.002*Sources!B20,0) -> 931 | C17: =ROUND(Sources!C25*0.002*Sources!C20,0) -> 382 | D17: =ROUND(Sources!D25*0.002*Sources!D20,0) -> 104 | E17: =B17-Sources!B26 -> 0 | F17: =C17-Sources!C26 -> -1 | G17: =D17-Sources!D26 -> 0 | H17: 2024 : 383 = arrondis séparés CSG / PSOL
A18: Majoration 40 % PS = ROUND(0,4 × PS) | B18: =ROUND(0.4*Sources!B25,0) -> 6647 | C18: =ROUND(0.4*Sources!C25,0) -> 4777 | D18: =ROUND(0.4*Sources!D25,0) -> 5198 | E18: =B18-Sources!B27 -> 0 | F18: =C18-Sources!C27 -> 0 | G18: =D18-Sources!D27 -> 0
A19: TOTAL PS = PS + intérêts + majoration | B19: =Sources!B25+Sources!B26+Sources!B27 -> 24196 | C19: =Sources!C25+Sources!C26+Sources!C27 -> 17102 | D19: =Sources!D25+Sources!D26+Sources!D27 -> 18297 | E19: =B19-Sources!B28 -> 0 | F19: =C19-Sources!C28 -> 0 | G19: =D19-Sources!D28 -> 0
A20: Supplément = TOTAL IR + TOTAL PS | B20: =Sources!B22+Sources!B28 -> 83391 | C20: =Sources!C22+Sources!C28 -> 56724 | D20: =Sources!D22+Sources!D28 -> 56830 | E20: =B20-Sources!B29 -> 0 | F20: =C20-Sources!C29 -> 0 | G20: =D20-Sources!D29 -> 0 | H20: soit 83 391 / 56 724 / 56 830 ; 3 ans 196 945
A21: Base PS vs base RCM (0 attendu ; 2025 : +1 €) | B21: =Sources!B23-Sources!B8 -> 0 | C21: =Sources!C23-Sources!C8 -> 0 | D21: =Sources!D23-Sources!D8 -> 1 | H21: 69 865 au lieu de 69 864 : 0,19 € de PS
A23: Total 3 ans du supplément recalculé | B23: =SUM(B20:D20) -> 196945 | E23: =B23-SUM(Sources!B29:D29) -> 0 | H23: attendu 196 945, écart 0

Sheet Decomposition
A1: DÉCOMPOSITION PAR NATURE (droits / majorations 40 % / intérêts) et taux effectifs sur la base distribuée.
A3: Nature | B3: 2023 | C3: 2024 | D3: 2025 | E3: 3 ans | F3: Règle
A4: IR (droits) | B4: =Sources!B18 -> 40693 | C4: =Sources!C18 -> 27669 | D4: =Sources!D18 -> 27367 | E4: =SUM(B4:D4) -> 95729 | F4: variation d'IR
A5: Prélèvements sociaux (droits) | B5: =Sources!B25 -> 16618 | C5: =Sources!C25 -> 11942 | D5: =Sources!D25 -> 12995 | E5: =SUM(B5:D5) -> 41555
A6: Droits (IR + PS) = | B6: =B4+B5 -> 57311 | C6: =C4+C5 -> 39611 | D6: =D4+D5 -> 40362 | E6: =SUM(B6:D6) -> 137284
A7: Majoration 40 % sur IR | B7: =Sources!B21 -> 16277 | C7: =Sources!C21 -> 11068 | D7: =Sources!D21 -> 10947 | E7: =SUM(B7:D7) -> 38292 | F7: art. 1729
A8: Majoration 40 % sur PS | B8: =Sources!B27 -> 6647 | C8: =Sources!C27 -> 4777 | D8: =Sources!D27 -> 5198 | E8: =SUM(B8:D8) -> 16622 | F8: art. 1729 (L. 136-6 III CSS : recouvrement comme en IR)
A9: Majorations 40 % (IR + PS) = | B9: =B7+B8 -> 22924 | C9: =C7+C8 -> 15845 | D9: =D7+D8 -> 16145 | E9: =SUM(B9:D9) -> 54914 | F9: enjeu de la décharge de la majoration au niveau du foyer
A10: Intérêts IR | B10: =Sources!B19 -> 2225 | C10: =Sources!C19 -> 885 | D10: =Sources!D19 -> 219 | E10: =SUM(B10:D10) -> 3329 | F10: art. 1727
A11: Intérêts PS | B11: =Sources!B26 -> 931 | C11: =Sources!C26 -> 383 | D11: =Sources!D26 -> 104 | E11: =SUM(B11:D11) -> 1418
A12: Intérêts (IR + PS) = | B12: =B10+B11 -> 3156 | C12: =C10+C11 -> 1268 | D12: =D10+D11 -> 323 | E12: =SUM(B12:D12) -> 4747
A13: Supplément notifié = droits + majorations + intérêts | B13: =B6+B9+B12 -> 83391 | C13: =C6+C9+C12 -> 56724 | D13: =D6+D9+D12 -> 56830 | E13: =SUM(B13:D13) -> 196945 | F13: contrôle : = Sources ligne 29
A14: Base RCM distribuée | B14: =Sources!B8 -> 96617 | C14: =Sources!C8 -> 69432 | D14: =Sources!D8 -> 69864 | E14: =SUM(B14:D14) -> 235913
A15: Taux effectif total = supplément ÷ base | B15: =B13/B14 -> 0.86310898 | C15: =C13/C14 -> 0.816972 | D15: =D13/D14 -> 0.81343754 | E15: =E13/E14 -> 0.83482046 | F15: CANON 83,5 % (3 ans)
A16: Taux hors majoration portée sur l'IR = (supplément − maj. IR) ÷ base | B16: =(B13-B7)/B14 -> 0.69463966 | C16: =(C13-C7)/C14 -> 0.65756424 | D16: =(D13-D7)/D14 -> 0.65674739 | E16: =(E13-E7)/E14 -> 0.67250639 | F16: CANON 67,3 % (3 ans) : ne retire que la majoration IR
A17: Taux hors TOUTES majorations (IR + PS) = (supplément − maj. IR − maj. PS) ÷ base | B17: =(B13-B9)/B14 -> 0.62584224 | C17: =(C13-C9)/C14 -> 0.58876311 | D17: =(D13-D9)/D14 -> 0.5823457 | E17: =(E13-E9)/E14 -> 0.60204821 | F17: 60,2 % (3 ans) : la majoration PS était cachée dans le « solde »
A18: Taux des droits seuls = (IR + PS) ÷ base | B18: =B6/B14 -> 0.59317718 | C18: =C6/C14 -> 0.57050063 | D18: =D6/D14 -> 0.57772243 | E18: =E6/E14 -> 0.58192639 | F18: 58,2 % (3 ans) : ce qui subsiste si la majoration tombe, hors intérêts
A19: IR ÷ base (taux marginal effectif de l'IR sur la distribution) | B19: =B4/B14 -> 0.42117847 | C19: =C4/C14 -> 0.39850501 | D19: =D4/D14 -> 0.3917182 | E19: =E4/E14 -> 0.40578094 | F19: 42,1 % / 39,9 % / 39,2 % : tranche à 41 % atteinte, QF plafonné
A20: Multiplication du revenu imposable (après ÷ avant) | B20: =Sources!B11/Sources!B10 -> 6.6868202 | C20: =Sources!C11/Sources!C10 -> 4.4543284 | D20: =Sources!D11/Sources!D10 -> 4.7098556 | F20: × 6,7 / × 4,5 / × 4,7

Sheet Scenarios CANON
A1: SCÉNARIOS CANON : la base distribuée tombe de 25 / 50 / 75 % (176 935 / 117 957 / 58 978 € sur 3 ans). Recalcul complet par formule, revenu hors distribution inchangé, 1,5 part, barème et plafonnement de l'année.
A3: Réduction de la reconstitution | B3: Année | C3: Base RCM | D3: Assiette × 1,25 | E3: IR (après − avant) | F3: PS (taux du service) | G3: Intérêts (IR + PS) | H3: Majorations 40 % (IR + PS) | I3: Supplément recalculé | J3: Supplément hors majoration 40 %
A4: 0 | B4: 2023 | C4: =ROUND(Sources!B4*(1-A4)/2,0) -> 96617 | D4: =ROUND(C4*1.25,0) -> 120771 | E4: =ROUND(MAX(SUMPRODUCT(((Sources!B10+D4)/Sources!B12>Barèmes!$B$4:$B$8)*((Sources!B10+D4)/Sources!B12-Barèmes!$B$4:$B$8)*Barèmes!$F$4:$F$8)*Sources!B12,SUMPRODUCT(((Sources!B10+D4)>Barèmes!$B$4:$B$8)*((Sources!B10+D4)-Barèmes!$B$4:$B$8)*Barèmes!$F$4:$F$8)-Barèmes!B11*(Sources!B12-1)*2),0)-(Sources!B17-Sources!B18) -> 40693 | F4: =ROUND(C4*Sources!B24,0) -> 16618 | G4: =ROUND(E4*0.002*Sources!B20,0)+ROUND(F4*0.002*Sources!B20,0) -> 3210 | H4: =ROUND(0.4*E4,0)+ROUND(0.4*F4,0) -> 22924 | I4: =E4+F4+G4+H4 -> 83445 | J4: =E4+F4+G4 -> 60521
A5: 0 | B5: 2024 | C5: =ROUND(Sources!C4*(1-A5)/2,0) -> 69432 | D5: =ROUND(C5*1.25,0) -> 86790 | E5: =ROUND(MAX(SUMPRODUCT(((Sources!C10+D5)/Sources!C12>Barèmes!$C$4:$C$8)*((Sources!C10+D5)/Sources!C12-Barèmes!$C$4:$C$8)*Barèmes!$F$4:$F$8)*Sources!C12,SUMPRODUCT(((Sources!C10+D5)>Barèmes!$C$4:$C$8)*((Sources!C10+D5)-Barèmes!$C$4:$C$8)*Barèmes!$F$4:$F$8)-Barèmes!C11*(Sources!C12-1)*2),0)-(Sources!C17-Sources!C18) -> 27669 | F5: =ROUND(C5*Sources!C24,0) -> 11942 | G5: =ROUND(E5*0.002*Sources!C20,0)+ROUND(F5*0.002*Sources!C20,0) -> 1267 | H5: =ROUND(0.4*E5,0)+ROUND(0.4*F5,0) -> 15845 | I5: =E5+F5+G5+H5 -> 56723 | J5: =E5+F5+G5 -> 40878
A6: 0 | B6: 2025 | C6: =ROUND(Sources!D4*(1-A6)/2,0) -> 69864 | D6: =ROUND(C6*1.25,0) -> 87330 | E6: =ROUND(MAX(SUMPRODUCT(((Sources!D10+D6)/Sources!D12>Barèmes!$D$4:$D$8)*((Sources!D10+D6)/Sources!D12-Barèmes!$D$4:$D$8)*Barèmes!$F$4:$F$8)*Sources!D12,SUMPRODUCT(((Sources!D10+D6)>Barèmes!$D$4:$D$8)*((Sources!D10+D6)-Barèmes!$D$4:$D$8)*Barèmes!$F$4:$F$8)-Barèmes!D11*(Sources!D12-1)*2),0)-(Sources!D17-Sources!D18) -> 27367 | F6: =ROUND(C6*Sources!D24,0) -> 12995 | G6: =ROUND(E6*0.002*Sources!D20,0)+ROUND(F6*0.002*Sources!D20,0) -> 323 | H6: =ROUND(0.4*E6,0)+ROUND(0.4*F6,0) -> 16145 | I6: =E6+F6+G6+H6 -> 56830 | J6: =E6+F6+G6 -> 40685
A7: Total 3 ans | C7: =SUM(C4:C6) -> 235913 | D7: =SUM(D4:D6) -> 294891 | E7: =SUM(E4:E6) -> 95729 | F7: =SUM(F4:F6) -> 41555 | G7: =SUM(G4:G6) -> 4800 | H7: =SUM(H4:H6) -> 54914 | I7: =SUM(I4:I6) -> 196998 | J7: =SUM(J4:J6) -> 142084
A8: 0.25 | B8: 2023 | C8: =ROUND(Sources!B4*(1-A8)/2,0) -> 72463 | D8: =ROUND(C8*1.25,0) -> 90579 | E8: =ROUND(MAX(SUMPRODUCT(((Sources!B10+D8)/Sources!B12>Barèmes!$B$4:$B$8)*((Sources!B10+D8)/Sources!B12-Barèmes!$B$4:$B$8)*Barèmes!$F$4:$F$8)*Sources!B12,SUMPRODUCT(((Sources!B10+D8)>Barèmes!$B$4:$B$8)*((Sources!B10+D8)-Barèmes!$B$4:$B$8)*Barèmes!$F$4:$F$8)-Barèmes!B11*(Sources!B12-1)*2),0)-(Sources!B17-Sources!B18) -> 28314 | F8: =ROUND(C8*Sources!B24,0) -> 12464 | G8: =ROUND(E8*0.002*Sources!B20,0)+ROUND(F8*0.002*Sources!B20,0) -> 2284 | H8: =ROUND(0.4*E8,0)+ROUND(0.4*F8,0) -> 16312 | I8: =E8+F8+G8+H8 -> 59374 | J8: =E8+F8+G8 -> 43062
A9: 0.25 | B9: 2024 | C9: =ROUND(Sources!C4*(1-A9)/2,0) -> 52074 | D9: =ROUND(C9*1.25,0) -> 65093 | E9: =ROUND(MAX(SUMPRODUCT(((Sources!C10+D9)/Sources!C12>Barèmes!$C$4:$C$8)*((Sources!C10+D9)/Sources!C12-Barèmes!$C$4:$C$8)*Barèmes!$F$4:$F$8)*Sources!C12,SUMPRODUCT(((Sources!C10+D9)>Barèmes!$C$4:$C$8)*((Sources!C10+D9)-Barèmes!$C$4:$C$8)*Barèmes!$F$4:$F$8)-Barèmes!C11*(Sources!C12-1)*2),0)-(Sources!C17-Sources!C18) -> 18773 | F9: =ROUND(C9*Sources!C24,0) -> 8957 | G9: =ROUND(E9*0.002*Sources!C20,0)+ROUND(F9*0.002*Sources!C20,0) -> 888 | H9: =ROUND(0.4*E9,0)+ROUND(0.4*F9,0) -> 11092 | I9: =E9+F9+G9+H9 -> 39710 | J9: =E9+F9+G9 -> 28618
A10: 0.25 | B10: 2025 | C10: =ROUND(Sources!D4*(1-A10)/2,0) -> 52398 | D10: =ROUND(C10*1.25,0) -> 65498 | E10: =ROUND(MAX(SUMPRODUCT(((Sources!D10+D10)/Sources!D12>Barèmes!$D$4:$D$8)*((Sources!D10+D10)/Sources!D12-Barèmes!$D$4:$D$8)*Barèmes!$F$4:$F$8)*Sources!D12,SUMPRODUCT(((Sources!D10+D10)>Barèmes!$D$4:$D$8)*((Sources!D10+D10)-Barèmes!$D$4:$D$8)*Barèmes!$F$4:$F$8)-Barèmes!D11*(Sources!D12-1)*2),0)-(Sources!D17-Sources!D18) -> 18416 | F10: =ROUND(C10*Sources!D24,0) -> 9746 | G10: =ROUND(E10*0.002*Sources!D20,0)+ROUND(F10*0.002*Sources!D20,0) -> 225 | H10: =ROUND(0.4*E10,0)+ROUND(0.4*F10,0) -> 11264 | I10: =E10+F10+G10+H10 -> 39651 | J10: =E10+F10+G10 -> 28387
A11: Total 3 ans | C11: =SUM(C8:C10) -> 176935 | D11: =SUM(D8:D10) -> 221170 | E11: =SUM(E8:E10) -> 65503 | F11: =SUM(F8:F10) -> 31167 | G11: =SUM(G8:G10) -> 3397 | H11: =SUM(H8:H10) -> 38668 | I11: =SUM(I8:I10) -> 138735 | J11: =SUM(J8:J10) -> 100067
A12: 0.5 | B12: 2023 | C12: =ROUND(Sources!B4*(1-A12)/2,0) -> 48309 | D12: =ROUND(C12*1.25,0) -> 60386 | E12: =ROUND(MAX(SUMPRODUCT(((Sources!B10+D12)/Sources!B12>Barèmes!$B$4:$B$8)*((Sources!B10+D12)/Sources!B12-Barèmes!$B$4:$B$8)*Barèmes!$F$4:$F$8)*Sources!B12,SUMPRODUCT(((Sources!B10+D12)>Barèmes!$B$4:$B$8)*((Sources!B10+D12)-Barèmes!$B$4:$B$8)*Barèmes!$F$4:$F$8)-Barèmes!B11*(Sources!B12-1)*2),0)-(Sources!B17-Sources!B18) -> 16014 | F12: =ROUND(C12*Sources!B24,0) -> 8309 | G12: =ROUND(E12*0.002*Sources!B20,0)+ROUND(F12*0.002*Sources!B20,0) -> 1362 | H12: =ROUND(0.4*E12,0)+ROUND(0.4*F12,0) -> 9730 | I12: =E12+F12+G12+H12 -> 35415 | J12: =E12+F12+G12 -> 25685
A13: 0.5 | B13: 2024 | C13: =ROUND(Sources!C4*(1-A13)/2,0) -> 34716 | D13: =ROUND(C13*1.25,0) -> 43395 | E13: =ROUND(MAX(SUMPRODUCT(((Sources!C10+D13)/Sources!C12>Barèmes!$C$4:$C$8)*((Sources!C10+D13)/Sources!C12-Barèmes!$C$4:$C$8)*Barèmes!$F$4:$F$8)*Sources!C12,SUMPRODUCT(((Sources!C10+D13)>Barèmes!$C$4:$C$8)*((Sources!C10+D13)-Barèmes!$C$4:$C$8)*Barèmes!$F$4:$F$8)-Barèmes!C11*(Sources!C12-1)*2),0)-(Sources!C17-Sources!C18) -> 11560 | F13: =ROUND(C13*Sources!C24,0) -> 5971 | G13: =ROUND(E13*0.002*Sources!C20,0)+ROUND(F13*0.002*Sources!C20,0) -> 561 | H13: =ROUND(0.4*E13,0)+ROUND(0.4*F13,0) -> 7012 | I13: =E13+F13+G13+H13 -> 25104 | J13: =E13+F13+G13 -> 18092
A14: 0.5 | B14: 2025 | C14: =ROUND(Sources!D4*(1-A14)/2,0) -> 34932 | D14: =ROUND(C14*1.25,0) -> 43665 | E14: =ROUND(MAX(SUMPRODUCT(((Sources!D10+D14)/Sources!D12>Barèmes!$D$4:$D$8)*((Sources!D10+D14)/Sources!D12-Barèmes!$D$4:$D$8)*Barèmes!$F$4:$F$8)*Sources!D12,SUMPRODUCT(((Sources!D10+D14)>Barèmes!$D$4:$D$8)*((Sources!D10+D14)-Barèmes!$D$4:$D$8)*Barèmes!$F$4:$F$8)-Barèmes!D11*(Sources!D12-1)*2),0)-(Sources!D17-Sources!D18) -> 11375 | F14: =ROUND(C14*Sources!D24,0) -> 6497 | G14: =ROUND(E14*0.002*Sources!D20,0)+ROUND(F14*0.002*Sources!D20,0) -> 143 | H14: =ROUND(0.4*E14,0)+ROUND(0.4*F14,0) -> 7149 | I14: =E14+F14+G14+H14 -> 25164 | J14: =E14+F14+G14 -> 18015
A15: Total 3 ans | C15: =SUM(C12:C14) -> 117957 | D15: =SUM(D12:D14) -> 147446 | E15: =SUM(E12:E14) -> 38949 | F15: =SUM(F12:F14) -> 20777 | G15: =SUM(G12:G14) -> 2066 | H15: =SUM(H12:H14) -> 23891 | I15: =SUM(I12:I14) -> 85683 | J15: =SUM(J12:J14) -> 61792
A16: 0.75 | B16: 2023 | C16: =ROUND(Sources!B4*(1-A16)/2,0) -> 24154 | D16: =ROUND(C16*1.25,0) -> 30193 | E16: =ROUND(MAX(SUMPRODUCT(((Sources!B10+D16)/Sources!B12>Barèmes!$B$4:$B$8)*((Sources!B10+D16)/Sources!B12-Barèmes!$B$4:$B$8)*Barèmes!$F$4:$F$8)*Sources!B12,SUMPRODUCT(((Sources!B10+D16)>Barèmes!$B$4:$B$8)*((Sources!B10+D16)-Barèmes!$B$4:$B$8)*Barèmes!$F$4:$F$8)-Barèmes!B11*(Sources!B12-1)*2),0)-(Sources!B17-Sources!B18) -> 6956 | F16: =ROUND(C16*Sources!B24,0) -> 4154 | G16: =ROUND(E16*0.002*Sources!B20,0)+ROUND(F16*0.002*Sources!B20,0) -> 623 | H16: =ROUND(0.4*E16,0)+ROUND(0.4*F16,0) -> 4444 | I16: =E16+F16+G16+H16 -> 16177 | J16: =E16+F16+G16 -> 11733
A17: 0.75 | B17: 2024 | C17: =ROUND(Sources!C4*(1-A17)/2,0) -> 17358 | D17: =ROUND(C17*1.25,0) -> 21698 | E17: =ROUND(MAX(SUMPRODUCT(((Sources!C10+D17)/Sources!C12>Barèmes!$C$4:$C$8)*((Sources!C10+D17)/Sources!C12-Barèmes!$C$4:$C$8)*Barèmes!$F$4:$F$8)*Sources!C12,SUMPRODUCT(((Sources!C10+D17)>Barèmes!$C$4:$C$8)*((Sources!C10+D17)-Barèmes!$C$4:$C$8)*Barèmes!$F$4:$F$8)-Barèmes!C11*(Sources!C12-1)*2),0)-(Sources!C17-Sources!C18) -> 5051 | F17: =ROUND(C17*Sources!C24,0) -> 2986 | G17: =ROUND(E17*0.002*Sources!C20,0)+ROUND(F17*0.002*Sources!C20,0) -> 258 | H17: =ROUND(0.4*E17,0)+ROUND(0.4*F17,0) -> 3214 | I17: =E17+F17+G17+H17 -> 11509 | J17: =E17+F17+G17 -> 8295
A18: 0.75 | B18: 2025 | C18: =ROUND(Sources!D4*(1-A18)/2,0) -> 17466 | D18: =ROUND(C18*1.25,0) -> 21833 | E18: =ROUND(MAX(SUMPRODUCT(((Sources!D10+D18)/Sources!D12>Barèmes!$D$4:$D$8)*((Sources!D10+D18)/Sources!D12-Barèmes!$D$4:$D$8)*Barèmes!$F$4:$F$8)*Sources!D12,SUMPRODUCT(((Sources!D10+D18)>Barèmes!$D$4:$D$8)*((Sources!D10+D18)-Barèmes!$D$4:$D$8)*Barèmes!$F$4:$F$8)-Barèmes!D11*(Sources!D12-1)*2),0)-(Sources!D17-Sources!D18) -> 4826 | F18: =ROUND(C18*Sources!D24,0) -> 3249 | G18: =ROUND(E18*0.002*Sources!D20,0)+ROUND(F18*0.002*Sources!D20,0) -> 65 | H18: =ROUND(0.4*E18,0)+ROUND(0.4*F18,0) -> 3230 | I18: =E18+F18+G18+H18 -> 11370 | J18: =E18+F18+G18 -> 8140
A19: Total 3 ans | C19: =SUM(C16:C18) -> 58978 | D19: =SUM(D16:D18) -> 73724 | E19: =SUM(E16:E18) -> 16833 | F19: =SUM(F16:F18) -> 10389 | G19: =SUM(G16:G18) -> 946 | H19: =SUM(H16:H18) -> 10888 | I19: =SUM(I16:I18) -> 39056 | J19: =SUM(J16:J18) -> 28168
A21: Lecture : la ligne « 0 % » reproduit le service (196 945 € ; écart 54 € sur les intérêts IR 2023 assis ici sur la variation). Les trois autres lignes sont le chiffrage du foyer si la reconstitution société est réduite ; l'IR est recalculé au barème sur (revenu avant contrôle + assiette réduite), diminué de l'écart constant entre l'IR barème et la variation retenue par le service (0 / 370 / 83 € : réductions et crédits inchangés) ; effet de tranche : la baisse est plus que proportionnelle.

Sheet Méthode
A1: MÉTHODE
A2: 1. Onglet Sources : chaque ligne est lue sur la proposition personnelle du 19/10/2026 (pages indiquées). Rien n'y est calculé.
A3: 2. Onglet Barèmes : paramètres de droit vérifiés (barème art. 197 par année de revenus, plafond de la demi-part, PS, intérêt 0,20 %/mois, 1,25, 40 %).
A4: 3. Onglet Controle : recalcul de chaque ligne du service par formule et écart. Résultat : toutes les lignes se recalculent à l'euro, sauf (a) intérêts IR 2023 assis sur 39 729 au lieu de 40 693 (54 € en faveur du contribuable), (b) base PS 2025 = 69 865 au lieu de 69 864 (0,19 €), (c) arrondis séparés CSG/PSOL sur les intérêts PS 2024 (1 €).
A5: 4. IR au barème : formule SUMPRODUCT sur les tranches (revenu ÷ parts, × parts), puis plafonnement du quotient familial : IR = MAX(IR avec QF ; IR 1 part − plafond × nombre de demi-parts). Avec 142 008 € de revenu et 1,5 part, le plafonnement joue : IR = 42 452 − 1 759 = 40 693 € (2023).
A6: 5. Onglet Decomposition : le supplément est éclaté en droits / majorations / intérêts. La majoration de 40 % frappe AUSSI les prélèvements sociaux (16 622 € sur 3 ans), ce que la lecture précédente (« solde ») ne montrait pas : majorations totales 54 914 €.
A7: 6. Onglet Scenarios : la base tombe de 25/50/75 % ; IR recalculé au barème à partir du revenu avant contrôle (effet de tranche), PS au taux appliqué par le service, intérêts et majorations recalculés.
A8: 7. Limites : le revenu « avant contrôle » est celui imprimé par le service (déclarations 2042 non au dossier) ; les réductions/crédits d'impôt (forfait scolarité 183 € en 2024, emploi à domicile) ne sont pas modélisés, ils n'affectent pas la variation.
