Workbook

Sheet Sources
A1: SOURCES PRIMAIRES — pièce R2-sur-versement-chiffrage
A4: 1. Volumes versés à la main par exercice (L) | B4: source : R1-sur-versement-fourchette.xlsx, onglet « Regimes de service » (dérivé de ANNEXE-C/D des ventes caisse)
A5: Exercice | B5: Vin au verre (L) | C5: Cocktails alcool (L) | D5: Spiritueux/apéritifs verre (L)
A6: 2022-2023 | B6: 371.77 | C6: 169.57 | D6: 22.58
A7: 2023-2024 | B7: 368.45 | C7: 178.08 | D7: 21.72
A8: 2024-2025 | B8: 379.69 | C8: 169.07 | D8: 18.39
A10: 2. Taux de la littérature (bornes documentées, lecture basse retenue)
A11: Vin au verre : Kerr 2008, volume moyen mesuré 6,18 oz = 18,28 cl ; rapporté à la dose de carte de 15 cl | B11: =18,28 / 15 -> #VALUE!
A12: Cocktails : Kerr 2008, 0,85 oz d'éthanol mesuré / 0,60 oz de référence | B12: =0,85 / 0,60 -> #VALUE!
A13: Spiritueux secs : Kerr 2008, 61 doses mesurées 1,51 oz / 1,50 oz de référence | B13: =1,51 / 1,50 -> #VALUE!
A15: 3. Prix de vente du verre de vin — ANNEXE-B1 (tickets 2022-2023) | B15: agrégat des lignes dont le libellé porte « verre » de vin
A16: Quantité de verres (unités) | B16: Recette TTC (€)
A17: 1533.7 | B17: 10308.42
A19: 4. Coefficient CA solides / CA liquides (digest 06, récapitulation par exercice)
A20: 2022-2023 | B20: 2.94
A21: 2023-2024 | B21: 3.02
A22: 2024-2025 | B22: 3.1
A24: 5. Abattements appliqués par le service avant coefficient (digest 06, §IV) | B24: remise 5% + pertes 5% + conso personnel 5% = 15% ; facteur résiduel 0,85

Sheet Calcul
A1: Exercice | B1: Vin verre vendu (L) | C1: Cocktails (L) | D1: Spiritueux (L) | E1: Taux verre | F1: Taux cockt. | G1: Taux spir. | H1: SV verre (L) | I1: SV cockt. (L) | J1: SV spir. (L) | K1: SV total (L)
A2: 2022-2023 | B2: =Sources!B6 -> 371.77 | C2: =Sources!C6 -> 169.57 | D2: =Sources!D6 -> 22.58 | E2: =18.28/15-1 -> 0.21866667 | F2: =0.85/0.6-1 -> 0.41666667 | G2: =1.51/1.5-1 -> 0.0066666667 | H2: =B2*E2 -> 81.293707 | I2: =C2*F2 -> 70.654167 | J2: =D2*G2 -> 0.15053333 | K2: =H2+I2+J2 -> 152.09841
A3: 2023-2024 | B3: =Sources!B7 -> 368.45 | C3: =Sources!C7 -> 178.08 | D3: =Sources!D7 -> 21.72 | E3: =18.28/15-1 -> 0.21866667 | F3: =0.85/0.6-1 -> 0.41666667 | G3: =1.51/1.5-1 -> 0.0066666667 | H3: =B3*E3 -> 80.567733 | I3: =C3*F3 -> 74.2 | J3: =D3*G3 -> 0.1448 | K3: =H3+I3+J3 -> 154.91253
A4: 2024-2025 | B4: =Sources!B8 -> 379.69 | C4: =Sources!C8 -> 169.07 | D4: =Sources!D8 -> 18.39 | E4: =18.28/15-1 -> 0.21866667 | F4: =0.85/0.6-1 -> 0.41666667 | G4: =1.51/1.5-1 -> 0.0066666667 | H4: =B4*E4 -> 83.025547 | I4: =C4*F4 -> 70.445833 | J4: =D4*G4 -> 0.1226 | K4: =H4+I4+J4 -> 153.59398
A5: TOTAL 3 exercices | B5: =SUM(B2:B4) -> 1119.91 | C5: =SUM(C2:C4) -> 516.72 | D5: =SUM(D2:D4) -> 62.69 | E5: =E2 -> 0.21866667 | F5: =F2 -> 0.41666667 | G5: =G2 -> 0.0066666667 | H5: =SUM(H2:H4) -> 244.88699 | I5: =SUM(I2:I4) -> 215.3 | J5: =SUM(J2:J4) -> 0.41793333 | K5: =SUM(K2:K4) -> 460.60492

Sheet Conversion EUR
A1: Exercice | B1: SV vin verre (L) | C1: Dose carte (L) | D1: Verres indûment reconstitués | E1: Prix moyen verre (€) | F1: CA liquides TTC retiré (€) | G1: Facteur abatt. | H1: Coef. solides | I1: CA total reconstitué en trop (€)
A2: 2022-2023 | B2: =Calcul!H2 -> 81.293707 | C2: 0.15 | D2: =B2/C2 -> 541.95804 | E2: =Sources!B17/Sources!A17 -> 6.7212753 | F2: =D2*E2 -> 3642.6492 | G2: 0.85 | H2: =Sources!B20 -> 2.94 | I2: =F2*G2*(1+H2) -> 12199.232
A3: 2023-2024 | B3: =Calcul!H3 -> 80.567733 | C3: 0.15 | D3: =B3/C3 -> 537.11822 | E3: =Sources!B17/Sources!A17 -> 6.7212753 | F3: =D3*E3 -> 3610.1195 | G3: 0.85 | H3: =Sources!B21 -> 3.02 | I3: =F3*G3*(1+H3) -> 12335.778
A4: 2024-2025 | B4: =Calcul!H4 -> 83.025547 | C4: 0.15 | D4: =B4/C4 -> 553.50364 | E4: =Sources!B17/Sources!A17 -> 6.7212753 | F4: =D4*E4 -> 3720.2504 | G4: 0.85 | H4: =Sources!B22 -> 3.1 | I4: =F4*G4*(1+H4) -> 12965.073
A5: TOTAL 3 exercices | B5: =SUM(B2:B4) -> 244.88699 | D5: =SUM(D2:D4) -> 1632.5799 | F5: =SUM(F2:F4) -> 10973.019 | I5: =SUM(I2:I4) -> 37500.083

Sheet Méthode
A1: MÉTHODE — d'où vient chaque chiffre
A3: Onglet Calcul :
A4: • Colonnes B,C,D : volumes versés à la main par régime et par exercice, repris de Sources (R1-sur-versement-fourchette).
A5: • Taux verre = 18,28/15 − 1 = +21,9 %. Kerr 2008 a MESURÉ un volume moyen de 6,18 oz = 18,28 cl ;
A6: rapporté à la dose de carte de 15 cl, le dépassement réel est +21,9 %, et NON +23,6 % (taux de Kerr
A7: contre un standard US de 5 oz = 14,79 cl). Appliquer +23,6 % à 15 cl donnerait 18,54 cl, soit plus que
A8: le volume que l'étude a observé : erreur de base corrigée ici.
A9: • Taux cocktails = 0,85/0,60 − 1 = +41,7 % (arrondi +42 % dans le mémoire). Éthanol mesuré par Kerr.
A10: • Taux spiritueux = 1,51/1,50 − 1 = +0,7 %. Kerr a mesuré 61 doses de spiritueux secs à 1,51 oz pour
A11: 1,50 de référence (« the only drink subtype to conform to the standard pour »). Le +20 % antérieur,
A12: tiré de Wansink, était contredit par cette mesure de terrain : corrigé à +0,7 %. Poste devenu négligeable.
A13: • SV (sur-versement) = volume × taux. SV total 3 exercices = 460,6 L.
... A29: • Les taux proviennent d'études étrangères ; aucune mesure de dose n'a été faite sur place.
