Workbook

Sheet Méthode
A1: R2 — Suppressions de notes (« DEL ») : rapprochement DEL vs encaissements, exercice 2022-2023
A3: OBJET. Pièce recalculée à formules, à partir des seules annexes de caisse remises au titre de l'article L. 47 A, II du LPF et
A4: effectivement présentes au dossier : ANNEXE-E1 (tpvevenement), F1 (règlements), G1 (journal TVA), H1 (liste des tickets),
A5: C1 (détail des tickets / prix pratiqués). Ces annexes couvrent le SEUL exercice 2022-2023. Les exercices 2023-2024 et
A6: 2024-2025 (annexes E2/E3, F2/F3, G2/G3, H2/H3, C2/C3) ne sont pas au dossier : aucune statistique n'est produite ici pour
A7: eux ; les montants que la proposition leur attribue (140 686,55 € et 97 071,51 €) sont repris tels quels, non vérifiés.
A9: SOURCE E1. Le fichier ANNEXE-E1 porte en dernière ligne un pied de totalisation (dateEven = « Nb lignes », mf_Number = 8014,
A10: amount = 193 005,09 €) qui n'est pas une opération : il est écarté. Restent 8 014 lignes « DEL », total 193 005,09 € —
A11: chiffres identiques au tableau de la proposition (8 014 / 193 005,09 € pour 2022-2023).
A13: CATALOGUE (onglet Catalogue_prix) : prix unitaires TTC pratiqués en 2022-2023, colonne 14 « Uprice_wt » de l'ANNEXE-C1
A14: (>0, dédoublonnés) : 258 valeurs.
A16: CLASSEMENT (onglet Sources_DEL). Pour chaque montant on cherche un prix p du catalogue et un entier k tels que
... A39: à lui seul, une preuve.

Sheet Calcul
A1: Agrégats — toutes les cellules de résultat sont des formules sur Sources_DEL
A2: Lignes « DEL » (total) | B2: =COUNT(Sources_DEL!$D$3:$D$8016)
A3: Montant total supprimé (€) | B3: =ROUND(SUM(Sources_DEL!$D$3:$D$8016),2)
A5: Lignes valant un prix unitaire de la carte | B5: =COUNTIF(Sources_DEL!$J$3:$J$8016,"carte")
A6: Euros des lignes « prix de la carte » | B6: =ROUND(SUMIF(Sources_DEL!$J$3:$J$8016,"carte",Sources_DEL!$D$3:$D$8016),2)
A7: Lignes valant une quantité entière × un prix | B7: =COUNTIF(Sources_DEL!$J$3:$J$8016,"multiple")
A8: Euros des lignes « multiple entier » | B8: =ROUND(SUMIF(Sources_DEL!$J$3:$J$8016,"multiple",Sources_DEL!$D$3:$D$8016),2)
A9: Lignes sans correspondance de prix | B9: =COUNTIF(Sources_DEL!$J$3:$J$8016,"none")
A10: Euros des lignes sans correspondance | B10: =ROUND(SUMIF(Sources_DEL!$J$3:$J$8016,"none",Sources_DEL!$D$3:$D$8016),2)
A12: Lignes expliquées par un prix (carte + multiple) | B12: =B5+B7
A13: Part en lignes | B13: =(B5+B7)/B2
A14: Part en euros (carte + multiple) | B14: =(B6+B8)/B3
A16: Contrôle : egal_montant = 1 là où un prix est trouvé | B16: =SUM(Sources_DEL!$I$3:$I$8016)
A17: … doit égaler (carte + multiple) lignes | B17: =B5+B7
A19: Lignes aberrantes de montant >= 1 000 € — nombre | B19: =COUNTIF(Sources_DEL!$D$3:$D$8016,">=1000")
A20: Lignes aberrantes >= 1 000 € — euros | B20: =ROUND(SUMIF(Sources_DEL!$D$3:$D$8016,">=1000",Sources_DEL!$D$3:$D$8016),2)
A21: Part en euros des 2 lignes aberrantes | B21: =B20/B3
A22: Euros « multiple » hors lignes aberrantes | B22: =ROUND(B8-B20,2)
A24: Médiane des montants supprimés (€) | B24: =MEDIAN(Sources_DEL!$D$3:$D$8016)
A25: Moyenne des montants supprimés (€) | B25: =ROUND(AVERAGE(Sources_DEL!$D$3:$D$8016),2)
A26: Valeurs distinctes prises par les montants « DEL » | B26: =SUMPRODUCT(1/COUNTIF(Sources_DEL!$D$3:$D$8016,Sources_DEL!$D$3:$D$8016))

Sheet Grosses_lignes
A1: Re-traçage des lignes « DEL » >= 1 000 € (exercice 2022-2023)
B3: 26/07/2022 (Z 3015) | C3: 07/08/2022 (Z 3026)
A4: Montant de la ligne « DEL » supprimée (€) | B4: 68993.1 | C4: 19600
A5: Décomposition apparente | B5: ≈ 27,40 € × 2 518 | C5: 100,00 € × 196
A6: Notes réellement encaissées ce jour-là | B6: 32 | C6: 31
A7: CA réellement encaissé ce jour (€) | B7: 2563.4 | C7: 2209.6
A8: Plus grosse note encaissée ce jour (€) | B8: 165.5 | C8: 131.2
A9: Plus grosse note de TOUT l'exercice 2022-2023 (€) | B9: 513.3 | C9: 513.3
A10: La ligne « DEL » vaut, en multiple du CA du jour | B10: =B4/B7 | C10: =C4/C7
A11: La ligne « DEL » vaut, en multiple de la plus grosse note | B11: =B4/B9 | C11: =C4/C9
A13: Conclusion : une recette de 68 993 € ou 19 600 € est impossible (plus grosse note de l'exercice : 513,30 €).
A14: Ces 2 lignes = erreurs de saisie sur la quantité, supprimées aussitôt ; elles pèsent pourtant 45,9 % du montant 2022-2023.

Sheet Univocite
A1: Mesure d'univocité de la clé (date + heure + montant + Z)
A3: Mesure | B3: Valeur
A4: Notes de l'exercice (ANNEXE-F1) | B4: 5658
A5: Totaux de note distincts | B5: 1637
A6: Notes partageant leur total avec une autre du même Z (moyenne/Z) | B6: 1.86
A7: Notes de l'exercice dont le total = 76,90 € | B7: 7
A8: Notes du Z 3052 (09/09/2022) dont le total = 76,90 € | B8: 1
A9: Notes du Z 3052 dont le total = 207,00 € | B9: 1
A10: Occurrences du montant 3,90 € parmi les lignes « DEL » | B10: 767
A11: Occurrences du montant 18,60 € parmi les lignes « DEL » | B11: 160
A13: Lecture : sur le Z 3052 les rafales de 12h07 et 12h23 n'ont qu'une note candidate chacune ; mais à l'échelle du
A14: fichier la clé n'est pas unique. Le rapprochement par rafale vaut comme indice, pas comme preuve par ligne.

Sheet Chainage_G1
A1: Totalisateur perpétuel « tot_sum » (ANNEXE-G1), trié croissant — contrôle de chaînage
A2: dateTicket | B2: noTicket | C2: no_zReport | D2: tot_ttc (€) | E2: tot_sum (€) | F2: delta | G2: ecart_vs_ttc
A3: 2022-04-14 | B3: 1 | C3: 2938 | D3: 67.4 | E3: 977807.18 | F3: =ROUND(E3-977739.78,2) | G3: =ROUND(F3-D3,2)
A4: 2022-04-14 | B4: 2 | C4: 2938 | D4: 20.9 | E4: 977828.08 | F4: =ROUND(E4-E3,2) | G4: =ROUND(F4-D4,2)
A5: 2022-04-14 | B5: 3 | C5: 2938 | D5: 61.4 | E5: 977889.48 | F5: =ROUND(E5-E4,2) | G5: =ROUND(F5-D5,2)
A6: 2022-04-14 | B6: 4 | C6: 2938 | D6: 23.8 | E6: 977913.28 | F6: =ROUND(E6-E5,2) | G6: =ROUND(F6-D6,2)
A7: 2022-04-14 | B7: 5 | C7: 2938 | D7: 23.8 | E7: 977937.08 | F7: =ROUND(E7-E6,2) | G7: =ROUND(F7-D7,2)
A8: 2022-04-14 | B8: 6 | C8: 2938 | D8: 33 | E8: 977970.08 | F8: =ROUND(E8-E7,2) | G8: =ROUND(F8-D8,2)
A9: 2022-04-14 | B9: 7 | C9: 2938 | D9: 59.4 | E9: 978029.48 | F9: =ROUND(E9-E8,2) | G9: =ROUND(F9-D9,2)
A10: 2022-04-14 | B10: 8 | C10: 2938 | D10: 19.9 | E10: 978049.38 | F10: =ROUND(E10-E9,2) | G10: =ROUND(F10-D10,2)
A11: 2022-04-14 | B11: 9 | C11: 2938 | D11: 19.9 | E11: 978069.28 | F11: =ROUND(E11-E10,2) | G11: =ROUND(F11-D11,2)
A12: 2022-04-14 | B12: 10 | C12: 2938 | D12: 52.2 | E12: 978121.48 | F12: =ROUND(E12-E11,2) | G12: =ROUND(F12-D12,2)
A13: 2022-04-14 | B13: 11 | C13: 2938 | D13: 29.35 | E13: 978150.83 | F13: =ROUND(E13-E12,2) | G13: =ROUND(F13-D13,2)
A14: 2022-04-14 | B14: 12 | C14: 2938 | D14: 29.35 | E14: 978180.18 | F14: =ROUND(E14-E13,2) | G14: =ROUND(F14-D14,2)
A15: 2022-04-14 | B15: 13 | C15: 2938 | D15: 26.45 | E15: 978206.63 | F15: =ROUND(E15-E14,2) | G15: =ROUND(F15-D15,2)
... A5660: 2023-03-31 | B5660: 21 | C5660: 3158 | D5660: 45.7 | E5660: 1381110.2 | F5660: =ROUND(E5660-E5659,2) | G5660: =ROUND(F5660-D5660,2)
A5662: Report à nouveau (A NOUVEAUX) | E5662: 977739.78
A5663: Compteur en fin de période (MAX) | E5663: =MAX(E3:E5660)
A5664: Progression du compteur (€) | E5664: =ROUND(MAX(E3:E5660)-977739.78,2)
A5665: Somme des tickets TTC (€) | E5665: =ROUND(SUM(D3:D5660),2)
A5666: Écart progression − somme TTC (€) | E5666: =ROUND((MAX(E3:E5660)-977739.78)-SUM(D3:D5660),2)
A5667: Nombre de tickets | E5667: =COUNT(D3:D5660)
A5668: Incréments négatifs (ruptures arrière) | E5668: =COUNTIF(F4:F5660,"<0")
A5669: Incréments ≠ TTC du ticket (|écart|>0) | E5669: =COUNTIF(G3:G5660,"<>0")

Sheet Reglements_F1
A1: Règlements 2022-2023 (ANNEXE-F1, hors pied « TOTAL ») — montant par mode
A2: mod_regl | B2: montant (€)
A3: CB | B3: 67.4
A4: CB | B4: 20.9
A5: CB | B5: 61.4
A6: CB | B6: 23.8
A7: CB | B7: 23.8
A8: CB | B8: 33
A9: CB | B9: 52.2
A10: CB | B10: 59.4
A11: CB | B11: 19.9
A12: CB | B12: 19.9
A13: CB | B13: 29.35
A14: CB | B14: 29.35
... A6428: CB | B6428: 45.9
A6430: TOTAL | B6430: =ROUND(SUM(B3:B6428),2)
A6431: CB | B6431: =ROUND(SUMIF($A$3:$A$6428,"CB",$B$3:$B$6428),2)
A6432: CHV | B6432: =ROUND(SUMIF($A$3:$A$6428,"CHV",$B$3:$B$6428),2)
A6433: TR | B6433: =ROUND(SUMIF($A$3:$A$6428,"TR",$B$3:$B$6428),2)
A6434: CHQ | B6434: =ROUND(SUMIF($A$3:$A$6428,"CHQ",$B$3:$B$6428),2)
A6435: ESP | B6435: =ROUND(SUMIF($A$3:$A$6428,"ESP",$B$3:$B$6428),2)
A6436: Espèces (ESP) — part | B6436: =SUMIF($A$3:$A$6428,"ESP",$B$3:$B$6428)/SUM(B3:B6428)
A6437: Bancarisé (hors ESP) — part | B6437: =1-SUMIF($A$3:$A$6428,"ESP",$B$3:$B$6428)/SUM(B3:B6428)
A6438: Montant DEL 2022-2023 / espèces encaissées (×) | B6438: =ROUND(Calcul!B3/SUMIF($A$3:$A$6428,"ESP",$B$3:$B$6428),1)

Sheet Tickets_zero
A1: Tickets clôturés à 0,00 € (ANNEXE-H1) et jumeau encaissé même n°/même jour
A2: date_ticket | B2: no_ticket | C2: tot_ttc | D2: jumeau
A3: 2022-04-14 | B3: 1 | C3: 0 | D3: 1
A4: 2022-04-14 | B4: 2 | C4: 0 | D4: 1
A5: 2022-04-14 | B5: 3 | C5: 0 | D5: 1
A6: 2022-04-14 | B6: 5 | C6: 0 | D6: 1
A7: 2022-04-14 | B7: 4 | C7: 0 | D7: 1
A8: 2022-04-14 | B8: 6 | C8: 0 | D8: 1
A9: 2022-04-14 | B9: 7 | C9: 0 | D9: 1
A10: 2022-04-14 | B10: 9 | C10: 0 | D10: 1
A11: 2022-04-14 | B11: 8 | C11: 0 | D11: 1
A12: 2022-04-15 | B12: 1 | C12: 0 | D12: 1
A13: 2022-04-15 | B13: 2 | C13: 0 | D13: 1
A14: 2022-04-15 | B14: 3 | C14: 0 | D14: 1
... A1192: 2023-03-30 | B1192: 1 | C1192: 0 | D1192: 1
A1194: Tickets à 0,00 € | D1194: =COUNT(D3:D1192)
A1195: … avec jumeau | D1195: =SUM(D3:D1192)
A1196: … orphelins (sans jumeau) | D1196: =COUNT(D3:D1192)-SUM(D3:D1192)

Sheet Catalogue_prix
A1: Prix unitaires TTC pratiqués 2022-2023 (ANNEXE-C1 col.14, >0, dédoublonnés)
A3: # | B3: Prix TTC (€)
A4: 1 | B4: 0.4
A5: 2 | B5: 0.5
A6: 3 | B6: 0.8
A7: 4 | B7: 0.9
A8: 5 | B8: 1.1
A9: 6 | B9: 1.2
A10: 7 | B10: 1.4
A11: 8 | B11: 1.5
A12: 9 | B12: 1.6
A13: 10 | B13: 1.7
A14: 11 | B14: 1.8
A15: 12 | B15: 1.9
... A261: 258 | B261: 100
A263: Nombre de prix distincts : | B263: =COUNT($B$4:$B$261)

Sheet Sources_DEL
A1: Lignes « DEL » 2022-2023 (ANNEXE-E1, pied « Nb lignes » écarté)
A2: dateEven | B2: heureEven | C2: no_zEport | D2: amount (€) | E2: id | F2: base_price (€) | G2: mult_k | H2: verif | I2: egal_montant | J2: categorie
A3: 2022-04-14 | B3: 11:26 | C3: 2938 | D3: 19 | E3: 36682 | F3: 19 | G3: 1 | H3: =ROUND(G3*F3,2) | I3: =IF(ROUND(H3-D3,2)=0,1,0) | J3: =IF(F3="","none",IF(G3=1,"carte","multiple"))
A4: 2022-04-14 | B4: 11:59 | C4: 2938 | D4: 3.4 | E4: 36683 | F4: 3.4 | G4: 1 | H4: =ROUND(G4*F4,2) | I4: =IF(ROUND(H4-D4,2)=0,1,0) | J4: =IF(F4="","none",IF(G4=1,"carte","multiple"))
A5: 2022-04-14 | B5: 12:06 | C5: 2938 | D5: 19.9 | E5: 36684 | F5: 19.9 | G5: 1 | H5: =ROUND(G5*F5,2) | I5: =IF(ROUND(H5-D5,2)=0,1,0) | J5: =IF(F5="","none",IF(G5=1,"carte","multiple"))
A6: 2022-04-14 | B6: 12:25 | C6: 2938 | D6: 22 | E6: 36685 | F6: 0.4 | G6: 55 | H6: =ROUND(G6*F6,2) | I6: =IF(ROUND(H6-D6,2)=0,1,0) | J6: =IF(F6="","none",IF(G6=1,"carte","multiple"))
A7: 2022-04-14 | B7: 12:25 | C7: 2938 | D7: 3.9 | E7: 36686 | F7: 3.9 | G7: 1 | H7: =ROUND(G7*F7,2) | I7: =IF(ROUND(H7-D7,2)=0,1,0) | J7: =IF(F7="","none",IF(G7=1,"carte","multiple"))
A8: 2022-04-14 | B8: 12:25 | C8: 2938 | D8: 4 | E8: 36687 | F8: 4 | G8: 1 | H8: =ROUND(G8*F8,2) | I8: =IF(ROUND(H8-D8,2)=0,1,0) | J8: =IF(F8="","none",IF(G8=1,"carte","multiple"))
A9: 2022-04-14 | B9: 13:35 | C9: 2938 | D9: 7.6 | E9: 36688 | F9: 7.6 | G9: 1 | H9: =ROUND(G9*F9,2) | I9: =IF(ROUND(H9-D9,2)=0,1,0) | J9: =IF(F9="","none",IF(G9=1,"carte","multiple"))
A10: 2022-04-14 | B10: 13:35 | C10: 2938 | D10: 19 | E10: 36689 | F10: 19 | G10: 1 | H10: =ROUND(G10*F10,2) | I10: =IF(ROUND(H10-D10,2)=0,1,0) | J10: =IF(F10="","none",IF(G10=1,"carte","multiple"))
A11: 2022-04-14 | B11: 13:35 | C11: 2938 | D11: 17.6 | E11: 36690 | F11: 17.6 | G11: 1 | H11: =ROUND(G11*F11,2) | I11: =IF(ROUND(H11-D11,2)=0,1,0) | J11: =IF(F11="","none",IF(G11=1,"carte","multiple"))
A12: 2022-04-14 | B12: 13:35 | C12: 2938 | D12: 4.4 | E12: 36691 | F12: 0.4 | G12: 11 | H12: =ROUND(G12*F12,2) | I12: =IF(ROUND(H12-D12,2)=0,1,0) | J12: =IF(F12="","none",IF(G12=1,"carte","multiple"))
A13: 2022-04-14 | B13: 18:35 | C13: 2938 | D13: 16.9 | E13: 36693 | F13: 16.9 | G13: 1 | H13: =ROUND(G13*F13,2) | I13: =IF(ROUND(H13-D13,2)=0,1,0) | J13: =IF(F13="","none",IF(G13=1,"carte","multiple"))
A14: 2022-04-14 | B14: 18:35 | C14: 2938 | D14: 15.9 | E14: 36694 | F14: 15.9 | G14: 1 | H14: =ROUND(G14*F14,2) | I14: =IF(ROUND(H14-D14,2)=0,1,0) | J14: =IF(F14="","none",IF(G14=1,"carte","multiple"))
... A353: 2022-04-22 | B353: 18:13 | C353: 2945 | D353: 11 | E353: 37054 | F353: 11 | G353: 1 | H353: =ROUND(G353*F353,2) | I353: =IF(ROUND(H353-D353,2)=0,1,0) | J353: =IF(F353="","none",IF(G353=1,"carte","multiple"))
A354: 2022-04-22 | B354: 18:20 | C354: 2945 | D354: 0 | E354: 37055 | J354: =IF(F354="","none",IF(G354=1,"carte","multiple"))
A355: 2022-04-22 | B355: 18:20 | C355: 2945 | D355: 19 | E355: 37056 | F355: 19 | G355: 1 | H355: =ROUND(G355*F355,2) | I355: =IF(ROUND(H355-D355,2)=0,1,0) | J355: =IF(F355="","none",IF(G355=1,"carte","multiple"))
A356: 2022-04-22 | B356: 18:57 | C356: 2945 | D356: 4.2 | E356: 37057 | F356: 4.2 | G356: 1 | H356: =ROUND(G356*F356,2) | I356: =IF(ROUND(H356-D356,2)=0,1,0) | J356: =IF(F356="","none",IF(G356=1,"carte","multiple"))
A357: 2022-04-22 | B357: 18:57 | C357: 2945 | D357: 7.8 | E357: 37058 | F357: 7.8 | G357: 1 | H357: =ROUND(G357*F357,2) | I357: =IF(ROUND(H357-D357,2)=0,1,0) | J357: =IF(F357="","none",IF(G357=1,"carte","multiple"))
A358: 2022-04-22 | B358: 19:27 | C358: 2945 | D358: 17.6 | E358: 37059 | F358: 17.6 | G358: 1 | H358: =ROUND(G358*F358,2) | I358: =IF(ROUND(H358-D358,2)=0,1,0) | J358: =IF(F358="","none",IF(G358=1,"carte","multiple"))
A359: 2022-04-22 | B359: 19:28 | C359: 2945 | D359: 19 | E359: 37060 | F359: 19 | G359: 1 | H359: =ROUND(G359*F359,2) | I359: =IF(ROUND(H359-D359,2)=0,1,0) | J359: =IF(F359="","none",IF(G359=1,"carte","multiple"))
A360: 2022-04-22 | B360: 19:43 | C360: 2945 | D360: 3.9 | E360: 37061 | F360: 3.9 | G360: 1 | H360: =ROUND(G360*F360,2) | I360: =IF(ROUND(H360-D360,2)=0,1,0) | J360: =IF(F360="","none",IF(G360=1,"carte","multiple"))
A361: 2022-04-22 | B361: 20:56 | C361: 2945 | D361: 14.4 | E361: 37062 | F361: 0.4 | G361: 36 | H361: =ROUND(G361*F361,2) | I361: =IF(ROUND(H361-D361,2)=0,1,0) | J361: =IF(F361="","none",IF(G361=1,"carte","multiple"))
A362: 2022-04-22 | B362: 20:56 | C362: 2945 | D362: 4.4 | E362: 37063 | F362: 0.4 | G362: 11 | H362: =ROUND(G362*F362,2) | I362: =IF(ROUND(H362-D362,2)=0,1,0) | J362: =IF(F362="","none",IF(G362=1,"carte","multiple"))
A363: 2022-04-22 | B363: 20:56 | C363: 2945 | D363: 10.4 | E363: 37064 | F363: 0.4 | G363: 26 | H363: =ROUND(G363*F363,2) | I363: =IF(ROUND(H363-D363,2)=0,1,0) | J363: =IF(F363="","none",IF(G363=1,"carte","multiple"))
A364: 2022-04-22 | B364: 20:56 | C364: 2945 | D364: 3.6 | E364: 37065 | F364: 3.6 | G364: 1 | H364: =ROUND(G364*F364,2) | I364: =IF(ROUND(H364-D364,2)=0,1,0) | J364: =IF(F364="","none",IF(G364=1,"carte","multiple"))
A365: 2022-04-22 | B365: 20:56 | C365: 2945 | D365: 19.4 | E365: 37066 | F365: 9.7 | G365: 2 | H365: =ROUND(G365*F365,2) | I365: =IF(ROUND(H365-D365,2)=0,1,0) | J365: =IF(F365="","none",IF(G365=1,"carte","multiple"))
A366: 2022-04-22 | B366: 20:56 | C366: 2945 | D366: 5.9 | E366: 37067 | F366: 5.9 | G366: 1 | H366: =ROUND(G366*F366,2) | I366: =IF(ROUND(H366-D366,2)=0,1,0) | J366: =IF(F366="","none",IF(G366=1,"carte","multiple"))
... A690: 2022-05-06 | B690: 20:08 | C690: 2954 | D690: 8.4 | E690: 37420 | F690: 8.4 | G690: 1 | H690: =ROUND(G690*F690,2) | I690: =IF(ROUND(H690-D690,2)=0,1,0) | J690: =IF(F690="","none",IF(G690=1,"carte","multiple"))
A691: 2022-05-06 | B691: 20:17 | C691: 2954 | D691: 0 | E691: 37422 | J691: =IF(F691="","none",IF(G691=1,"carte","multiple"))
A692: 2022-05-06 | B692: 20:17 | C692: 2954 | D692: 17.6 | E692: 37423 | F692: 17.6 | G692: 1 | H692: =ROUND(G692*F692,2) | I692: =IF(ROUND(H692-D692,2)=0,1,0) | J692: =IF(F692="","none",IF(G692=1,"carte","multiple"))
A693: 2022-05-06 | B693: 20:17 | C693: 2954 | D693: 17.6 | E693: 37424 | F693: 17.6 | G693: 1 | H693: =ROUND(G693*F693,2) | I693: =IF(ROUND(H693-D693,2)=0,1,0) | J693: =IF(F693="","none",IF(G693=1,"carte","multiple"))
A694: 2022-05-06 | B694: 20:17 | C694: 2954 | D694: 0 | E694: 37425 | J694: =IF(F694="","none",IF(G694=1,"carte","multiple"))
A695: 2022-05-06 | B695: 20:30 | C695: 2954 | D695: 3.9 | E695: 37426 | F695: 3.9 | G695: 1 | H695: =ROUND(G695*F695,2) | I695: =IF(ROUND(H695-D695,2)=0,1,0) | J695: =IF(F695="","none",IF(G695=1,"carte","multiple"))
A696: 2022-05-06 | B696: 20:30 | C696: 2954 | D696: 6.5 | E696: 37427 | F696: 6.5 | G696: 1 | H696: =ROUND(G696*F696,2) | I696: =IF(ROUND(H696-D696,2)=0,1,0) | J696: =IF(F696="","none",IF(G696=1,"carte","multiple"))
A697: 2022-05-06 | B697: 20:37 | C697: 2954 | D697: 7.9 | E697: 37428 | F697: 7.9 | G697: 1 | H697: =ROUND(G697*F697,2) | I697: =IF(ROUND(H697-D697,2)=0,1,0) | J697: =IF(F697="","none",IF(G697=1,"carte","multiple"))
A698: 2022-05-06 | B698: 20:37 | C698: 2954 | D698: 39.5 | E698: 37429 | F698: 39.5 | G698: 1 | H698: =ROUND(G698*F698,2) | I698: =IF(ROUND(H698-D698,2)=0,1,0) | J698: =IF(F698="","none",IF(G698=1,"carte","multiple"))
A699: 2022-05-07 | B699: 10:38 | C699: 2955 | D699: 5.9 | E699: 37432 | F699: 5.9 | G699: 1 | H699: =ROUND(G699*F699,2) | I699: =IF(ROUND(H699-D699,2)=0,1,0) | J699: =IF(F699="","none",IF(G699=1,"carte","multiple"))
A700: 2022-05-07 | B700: 11:17 | C700: 2955 | D700: 15 | E700: 37433 | F700: 15 | G700: 1 | H700: =ROUND(G700*F700,2) | I700: =IF(ROUND(H700-D700,2)=0,1,0) | J700: =IF(F700="","none",IF(G700=1,"carte","multiple"))
A701: 2022-05-07 | B701: 11:17 | C701: 2955 | D701: 19.9 | E701: 37434 | F701: 19.9 | G701: 1 | H701: =ROUND(G701*F701,2) | I701: =IF(ROUND(H701-D701,2)=0,1,0) | J701: =IF(F701="","none",IF(G701=1,"carte","multiple"))
A702: 2022-05-07 | B702: 11:17 | C702: 2955 | D702: 19.9 | E702: 37435 | F702: 19.9 | G702: 1 | H702: =ROUND(G702*F702,2) | I702: =IF(ROUND(H702-D702,2)=0,1,0) | J702: =IF(F702="","none",IF(G702=1,"carte","multiple"))
A703: 2022-05-07 | B703: 11:32 | C703: 2955 | D703: 2.2 | E703: 37436 | F703: 2.2 | G703: 1 | H703: =ROUND(G703*F703,2) | I703: =IF(ROUND(H703-D703,2)=0,1,0) | J703: =IF(F703="","none",IF(G703=1,"carte","multiple"))
A704: 2022-05-07 | B704: 11:32 | C704: 2955 | D704: 7.5 | E704: 37437 | F704: 7.5 | G704: 1 | H704: =ROUND(G704*F704,2) | I704: =IF(ROUND(H704-D704,2)=0,1,0) | J704: =IF(F704="","none",IF(G704=1,"carte","multiple"))
A705: 2022-05-07 | B705: 11:32 | C705: 2955 | D705: 7.2 | E705: 37438 | F705: 7.2 | G705: 1 | H705: =ROUND(G705*F705,2) | I705: =IF(ROUND(H705-D705,2)=0,1,0) | J705: =IF(F705="","none",IF(G705=1,"carte","multiple"))
A706: 2022-05-07 | B706: 11:32 | C706: 2955 | D706: 17.6 | E706: 37439 | F706: 17.6 | G706: 1 | H706: =ROUND(G706*F706,2) | I706: =IF(ROUND(H706-D706,2)=0,1,0) | J706: =IF(F706="","none",IF(G706=1,"carte","multiple"))
... A718: 2022-05-07 | B718: 17:33 | C718: 2955 | D718: 5.2 | E718: 37452 | F718: 5.2 | G718: 1 | H718: =ROUND(G718*F718,2) | I718: =IF(ROUND(H718-D718,2)=0,1,0) | J718: =IF(F718="","none",IF(G718=1,"carte","multiple"))
A719: 2022-05-07 | B719: 18:33 | C719: 2955 | D719: 0 | E719: 37454 | J719: =IF(F719="","none",IF(G719=1,"carte","multiple"))
A720: 2022-05-07 | B720: 18:33 | C720: 2955 | D720: 0 | E720: 37455 | J720: =IF(F720="","none",IF(G720=1,"carte","multiple"))
A721: 2022-05-07 | B721: 18:33 | C721: 2955 | D721: 17.6 | E721: 37456 | F721: 17.6 | G721: 1 | H721: =ROUND(G721*F721,2) | I721: =IF(ROUND(H721-D721,2)=0,1,0) | J721: =IF(F721="","none",IF(G721=1,"carte","multiple"))
A722: 2022-05-07 | B722: 18:33 | C722: 2955 | D722: 27.8 | E722: 37457 | F722: 27.8 | G722: 1 | H722: =ROUND(G722*F722,2) | I722: =IF(ROUND(H722-D722,2)=0,1,0) | J722: =IF(F722="","none",IF(G722=1,"carte","multiple"))
A723: 2022-05-07 | B723: 19:44 | C723: 2955 | D723: 10.4 | E723: 37458 | F723: 0.4 | G723: 26 | H723: =ROUND(G723*F723,2) | I723: =IF(ROUND(H723-D723,2)=0,1,0) | J723: =IF(F723="","none",IF(G723=1,"carte","multiple"))
A724: 2022-05-07 | B724: 19:44 | C724: 2955 | D724: 3.9 | E724: 37459 | F724: 3.9 | G724: 1 | H724: =ROUND(G724*F724,2) | I724: =IF(ROUND(H724-D724,2)=0,1,0) | J724: =IF(F724="","none",IF(G724=1,"carte","multiple"))
A725: 2022-05-07 | B725: 19:44 | C725: 2955 | D725: 29.9 | E725: 37460 | F725: 29.9 | G725: 1 | H725: =ROUND(G725*F725,2) | I725: =IF(ROUND(H725-D725,2)=0,1,0) | J725: =IF(F725="","none",IF(G725=1,"carte","multiple"))
A726: 2022-05-07 | B726: 19:44 | C726: 2955 | D726: 19 | E726: 37461 | F726: 19 | G726: 1 | H726: =ROUND(G726*F726,2) | I726: =IF(ROUND(H726-D726,2)=0,1,0) | J726: =IF(F726="","none",IF(G726=1,"carte","multiple"))
A727: 2022-05-07 | B727: 19:44 | C727: 2955 | D727: 59.8 | E727: 37462 | F727: 4.6 | G727: 13 | H727: =ROUND(G727*F727,2) | I727: =IF(ROUND(H727-D727,2)=0,1,0) | J727: =IF(F727="","none",IF(G727=1,"carte","multiple"))
A728: 2022-05-07 | B728: 19:44 | C728: 2955 | D728: 32 | E728: 37463 | F728: 32 | G728: 1 | H728: =ROUND(G728*F728,2) | I728: =IF(ROUND(H728-D728,2)=0,1,0) | J728: =IF(F728="","none",IF(G728=1,"carte","multiple"))
A729: 2022-05-07 | B729: 19:49 | C729: 2955 | D729: 2 | E729: 37464 | F729: 2 | G729: 1 | H729: =ROUND(G729*F729,2) | I729: =IF(ROUND(H729-D729,2)=0,1,0) | J729: =IF(F729="","none",IF(G729=1,"carte","multiple"))
A730: 2022-05-07 | B730: 19:49 | C730: 2955 | D730: 11.7 | E730: 37465 | F730: 0.9 | G730: 13 | H730: =ROUND(G730*F730,2) | I730: =IF(ROUND(H730-D730,2)=0,1,0) | J730: =IF(F730="","none",IF(G730=1,"carte","multiple"))
A731: 2022-05-07 | B731: 19:49 | C731: 2955 | D731: 3.9 | E731: 37466 | F731: 3.9 | G731: 1 | H731: =ROUND(G731*F731,2) | I731: =IF(ROUND(H731-D731,2)=0,1,0) | J731: =IF(F731="","none",IF(G731=1,"carte","multiple"))
A732: 2022-05-07 | B732: 19:49 | C732: 2955 | D732: 3.9 | E732: 37467 | F732: 3.9 | G732: 1 | H732: =ROUND(G732*F732,2) | I732: =IF(ROUND(H732-D732,2)=0,1,0) | J732: =IF(F732="","none",IF(G732=1,"carte","multiple"))
... A1241: 2022-05-25 | B1241: 19:59 | C1241: 2967 | D1241: 29.9 | E1241: 38020 | F1241: 29.9 | G1241: 1 | H1241: =ROUND(G1241*F1241,2) | I1241: =IF(ROUND(H1241-D1241,2)=0,1,0) | J1241: =IF(F1241="","none",IF(G1241=1,"carte","multiple"))
A1242: 2022-05-25 | B1242: 20:20 | C1242: 2967 | D1242: 5.45 | E1242: 38021 | J1242: =IF(F1242="","none",IF(G1242=1,"carte","multiple"))
A1243: 2022-05-25 | B1243: 20:20 | C1243: 2967 | D1243: 4 | E1243: 38022 | F1243: 4 | G1243: 1 | H1243: =ROUND(G1243*F1243,2) | I1243: =IF(ROUND(H1243-D1243,2)=0,1,0) | J1243: =IF(F1243="","none",IF(G1243=1,"carte","multiple"))
A1244: 2022-05-25 | B1244: 20:20 | C1244: 2967 | D1244: 59.8 | E1244: 38023 | F1244: 4.6 | G1244: 13 | H1244: =ROUND(G1244*F1244,2) | I1244: =IF(ROUND(H1244-D1244,2)=0,1,0) | J1244: =IF(F1244="","none",IF(G1244=1,"carte","multiple"))
A1245: 2022-05-25 | B1245: 20:20 | C1245: 2967 | D1245: 13.4 | E1245: 38024 | F1245: 13.4 | G1245: 1 | H1245: =ROUND(G1245*F1245,2) | I1245: =IF(ROUND(H1245-D1245,2)=0,1,0) | J1245: =IF(F1245="","none",IF(G1245=1,"carte","multiple"))
A1246: 2022-05-25 | B1246: 20:20 | C1246: 2967 | D1246: 3.8 | E1246: 38025 | F1246: 3.8 | G1246: 1 | H1246: =ROUND(G1246*F1246,2) | I1246: =IF(ROUND(H1246-D1246,2)=0,1,0) | J1246: =IF(F1246="","none",IF(G1246=1,"carte","multiple"))
A1247: 2022-05-25 | B1247: 20:25 | C1247: 2967 | D1247: 19 | E1247: 38026 | F1247: 19 | G1247: 1 | H1247: =ROUND(G1247*F1247,2) | I1247: =IF(ROUND(H1247-D1247,2)=0,1,0) | J1247: =IF(F1247="","none",IF(G1247=1,"carte","multiple"))
A1248: 2022-05-25 | B1248: 20:25 | C1248: 2967 | D1248: 4.9 | E1248: 38027 | F1248: 4.9 | G1248: 1 | H1248: =ROUND(G1248*F1248,2) | I1248: =IF(ROUND(H1248-D1248,2)=0,1,0) | J1248: =IF(F1248="","none",IF(G1248=1,"carte","multiple"))
A1249: 2022-05-25 | B1249: 20:25 | C1249: 2967 | D1249: 2.2 | E1249: 38028 | F1249: 2.2 | G1249: 1 | H1249: =ROUND(G1249*F1249,2) | I1249: =IF(ROUND(H1249-D1249,2)=0,1,0) | J1249: =IF(F1249="","none",IF(G1249=1,"carte","multiple"))
A1250: 2022-05-25 | B1250: 20:37 | C1250: 2967 | D1250: 4.2 | E1250: 38029 | F1250: 4.2 | G1250: 1 | H1250: =ROUND(G1250*F1250,2) | I1250: =IF(ROUND(H1250-D1250,2)=0,1,0) | J1250: =IF(F1250="","none",IF(G1250=1,"carte","multiple"))
A1251: 2022-05-25 | B1251: 20:37 | C1251: 2967 | D1251: 7.5 | E1251: 38030 | F1251: 7.5 | G1251: 1 | H1251: =ROUND(G1251*F1251,2) | I1251: =IF(ROUND(H1251-D1251,2)=0,1,0) | J1251: =IF(F1251="","none",IF(G1251=1,"carte","multiple"))
A1252: 2022-05-25 | B1252: 20:37 | C1252: 2967 | D1252: 28 | E1252: 38031 | F1252: 28 | G1252: 1 | H1252: =ROUND(G1252*F1252,2) | I1252: =IF(ROUND(H1252-D1252,2)=0,1,0) | J1252: =IF(F1252="","none",IF(G1252=1,"carte","multiple"))
A1253: 2022-05-25 | B1253: 20:37 | C1253: 2967 | D1253: 17.6 | E1253: 38032 | F1253: 17.6 | G1253: 1 | H1253: =ROUND(G1253*F1253,2) | I1253: =IF(ROUND(H1253-D1253,2)=0,1,0) | J1253: =IF(F1253="","none",IF(G1253=1,"carte","multiple"))
A1254: 2022-05-25 | B1254: 20:37 | C1254: 2967 | D1254: 17.6 | E1254: 38033 | F1254: 17.6 | G1254: 1 | H1254: =ROUND(G1254*F1254,2) | I1254: =IF(ROUND(H1254-D1254,2)=0,1,0) | J1254: =IF(F1254="","none",IF(G1254=1,"carte","multiple"))
... A1294: 2022-05-26 | B1294: 19:45 | C1294: 2968 | D1294: 19.9 | E1294: 38076 | F1294: 19.9 | G1294: 1 | H1294: =ROUND(G1294*F1294,2) | I1294: =IF(ROUND(H1294-D1294,2)=0,1,0) | J1294: =IF(F1294="","none",IF(G1294=1,"carte","multiple"))
A1295: 2022-05-26 | B1295: 19:45 | C1295: 2968 | D1295: 0 | E1295: 38077 | J1295: =IF(F1295="","none",IF(G1295=1,"carte","multiple"))
A1296: 2022-05-26 | B1296: 19:45 | C1296: 2968 | D1296: 0 | E1296: 38078 | J1296: =IF(F1296="","none",IF(G1296=1,"carte","multiple"))
A1297: 2022-05-26 | B1297: 20:13 | C1297: 2968 | D1297: 5.8 | E1297: 38079 | F1297: 5.8 | G1297: 1 | H1297: =ROUND(G1297*F1297,2) | I1297: =IF(ROUND(H1297-D1297,2)=0,1,0) | J1297: =IF(F1297="","none",IF(G1297=1,"carte","multiple"))
A1298: 2022-05-27 | B1298: 11:10 | C1298: 2969 | D1298: 6.5 | E1298: 38082 | F1298: 6.5 | G1298: 1 | H1298: =ROUND(G1298*F1298,2) | I1298: =IF(ROUND(H1298-D1298,2)=0,1,0) | J1298: =IF(F1298="","none",IF(G1298=1,"carte","multiple"))
A1299: 2022-05-27 | B1299: 11:10 | C1299: 2969 | D1299: 7.2 | E1299: 38083 | F1299: 7.2 | G1299: 1 | H1299: =ROUND(G1299*F1299,2) | I1299: =IF(ROUND(H1299-D1299,2)=0,1,0) | J1299: =IF(F1299="","none",IF(G1299=1,"carte","multiple"))
A1300: 2022-05-27 | B1300: 11:30 | C1300: 2969 | D1300: 14.4 | E1300: 38084 | F1300: 0.4 | G1300: 36 | H1300: =ROUND(G1300*F1300,2) | I1300: =IF(ROUND(H1300-D1300,2)=0,1,0) | J1300: =IF(F1300="","none",IF(G1300=1,"carte","multiple"))
A1301: 2022-05-27 | B1301: 11:30 | C1301: 2969 | D1301: 33.6 | E1301: 38085 | F1301: 33.6 | G1301: 1 | H1301: =ROUND(G1301*F1301,2) | I1301: =IF(ROUND(H1301-D1301,2)=0,1,0) | J1301: =IF(F1301="","none",IF(G1301=1,"carte","multiple"))
A1302: 2022-05-27 | B1302: 11:30 | C1302: 2969 | D1302: 13 | E1302: 38086 | F1302: 13 | G1302: 1 | H1302: =ROUND(G1302*F1302,2) | I1302: =IF(ROUND(H1302-D1302,2)=0,1,0) | J1302: =IF(F1302="","none",IF(G1302=1,"carte","multiple"))
A1303: 2022-05-27 | B1303: 11:30 | C1303: 2969 | D1303: 3.9 | E1303: 38087 | F1303: 3.9 | G1303: 1 | H1303: =ROUND(G1303*F1303,2) | I1303: =IF(ROUND(H1303-D1303,2)=0,1,0) | J1303: =IF(F1303="","none",IF(G1303=1,"carte","multiple"))
A1304: 2022-05-27 | B1304: 11:30 | C1304: 2969 | D1304: 1.8 | E1304: 38088 | F1304: 1.8 | G1304: 1 | H1304: =ROUND(G1304*F1304,2) | I1304: =IF(ROUND(H1304-D1304,2)=0,1,0) | J1304: =IF(F1304="","none",IF(G1304=1,"carte","multiple"))
A1305: 2022-05-27 | B1305: 11:30 | C1305: 2969 | D1305: 10.5 | E1305: 38089 | F1305: 10.5 | G1305: 1 | H1305: =ROUND(G1305*F1305,2) | I1305: =IF(ROUND(H1305-D1305,2)=0,1,0) | J1305: =IF(F1305="","none",IF(G1305=1,"carte","multiple"))
A1306: 2022-05-27 | B1306: 11:50 | C1306: 2969 | D1306: 3.9 | E1306: 38090 | F1306: 3.9 | G1306: 1 | H1306: =ROUND(G1306*F1306,2) | I1306: =IF(ROUND(H1306-D1306,2)=0,1,0) | J1306: =IF(F1306="","none",IF(G1306=1,"carte","multiple"))
A1307: 2022-05-27 | B1307: 12:23 | C1307: 2969 | D1307: 6.4 | E1307: 38091 | F1307: 6.4 | G1307: 1 | H1307: =ROUND(G1307*F1307,2) | I1307: =IF(ROUND(H1307-D1307,2)=0,1,0) | J1307: =IF(F1307="","none",IF(G1307=1,"carte","multiple"))
A1308: 2022-05-27 | B1308: 12:23 | C1308: 2969 | D1308: 2.2 | E1308: 38092 | F1308: 2.2 | G1308: 1 | H1308: =ROUND(G1308*F1308,2) | I1308: =IF(ROUND(H1308-D1308,2)=0,1,0) | J1308: =IF(F1308="","none",IF(G1308=1,"carte","multiple"))
... A1442: 2022-06-01 | B1442: 12:25 | C1442: 2972 | D1442: 8.8 | E1442: 38235 | F1442: 8.8 | G1442: 1 | H1442: =ROUND(G1442*F1442,2) | I1442: =IF(ROUND(H1442-D1442,2)=0,1,0) | J1442: =IF(F1442="","none",IF(G1442=1,"carte","multiple"))
A1443: 2022-06-01 | B1443: 12:25 | C1443: 2972 | D1443: 2.6 | E1443: 38236 | J1443: =IF(F1443="","none",IF(G1443=1,"carte","multiple"))
A1444: 2022-06-01 | B1444: 12:25 | C1444: 2972 | D1444: 1.8 | E1444: 38237 | F1444: 1.8 | G1444: 1 | H1444: =ROUND(G1444*F1444,2) | I1444: =IF(ROUND(H1444-D1444,2)=0,1,0) | J1444: =IF(F1444="","none",IF(G1444=1,"carte","multiple"))
A1445: 2022-06-01 | B1445: 12:25 | C1445: 2972 | D1445: 4.2 | E1445: 38238 | F1445: 4.2 | G1445: 1 | H1445: =ROUND(G1445*F1445,2) | I1445: =IF(ROUND(H1445-D1445,2)=0,1,0) | J1445: =IF(F1445="","none",IF(G1445=1,"carte","multiple"))
A1446: 2022-06-01 | B1446: 12:45 | C1446: 2972 | D1446: 4 | E1446: 38239 | F1446: 4 | G1446: 1 | H1446: =ROUND(G1446*F1446,2) | I1446: =IF(ROUND(H1446-D1446,2)=0,1,0) | J1446: =IF(F1446="","none",IF(G1446=1,"carte","multiple"))
A1447: 2022-06-01 | B1447: 12:45 | C1447: 2972 | D1447: 2 | E1447: 38240 | F1447: 2 | G1447: 1 | H1447: =ROUND(G1447*F1447,2) | I1447: =IF(ROUND(H1447-D1447,2)=0,1,0) | J1447: =IF(F1447="","none",IF(G1447=1,"carte","multiple"))
A1448: 2022-06-01 | B1448: 12:45 | C1448: 2972 | D1448: 27.8 | E1448: 38241 | F1448: 27.8 | G1448: 1 | H1448: =ROUND(G1448*F1448,2) | I1448: =IF(ROUND(H1448-D1448,2)=0,1,0) | J1448: =IF(F1448="","none",IF(G1448=1,"carte","multiple"))
A1449: 2022-06-01 | B1449: 12:45 | C1449: 2972 | D1449: 46 | E1449: 38242 | F1449: 0.4 | G1449: 115 | H1449: =ROUND(G1449*F1449,2) | I1449: =IF(ROUND(H1449-D1449,2)=0,1,0) | J1449: =IF(F1449="","none",IF(G1449=1,"carte","multiple"))
A1450: 2022-06-01 | B1450: 12:45 | C1450: 2972 | D1450: 3.9 | E1450: 38243 | F1450: 3.9 | G1450: 1 | H1450: =ROUND(G1450*F1450,2) | I1450: =IF(ROUND(H1450-D1450,2)=0,1,0) | J1450: =IF(F1450="","none",IF(G1450=1,"carte","multiple"))
A1451: 2022-06-01 | B1451: 18:50 | C1451: 2972 | D1451: 2.9 | E1451: 38245 | F1451: 2.9 | G1451: 1 | H1451: =ROUND(G1451*F1451,2) | I1451: =IF(ROUND(H1451-D1451,2)=0,1,0) | J1451: =IF(F1451="","none",IF(G1451=1,"carte","multiple"))
A1452: 2022-06-01 | B1452: 18:50 | C1452: 2972 | D1452: 14 | E1452: 38246 | F1452: 14 | G1452: 1 | H1452: =ROUND(G1452*F1452,2) | I1452: =IF(ROUND(H1452-D1452,2)=0,1,0) | J1452: =IF(F1452="","none",IF(G1452=1,"carte","multiple"))
...
